Workbook

Sheet Cover
A1: TXN GTM Qualification Matrix
A2: Version 0.7 | 19 August 2026 | Owner: I. Johnson
A4: Purpose
A5: Named Account List register and CRM staging layer for the TXN prospecting motion. Carries the ICP v0.3 Section 8 scoring formulas, tier assignments, contacts, triggers, activities, meetings, and the suppression list. Operates as the operational system of record until Freshsales configuration is complete, then transitions to the scoring engine role while Freshsales owns the operational data.
A10: Change log
A11: Version | B11: Date | C11: Description
A12: 0.1 | B12: 22/04/2026 | C12: Initial version.
A13: 0.2 | B13: 01/05/2026 | C13: Formula corrections; expanded reference tabs.
A14: 0.3 | B14: 13/07/2026 | C14: Extended to full CRM staging layer: 06_Activities, 07_Meetings, 08_Suppression_List, 09_Freshsales_Field_Map. Manual P1-P10 score entry.
A15: 0.4 | B15: 13/07/2026 | C15: Auto-scoring. 02_Scoring_Register rebuilt with 20 input columns and 10 auto-scoring formulas via VLOOKUPs and nested IFs against a new Scoring_Lookups tab. Added Licence Type, Funding Stage, Last Raise Date, BIN Sponsor Status, Tech Stack Profile, Cards In Issue, Cards Projected 18mo, Multi-Product Roadmap, Incumbent Locked. Incumbent Processor now a dropdown. Scoring Rationale auto-composes from the input plus score of each parameter. Field Map updated to reflect the new inputs and their proposed Freshsales targets.
A16: 0.6 | B16: 19/08/2026 | C16: Added Card Program Category input column at AQ. Four canonical categories (Consumer, Commercial and B2B, Disbursement and Payout, Vertical-specialist) per Card-Program-Categories.docx (07_GTM/04_Sales_Motion/Assets/Pipeline/). All 99 existing accounts classified with best-effort primary Category. Additional Categories for accounts running multiple programs captured in Trigger Notes. Owner should validate categorisation before Stage 3.
A17: Sheet map
A18: Sheet | B18: Purpose | C18: Foreign keys
A19: 01_Parameter_Reference | B19: ICP v0.3 Section 8.1 scoring parameter definitions. | C19: None
A20: 02_Scoring_Register | B20: Accounts with auto-scored tiers. Input columns C-U; calculated V-AN. | C20: None (Account_ID is the primary key)
A21: 03_Contacts | B21: One row per named contact. | C21: Account_ID → 02
A22: 04_Triggers | B22: One row per detected trigger event. P6 formula counts against this tab. | C22: Account_ID → 02
A23: 05_Audit_Log | B23: One row per refresh run or material action. | C23: None
A24: 06_Activities | B24: Per-send log: outbound emails, LinkedIn touches, replies. | C24: Account_ID → 02, Contact_ID → 03
A25: 07_Meetings | B25: Scheduled and completed meetings. | C25: Account_ID → 02, Contact_ID → 03
A26: 08_Suppression_List | B26: Permanent opt-outs, bounces, GDPR erasures. | C26: Contact_ID → 03 (optional)
A27: 09_Freshsales_Field_Map | B27: Column-to-Freshsales field mapping for import. | C27: None (reference)
A28: Anti_Profile_Reference | B28: ICP v0.3 Section 7 anti-profile checklist. | C28: None (reference)
A29: Tier_Definitions | B29: ICP v0.3 Section 8.3 and 8.4 tier definitions and actions. | C29: None (reference)
... A32: 0.7 | B32: 19/08/2026 | C32: Added 10_Watch_List tab for very early-stage fintechs (pre-Series-A, pre-launch). Signal-driven, not scored. Populated with 20 candidates from the first monthly scan. Per Prospecting Process v0.6 Section 4.1.5. Promote-to-Prospect trigger criteria per row. Owner reviews weekly; monthly Claude scan runs on first working day of each month.

Sheet 01_Parameter_Reference
A1: ICP v0.3 Section 8.1 Scoring Parameters
A2: Ten parameters, 100 points max. Bands and their point values. Auto-scored from Scoring_Lookups.
A4: # | B4: Parameter | C4: Source | D4: Max | E4: Band P1 | F4: Band P2 | G4: Band P3 | H4: Band DQ
A5: 1 | B5: Sub-sector / Use Case Fit | C5: Sec 4.2 | D5: 10 | E5: 10: Digital Banking, Neobank | F5: 7: Expense Mgmt, Lending (SMB/Consumer), BaaS, FX | G5: 4: Investment Mgmt, Disbursement, Payments, Ecommerce, Retail, Gift Card, Crypto | H5: 0: Outside listed sub-sectors
A6: 2 | B6: Company Size (employees) | C6: Sec 4.3 | D6: 10 | E6: 10: 50 to 1,000 | F6: 7: 20 to 49 or 1,001 to 2,000 | G6: 4: 10 to 19 or 2,001 to 5,000 | H6: 0: Below 10 or above 5,000
A7: 3 | B7: Geography / Region Phase | C7: Sec 4.4 | D7: 12 | E7: 12: MVP (PL, CZ, RO, HU) | F7: 8: Phase 1a/1b (ES, PT, GR, NL, BE, AT, UK) | G7: 5: Rest of EEA | H7: 0: Outside EEA + UK
A8: 4 | B8: Regulatory Licence Status | C8: Sec 4.5 | D8: 8 | E8: 8: EMI, Credit Institution, Scheme Principal | F8: 6: PI, EMI Applied, BIN Sponsor In Place | G8: 3: No Licence + BIN Sponsor Engaged, Secondary Regime | H8: 0: Unlicensed no Sponsor, Revoked, Sanctions
A9: 5 | B9: Ownership and Funding Stage | C9: Sec 4.6 | D9: 8 | E9: 8: Series B-D last raise <24mo; PE Growth; Listed Growth | F9: 6: Series A; Bootstrapped Profitable; PE Stable; Series B-D >24mo | G9: 3: Seed; Bootstrapped; Listed Stable | H9: 0: Administration, Insolvency, Wind-down
A10: 6 | B10: Behavioural / Situational Triggers | C10: Sec 5 | D10: 20 | E10: 20: Two or more active triggers within 12mo | F10: 14: One strong (High priority) active trigger | G10: 7: One weak/historical trigger, or one 12-36mo old | H10: 0: Incumbent Locked = Yes (multi-year contract signed <12mo)
A11: 7 | B11: Incumbent Processor Signal | C11: Sec 6 | D11: 8 | E11: 8: Marqeta, Paymentology, Thredd, Enfuce, Episode Six, Pismo, Legacy (named), In-house Legacy | F11: 6: Smaller/less-known processor; Hybrid in-house | G11: 3: Card program running; incumbent unknown | H11: 0: No card program
A12: 8 | B12: Tech Stack and Engineering | C12: Sec 6 | D12: 6 | E12: 6: Cloud-native (AWS/Azure/GCP), API-first, AI signals | F12: 4: Cloud modern, Not API-first | G12: 2: Hybrid stack, limited signals | H12: 0: On-prem or No in-house engineering
A13: 9 | B13: Scheme / BIN Sponsor Signal | C13: Sec 6 | D13: 8 | E13: 8: Existing BIN Sponsor Relationship; Scheme Principal | F13: 6: Scheme Participation Visible (Apple/Google Pay, 3DS) | G13: 3: No Sponsor, Licensing Suggests Imminent | H13: 0: No Scheme Participation Path
A14: 10 | B14: Card Program Scale and Ambition | C14: Sec 3, 4 | D14: 10 | E14: 10: 500k+ cards or Multi-Product Roadmap | F14: 7: 100k-500k cards | G14: 4: 10k-100k cards | H14: 0: <10k cards or staff-card only

Sheet Scoring_Lookups
A1: Scoring Lookups (used by auto-scoring formulas)
A2: Keyed tables referenced by VLOOKUP formulas in 02_Scoring_Register. Do not rename columns or move rows without updating the formulas.
A4: Sub-sector | B4: P1 Score | D4: Country | E4: P3 Score | G4: Licence Type | H4: P4 Score | J4: Incumbent Processor | K4: P7 Score | M4: Tech Stack Profile | N4: P8 Score | P4: BIN Sponsor Status | Q4: P9 Score
A5: Digital Banking | B5: 10 | D5: Poland | E5: 12 | G5: EMI Licence | H5: 8 | J5: Marqeta | K5: 8 | M5: Cloud-native (AWS/Azure/GCP), API-first, AI signals | N5: 6 | P5: Existing BIN Sponsor Relationship | Q5: 8
A6: Neobank | B6: 10 | D6: Czech Republic | E6: 12 | G6: Credit Institution Licence | H6: 8 | J6: Paymentology | K6: 8 | M6: Cloud modern, Not API-first | N6: 4 | P6: Scheme Principal | Q6: 8
A7: Expense Management | B7: 7 | D7: Romania | E7: 12 | G7: Scheme Principal Member | H7: 8 | J7: Thredd | K7: 8 | M7: Hybrid stack, limited signals | N7: 2 | P7: Scheme Participation Visible | Q7: 6
A8: Lending (SMB) | B8: 7 | D8: Hungary | E8: 12 | G8: PI Licence | H8: 6 | J8: Enfuce | K8: 8 | M8: On-prem or No in-house engineering | N8: 0 | P8: No Sponsor, Licensing Suggests Imminent | Q8: 3
A9: Lending (Consumer) | B9: 7 | D9: Spain | E9: 8 | G9: EMI Licence In Application | H9: 6 | J9: Episode Six | K9: 8 | P9: No Scheme Participation Path | Q9: 0
A10: FX Payments | B10: 7 | D10: Portugal | E10: 8 | G10: BIN Sponsor Agreement In Place | H10: 6 | J10: Pismo | K10: 8
A11: BaaS | B11: 7 | D11: Greece | E11: 8 | G11: No Licence, BIN Sponsor Engaged | H11: 3 | J11: Legacy Processor (Named) | K11: 8
A12: Investment Management | B12: 4 | D12: Netherlands | E12: 8 | G12: Secondary Regime | H12: 3 | J12: In-house Legacy Processor | K12: 8
A13: Disbursement | B13: 4 | D13: Belgium | E13: 8 | G13: Unlicensed, No Sponsor | H13: 0 | J13: Smaller/Less-known Processor | K13: 6
A14: Payments | B14: 4 | D14: Austria | E14: 8 | G14: Licence Revoked | H14: 0 | J14: Hybrid In-house Solution | K14: 6
A15: Ecommerce | B15: 4 | D15: United Kingdom | E15: 8 | G15: Sanctions Exposure | H15: 0 | J15: Planning to Launch (No Incumbent Yet) | K15: 4
A16: Retail | B16: 4 | D16: France | E16: 5 | J16: Incumbent Unknown | K16: 3
A17: Gift Card | B17: 4 | D17: Germany | E17: 5 | J17: No Card Program, No Plan | K17: 0
A18: Crypto | B18: 4 | D18: Italy | E18: 5
D19: Ireland | E19: 5
D20: Norway | E20: 5
D21: Sweden | E21: 5
D22: Finland | E22: 5
D23: Denmark | E23: 5
D24: Iceland | E24: 5
D25: Luxembourg | E25: 5
D26: Malta | E26: 5
D27: Cyprus | E27: 5
D28: Slovakia | E28: 5
D29: Slovenia | E29: 5
D30: Bulgaria | E30: 5
... D35: Liechtenstein | E35: 5

Sheet 02_Scoring_Register
A1: Scoring Register (Accounts) - AUTO-SCORED
A2: Input columns C to U. Auto-scored V to AE. Total, gating, and tier resolve automatically. Do not overwrite the scoring formulas.
A4: Account_ID | B4: Name | C4: Country | D4: Sector | E4: Sub-sector | F4: Employees | G4: Licence Type | H4: Ownership Model | I4: Funding Stage | J4: Last Raise Date | K4: BIN Sponsor Name | L4: BIN Sponsor Status | M4: Incumbent Processor | N4: Incumbent Locked | O4: Tech Stack Profile | P4: Cards In Issue | Q4: Cards Projected 18mo | R4: Multi-Product Roadmap | S4: Discovery Source | T4: Discovery Date | U4: Trigger Notes | V4: P1 Sub-sector | W4: P2 Size | X4: P3 Geo | Y4: P4 Licence | Z4: P5 Ownership | AA4: P6 Triggers | AB4: P7 Incumbent | AC4: P8 TechStack | AD4: P9 Scheme | AE4: P10 Ambition | AF4: Total Score | AG4: Gating Flag | AH4: Anti-Profile Hit | AI4: Tier | AJ4: Scoring Rationale | AK4: Last Scored Date | AL4: Status | AM4: Freshsales_Ready | AN4: Freshsales_ID | AO4: Card Program Target Date | AP4: Timing Fit | AQ4: Card Program Category
A5: ACC-PL-001 | B5: Paymove | C5: Poland | D5: FinTech | E5: Payments | F5: 25 | G5: PI Licence | H5: VC-backed | I5: Seed | J5: 46183 | K5: TBD | L5: No Sponsor, Licensing Suggests Imminent | M5: Planning to Launch (No Incumbent Yet) | N5: No | O5: Cloud-native (AWS/Azure/GCP), API-first, AI signals | P5: 0 | Q5: 50000 | R5: Unknown | S5: Second-pass agent research | T5: 46216 | U5: EUR 2.12M seed 10 Jun 2026; agentic AI payments infrastructure; 600k users, 2k locations; expanding ES/PT/IT | V5: =IF(E5="","",IFERROR(VLOOKUP(E5,Scoring_Lookups!$A$5:$B$18,2,FALSE()),0)) -> 4 | W5: =IF(F5="","",IF(AND(F5>=50,F5<=1000),10,IF(OR(AND(F5>=20,F5<=49),AND(F5>=1001,F5<=2000)),7,IF(OR(AND(F5>=10,F5<=19),AND(F5>=2001,F5<=5000)),4,0)))) -> 7 | X5: =IF(C5="","",IFERROR(VLOOKUP(C5,Scoring_Lookups!$D$5:$E$35,2,FALSE()),0)) -> 12 | Y5: =IF(G5="","",IFERROR(VLOOKUP(G5,Scoring_Lookups!$G$5:$H$16,2,FALSE()),0)) -> 6 | Z5: =IF(I5="","",IF(OR(I5="Administration/Insolvency",I5="Pending Wind-down",I5="Sanctions Exposure"),0,IF(OR(AND(OR(I5="Series B",I5="Series C",I5="Series D+"),J5<>"",J5>=TODAY()-730),I5="PE-controlled Growth Mandate",I5="Listed with Growth Profile"),8,IF(OR(I5="Series A",I5="Bootstrapped Profitable",I5="PE-controlled Stable",AND(OR(I5="Series B",I5="Series C",I5="Series D+"),J5<>"",J5<TODAY()-730)),6,IF(OR(I5="Seed",I5="Bootstrapped",I5="Listed Stable",I5="Established Private Flat"),3,0))))) -> 3 | AA5: =IF(N5="Yes",0,IF(A5="",0,IF(COUNTIFS('04_Triggers'!B:B,A5,'04_Triggers'!D:D,">="&(TODAY()-365))>=2,20,IF(COUNTIFS('04_Triggers'!B:B,A5,'04_Triggers'!D:D,">="&(TODAY()-365),'04_Triggers'!G:G,"High")>=1,14,IF(COUNTIFS('04_Triggers'!B:B,A5,'04_Triggers'!D:D,">="&(TODAY()-365))>=1,7,IF(COUNTIFS('04_Triggers'!B:B,A5,'04_Triggers'!D:D,">="&(TODAY()-1095),'04_Triggers'!D:D,"<"&(TODAY()-365))>=1,7,0)))))) -> 20 | AB5: =IF(M5="","",IFERROR(VLOOKUP(M5,Scoring_Lookups!$J$5:$K$16,2,FALSE()),0)) -> 4 | AC5: =IF(O5="","",IFERROR(VLOOKUP(O5,Scoring_Lookups!$M$5:$N$8,2,FALSE()),0)) -> 6 | AD5: =IF(L5="","",IFERROR(VLOOKUP(L5,Scoring_Lookups!$P$5:$Q$9,2,FALSE()),0)) -> 3 | AE5: =IF(AND(P5="",Q5="",R5=""),"",IF(OR(IFERROR(MAX(P5,Q5),0)>=500000,R5="Yes"),10,IF(IFERROR(MAX(P5,Q5),0)>=100000,7,IF(IFERROR(MAX(P5,Q5),0)>=10000,4,0)))) -> 4 | AF5: =IFERROR(N(V5)+N(W5)+N(X5)+N(Y5)+N(Z5)+N(AA5)+N(AB5)+N(AC5)+N(AD5)+N(AE5),0) -> 69 | AG5: =IF(OR(E5="",C5="",G5=""),"Not scored",IF(OR(V5=0,X5=0,Y5=0,N5="Yes"),"DQ Gating","OK")) -> OK | AH5: No | AI5: =IF(AG5="Not scored","",IF(OR(AG5="DQ Gating",AH5="Yes"),"Disqualified",IF(AF5>=80,"Priority 1",IF(AF5>=60,"Priority 2",IF(AF5>=40,"Priority 3","Disqualified"))))) -> Priority 2 | AJ5: =IF(AG5="Not scored","","P1 "&IF(E5="","?",E5)&"="&V5&" | P2 "&IF(F5="","?",F5)&"="&W5&" | P3 "&IF(C5="","?",C5)&"="&X5&" | P4 "&IF(G5="","?",G5)&"="&Y5&" | P5 "&IF(I5="","?",I5)&"="&Z5&" | P6="&AA5&" | P7 "&IF(M5="","?",M5)&"="&AB5&" | P8 "&IF(O5="","?",O5)&"="&AC5&" | P9 "&IF(L5="","?",L5)&"="&AD5&" | P10="&AE5) -> P1 Payments=4 | P2 25=7 | P3 Poland=12 | P4 PI Licence=6 | P5 Seed=3 | P6=20 | P7 Planning to Launch (No Incumbent Yet)=4 | P8 Cloud-native (AWS/Azure/GCP), API-first, AI signals=6 | P9 No Sponsor, Licensing Suggests Imminent=3 | P10=4 | AL5: Prospect | AM5: No | AO5: Q2 2027 | AP5: =IF(AO5="","Not set",IF(OR(AO5="Q1 2027",AO5="Q2 2027",AO5="Q3 2027",AO5="Q4 2027",AO5="Live, Migration Window"),"OK",IF(AO5="Live, Urgent Need","Deferred","Watch"))) -> OK | AQ5: Commercial and B2B
A6: ACC-PL-002 | B6: PragmaGO | C6: Poland | D6: FinTech | E6: Lending (SMB) | F6: 81 | G6: BIN Sponsor Agreement In Place | H6: Private | I6: Bootstrapped Profitable | K6: TBD | L6: No Sponsor, Licensing Suggests Imminent | M6: Planning to Launch (No Incumbent Yet) | N6: No | O6: Cloud modern, Not API-first | P6: 0 | Q6: 200000 | R6: Yes | S6: Second-pass agent research | T6: 46216 | U6: FT1000 Europe Fastest-Growing 2026 (only Polish financial entry); Q1 embedded finance +35% YoY; expanded ES/HR/RO early 2026 | V6: =IF(E6="","",IFERROR(VLOOKUP(E6,Scoring_Lookups!$A$5:$B$18,2,FALSE()),0)) -> 7 | W6: =IF(F6="","",IF(AND(F6>=50,F6<=1000),10,IF(OR(AND(F6>=20,F6<=49),AND(F6>=1001,F6<=2000)),7,IF(OR(AND(F6>=10,F6<=19),AND(F6>=2001,F6<=5000)),4,0)))) -> 10 | X6: =IF(C6="","",IFERROR(VLOOKUP(C6,Scoring_Lookups!$D$5:$E$35,2,FALSE()),0)) -> 12 | Y6: =IF(G6="","",IFERROR(VLOOKUP(G6,Scoring_Lookups!$G$5:$H$16,2,FALSE()),0)) -> 6 | Z6: =IF(I6="","",IF(OR(I6="Administration/Insolvency",I6="Pending Wind-down",I6="Sanctions Exposure"),0,IF(OR(AND(OR(I6="Series B",I6="Series C",I6="Series D+"),J6<>"",J6>=TODAY()-730),I6="PE-controlled Growth Mandate",I6="Listed with Growth Profile"),8,IF(OR(I6="Series A",I6="Bootstrapped Profitable",I6="PE-controlled Stable",AND(OR(I6="Series B",I6="Series C",I6="Series D+"),J6<>"",J6<TODAY()-730)),6,IF(OR(I6="Seed",I6="Bootstrapped",I6="Listed Stable",I6="Established Private Flat"),3,0))))) -> 6 | AA6: =IF(N6="Yes",0,IF(A6="",0,IF(COUNTIFS('04_Triggers'!B:B,A6,'04_Triggers'!D:D,">="&(TODAY()-365))>=2,20,IF(COUNTIFS('04_Triggers'!B:B,A6,'04_Triggers'!D:D,">="&(TODAY()-365),'04_Triggers'!G:G,"High")>=1,14,IF(COUNTIFS('04_Triggers'!B:B,A6,'04_Triggers'!D:D,">="&(TODAY()-365))>=1,7,IF(COUNTIFS('04_Triggers'!B:B,A6,'04_Triggers'!D:D,">="&(TODAY()-1095),'04_Triggers'!D:D,"<"&(TODAY()-365))>=1,7,0)))))) -> 20 | AB6: =IF(M6="","",IFERROR(VLOOKUP(M6,Scoring_Lookups!$J$5:$K$16,2,FALSE()),0)) -> 4 | AC6: =IF(O6="","",IFERROR(VLOOKUP(O6,Scoring_Lookups!$M$5:$N$8,2,FALSE()),0)) -> 4 | AD6: =IF(L6="","",IFERROR(VLOOKUP(L6,Scoring_Lookups!$P$5:$Q$9,2,FALSE()),0)) -> 3 | AE6: =IF(AND(P6="",Q6="",R6=""),"",IF(OR(IFERROR(MAX(P6,Q6),0)>=500000,R6="Yes"),10,IF(IFERROR(MAX(P6,Q6),0)>=100000,7,IF(IFERROR(MAX(P6,Q6),0)>=10000,4,0)))) -> 10 | AF6: =IFERROR(N(V6)+N(W6)+N(X6)+N(Y6)+N(Z6)+N(AA6)+N(AB6)+N(AC6)+N(AD6)+N(AE6),0) -> 82 | AG6: =IF(OR(E6="",C6="",G6=""),"Not scored",IF(OR(V6=0,X6=0,Y6=0,N6="Yes"),"DQ Gating","OK")) -> OK | AH6: No | AI6: =IF(AG6="Not scored","",IF(OR(AG6="DQ Gating",AH6="Yes"),"Disqualified",IF(AF6>=80,"Priority 1",IF(AF6>=60,"Priority 2",IF(AF6>=40,"Priority 3","Disqualified"))))) -> Priority 1 | AJ6: =IF(AG6="Not scored","","P1 "&IF(E6="","?",E6)&"="&V6&" | P2 "&IF(F6="","?",F6)&"="&W6&" | P3 "&IF(C6="","?",C6)&"="&X6&" | P4 "&IF(G6="","?",G6)&"="&Y6&" | P5 "&IF(I6="","?",I6)&"="&Z6&" | P6="&AA6&" | P7 "&IF(M6="","?",M6)&"="&AB6&" | P8 "&IF(O6="","?",O6)&"="&AC6&" | P9 "&IF(L6="","?",L6)&"="&AD6&" | P10="&AE6) -> P1 Lending (SMB)=7 | P2 81=10 | P3 Poland=12 | P4 BIN Sponsor Agreement In Place=6 | P5 Bootstrapped Profitable=6 | P6=20 | P7 Planning to Launch (No Incumbent Yet)=4 | P8 Cloud modern, Not API-first=4 | P9 No Sponsor, Licensing Suggests Imminent=3 | P10=10 | AL6: Prospect | AM6: No | AO6: Q3 2027 | AP6: =IF(AO6="","Not set",IF(OR(AO6="Q1 2027",AO6="Q2 2027",AO6="Q3 2027",AO6="Q4 2027",AO6="Live, Migration Window"),"OK",IF(AO6="Live, Urgent Need","Deferred","Watch"))) -> OK | AQ6: Commercial and B2B
A7: ACC-PL-003 | B7: BanqUP | C7: Poland | D7: FinTech | E7: BaaS | F7: 750 | G7: PI Licence | H7: Private | I7: Bootstrapped Profitable | K7: TBD | L7: Existing BIN Sponsor Relationship | M7: Planning to Launch (No Incumbent Yet) | N7: No | O7: Cloud-native (AWS/Azure/GCP), API-first, AI signals | P7: 0 | Q7: 100000 | R7: Yes | S7: Second-pass agent research | T7: 46216 | U7: Feb 2026 Visa strategic partnership (Visa Direct plus Commercial Solutions); iPiD Verification-of-Payee integration; Polish engineering base; SME BaaS focus | V7: =IF(E7="","",IFERROR(VLOOKUP(E7,Scoring_Lookups!$A$5:$B$18,2,FALSE()),0)) -> 7 | W7: =IF(F7="","",IF(AND(F7>=50,F7<=1000),10,IF(OR(AND(F7>=20,F7<=49),AND(F7>=1001,F7<=2000)),7,IF(OR(AND(F7>=10,F7<=19),AND(F7>=2001,F7<=5000)),4,0)))) -> 10 | X7: =IF(C7="","",IFERROR(VLOOKUP(C7,Scoring_Lookups!$D$5:$E$35,2,FALSE()),0)) -> 12 | Y7: =IF(G7="","",IFERROR(VLOOKUP(G7,Scoring_Lookups!$G$5:$H$16,2,FALSE()),0)) -> 6 | Z7: =IF(I7="","",IF(OR(I7="Administration/Insolvency",I7="Pending Wind-down",I7="Sanctions Exposure"),0,IF(OR(AND(OR(I7="Series B",I7="Series C",I7="Series D+"),J7<>"",J7>=TODAY()-730),I7="PE-controlled Growth Mandate",I7="Listed with Growth Profile"),8,IF(OR(I7="Series A",I7="Bootstrapped Profitable",I7="PE-controlled Stable",AND(OR(I7="Series B",I7="Series C",I7="Series D+"),J7<>"",J7<TODAY()-730)),6,IF(OR(I7="Seed",I7="Bootstrapped",I7="Listed Stable",I7="Established Private Flat"),3,0))))) -> 6 | AA7: =IF(N7="Yes",0,IF(A7="",0,IF(COUNTIFS('04_Triggers'!B:B,A7,'04_Triggers'!D:D,">="&(TODAY()-365))>=2,20,IF(COUNTIFS('04_Triggers'!B:B,A7,'04_Triggers'!D:D,">="&(TODAY()-365),'04_Triggers'!G:G,"High")>=1,14,IF(COUNTIFS('04_Triggers'!B:B,A7,'04_Triggers'!D:D,">="&(TODAY()-365))>=1,7,IF(COUNTIFS('04_Triggers'!B:B,A7,'04_Triggers'!D:D,">="&(TODAY()-1095),'04_Triggers'!D:D,"<"&(TODAY()-365))>=1,7,0)))))) -> 20 | AB7: =IF(M7="","",IFERROR(VLOOKUP(M7,Scoring_Lookups!$J$5:$K$16,2,FALSE()),0)) -> 4 | AC7: =IF(O7="","",IFERROR(VLOOKUP(O7,Scoring_Lookups!$M$5:$N$8,2,FALSE()),0)) -> 6 | AD7: =IF(L7="","",IFERROR(VLOOKUP(L7,Scoring_Lookups!$P$5:$Q$9,2,FALSE()),0)) -> 8 | AE7: =IF(AND(P7="",Q7="",R7=""),"",IF(OR(IFERROR(MAX(P7,Q7),0)>=500000,R7="Yes"),10,IF(IFERROR(MAX(P7,Q7),0)>=100000,7,IF(IFERROR(MAX(P7,Q7),0)>=10000,4,0)))) -> 10 | AF7: =IFERROR(N(V7)+N(W7)+N(X7)+N(Y7)+N(Z7)+N(AA7)+N(AB7)+N(AC7)+N(AD7)+N(AE7),0) -> 89 | AG7: =IF(OR(E7="",C7="",G7=""),"Not scored",IF(OR(V7=0,X7=0,Y7=0,N7="Yes"),"DQ Gating","OK")) -> OK | AH7: No | AI7: =IF(AG7="Not scored","",IF(OR(AG7="DQ Gating",AH7="Yes"),"Disqualified",IF(AF7>=80,"Priority 1",IF(AF7>=60,"Priority 2",IF(AF7>=40,"Priority 3","Disqualified"))))) -> Priority 1 | AJ7: =IF(AG7="Not scored","","P1 "&IF(E7="","?",E7)&"="&V7&" | P2 "&IF(F7="","?",F7)&"="&W7&" | P3 "&IF(C7="","?",C7)&"="&X7&" | P4 "&IF(G7="","?",G7)&"="&Y7&" | P5 "&IF(I7="","?",I7)&"="&Z7&" | P6="&AA7&" | P7 "&IF(M7="","?",M7)&"="&AB7&" | P8 "&IF(O7="","?",O7)&"="&AC7&" | P9 "&IF(L7="","?",L7)&"="&AD7&" | P10="&AE7) -> P1 BaaS=7 | P2 750=10 | P3 Poland=12 | P4 PI Licence=6 | P5 Bootstrapped Profitable=6 | P6=20 | P7 Planning to Launch (No Incumbent Yet)=4 | P8 Cloud-native (AWS/Azure/GCP), API-first, AI signals=6 | P9 Existing BIN Sponsor Relationship=8 | P10=10 | AL7: Prospect | AM7: No | AO7: Q2 2027 | AP7: =IF(AO7="","Not set",IF(OR(AO7="Q1 2027",AO7="Q2 2027",AO7="Q3 2027",AO7="Q4 2027",AO7="Live, Migration Window"),"OK",IF(AO7="Live, Urgent Need","Deferred","Watch"))) -> OK | AQ7: Commercial and B2B
A8: ACC-PL-004 | B8: Comperia (Comfino) | C8: Poland | D8: FinTech | E8: Payments | F8: 47 | G8: PI Licence | H8: Listed | I8: Listed Stable | K8: TBD | L8: No Sponsor, Licensing Suggests Imminent | M8: Planning to Launch (No Incumbent Yet) | N8: No | O8: Cloud modern, Not API-first | P8: 0 | Q8: 150000 | R8: Yes | S8: Second-pass agent research | T8: 46216 | U8: WSE-listed; new Comperia Pay subsidiary formed; Comfino BNPL +63% YoY Q1 2026; Cashless Fintech Project 2026 nominee | V8: =IF(E8="","",IFERROR(VLOOKUP(E8,Scoring_Lookups!$A$5:$B$18,2,FALSE()),0)) -> 4 | W8: =IF(F8="","",IF(AND(F8>=50,F8<=1000),10,IF(OR(AND(F8>=20,F8<=49),AND(F8>=1001,F8<=2000)),7,IF(OR(AND(F8>=10,F8<=19),AND(F8>=2001,F8<=5000)),4,0)))) -> 7 | X8: =IF(C8="","",IFERROR(VLOOKUP(C8,Scoring_Lookups!$D$5:$E$35,2,FALSE()),0)) -> 12 | Y8: =IF(G8="","",IFERROR(VLOOKUP(G8,Scoring_Lookups!$G$5:$H$16,2,FALSE()),0)) -> 6 | Z8: =IF(I8="","",IF(OR(I8="Administration/Insolvency",I8="Pending Wind-down",I8="Sanctions Exposure"),0,IF(OR(AND(OR(I8="Series B",I8="Series C",I8="Series D+"),J8<>"",J8>=TODAY()-730),I8="PE-controlled Growth Mandate",I8="Listed with Growth Profile"),8,IF(OR(I8="Series A",I8="Bootstrapped Profitable",I8="PE-controlled Stable",AND(OR(I8="Series B",I8="Series C",I8="Series D+"),J8<>"",J8<TODAY()-730)),6,IF(OR(I8="Seed",I8="Bootstrapped",I8="Listed Stable",I8="Established Private Flat"),3,0))))) -> 3 | AA8: =IF(N8="Yes",0,IF(A8="",0,IF(COUNTIFS('04_Triggers'!B:B,A8,'04_Triggers'!D:D,">="&(TODAY()-365))>=2,20,IF(COUNTIFS('04_Triggers'!B:B,A8,'04_Triggers'!D:D,">="&(TODAY()-365),'04_Triggers'!G:G,"High")>=1,14,IF(COUNTIFS('04_Triggers'!B:B,A8,'04_Triggers'!D:D,">="&(TODAY()-365))>=1,7,IF(COUNTIFS('04_Triggers'!B:B,A8,'04_Triggers'!D:D,">="&(TODAY()-1095),'04_Triggers'!D:D,"<"&(TODAY()-365))>=1,7,0)))))) -> 0 | AB8: =IF(M8="","",IFERROR(VLOOKUP(M8,Scoring_Lookups!$J$5:$K$16,2,FALSE()),0)) -> 4 | AC8: =IF(O8="","",IFERROR(VLOOKUP(O8,Scoring_Lookups!$M$5:$N$8,2,FALSE()),0)) -> 4 | AD8: =IF(L8="","",IFERROR(VLOOKUP(L8,Scoring_Lookups!$P$5:$Q$9,2,FALSE()),0)) -> 3 | AE8: =IF(AND(P8="",Q8="",R8=""),"",IF(OR(IFERROR(MAX(P8,Q8),0)>=500000,R8="Yes"),10,IF(IFERROR(MAX(P8,Q8),0)>=100000,7,IF(IFERROR(MAX(P8,Q8),0)>=10000,4,0)))) -> 10 | AF8: =IFERROR(N(V8)+N(W8)+N(X8)+N(Y8)+N(Z8)+N(AA8)+N(AB8)+N(AC8)+N(AD8)+N(AE8),0) -> 53 | AG8: =IF(OR(E8="",C8="",G8=""),"Not scored",IF(OR(V8=0,X8=0,Y8=0,N8="Yes"),"DQ Gating","OK")) -> OK | AH8: No | AI8: =IF(AG8="Not scored","",IF(OR(AG8="DQ Gating",AH8="Yes"),"Disqualified",IF(AF8>=80,"Priority 1",IF(AF8>=60,"Priority 2",IF(AF8>=40,"Priority 3","Disqualified"))))) -> Priority 3 | AJ8: =IF(AG8="Not scored","","P1 "&IF(E8="","?",E8)&"="&V8&" | P2 "&IF(F8="","?",F8)&"="&W8&" | P3 "&IF(C8="","?",C8)&"="&X8&" | P4 "&IF(G8="","?",G8)&"="&Y8&" | P5 "&IF(I8="","?",I8)&"="&Z8&" | P6="&AA8&" | P7 "&IF(M8="","?",M8)&"="&AB8&" | P8 "&IF(O8="","?",O8)&"="&AC8&" | P9 "&IF(L8="","?",L8)&"="&AD8&" | P10="&AE8) -> P1 Payments=4 | P2 47=7 | P3 Poland=12 | P4 PI Licence=6 | P5 Listed Stable=3 | P6=0 | P7 Planning to Launch (No Incumbent Yet)=4 | P8 Cloud modern, Not API-first=4 | P9 No Sponsor, Licensing Suggests Imminent=3 | P10=10 | AL8: Prospect | AM8: No | AO8: Q3 2027 | AP8: =IF(AO8="","Not set",IF(OR(AO8="Q1 2027",AO8="Q2 2027",AO8="Q3 2027",AO8="Q4 2027",AO8="Live, Migration Window"),"OK",IF(AO8="Live, Urgent Need","Deferred","Watch"))) -> OK | AQ8: Consumer
A9: ACC-PL-005 | B9: Wealthon | C9: Poland | D9: FinTech | E9: Lending (SMB) | F9: 80 | G9: PI Licence | H9: VC-backed | I9: Series A | J9: 45703 | K9: Vodeno-adjacent | L9: Existing BIN Sponsor Relationship | M9: Incumbent Unknown | N9: No | O9: Cloud modern, Not API-first | P9: 5000 | Q9: 50000 | R9: Yes | S9: First-pass agent research | T9: 46216 | U9: Feb 2025 PLN 531M raise (equity plus Fortress debt); Jul 2025 UniCredit receivables purchase to scale SME book to PLN 1B; Wealthon CARD live | V9: =IF(E9="","",IFERROR(VLOOKUP(E9,Scoring_Lookups!$A$5:$B$18,2,FALSE()),0)) -> 7 | W9: =IF(F9="","",IF(AND(F9>=50,F9<=1000),10,IF(OR(AND(F9>=20,F9<=49),AND(F9>=1001,F9<=2000)),7,IF(OR(AND(F9>=10,F9<=19),AND(F9>=2001,F9<=5000)),4,0)))) -> 10 | X9: =IF(C9="","",IFERROR(VLOOKUP(C9,Scoring_Lookups!$D$5:$E$35,2,FALSE()),0)) -> 12 | Y9: =IF(G9="","",IFERROR(VLOOKUP(G9,Scoring_Lookups!$G$5:$H$16,2,FALSE()),0)) -> 6 | Z9: =IF(I9="","",IF(OR(I9="Administration/Insolvency",I9="Pending Wind-down",I9="Sanctions Exposure"),0,IF(OR(AND(OR(I9="Series B",I9="Series C",I9="Series D+"),J9<>"",J9>=TODAY()-730),I9="PE-controlled Growth Mandate",I9="Listed with Growth Profile"),8,IF(OR(I9="Series A",I9="Bootstrapped Profitable",I9="PE-controlled Stable",AND(OR(I9="Series B",I9="Series C",I9="Series D+"),J9<>"",J9<TODAY()-730)),6,IF(OR(I9="Seed",I9="Bootstrapped",I9="Listed Stable",I9="Established Private Flat"),3,0))))) -> 6 | AA9: =IF(N9="Yes",0,IF(A9="",0,IF(COUNTIFS('04_Triggers'!B:B,A9,'04_Triggers'!D:D,">="&(TODAY()-365))>=2,20,IF(COUNTIFS('04_Triggers'!B:B,A9,'04_Triggers'!D:D,">="&(TODAY()-365),'04_Triggers'!G:G,"High")>=1,14,IF(COUNTIFS('04_Triggers'!B:B,A9,'04_Triggers'!D:D,">="&(TODAY()-365))>=1,7,IF(COUNTIFS('04_Triggers'!B:B,A9,'04_Triggers'!D:D,">="&(TODAY()-1095),'04_Triggers'!D:D,"<"&(TODAY()-365))>=1,7,0)))))) -> 7 | AB9: =IF(M9="","",IFERROR(VLOOKUP(M9,Scoring_Lookups!$J$5:$K$16,2,FALSE()),0)) -> 3 | AC9: =IF(O9="","",IFERROR(VLOOKUP(O9,Scoring_Lookups!$M$5:$N$8,2,FALSE()),0)) -> 4 | AD9: =IF(L9="","",IFERROR(VLOOKUP(L9,Scoring_Lookups!$P$5:$Q$9,2,FALSE()),0)) -> 8 | AE9: =IF(AND(P9="",Q9="",R9=""),"",IF(OR(IFERROR(MAX(P9,Q9),0)>=500000,R9="Yes"),10,IF(IFERROR(MAX(P9,Q9),0)>=100000,7,IF(IFERROR(MAX(P9,Q9),0)>=10000,4,0)))) -> 10 | AF9: =IFERROR(N(V9)+N(W9)+N(X9)+N(Y9)+N(Z9)+N(AA9)+N(AB9)+N(AC9)+N(AD9)+N(AE9),0) -> 73 | AG9: =IF(OR(E9="",C9="",G9=""),"Not scored",IF(OR(V9=0,X9=0,Y9=0,N9="Yes"),"DQ Gating","OK")) -> OK | AH9: No | AI9: =IF(AG9="Not scored","",IF(OR(AG9="DQ Gating",AH9="Yes"),"Disqualified",IF(AF9>=80,"Priority 1",IF(AF9>=60,"Priority 2",IF(AF9>=40,"Priority 3","Disqualified"))))) -> Priority 2 | AJ9: =IF(AG9="Not scored","","P1 "&IF(E9="","?",E9)&"="&V9&" | P2 "&IF(F9="","?",F9)&"="&W9&" | P3 "&IF(C9="","?",C9)&"="&X9&" | P4 "&IF(G9="","?",G9)&"="&Y9&" | P5 "&IF(I9="","?",I9)&"="&Z9&" | P6="&AA9&" | P7 "&IF(M9="","?",M9)&"="&AB9&" | P8 "&IF(O9="","?",O9)&"="&AC9&" | P9 "&IF(L9="","?",L9)&"="&AD9&" | P10="&AE9) -> P1 Lending (SMB)=7 | P2 80=10 | P3 Poland=12 | P4 PI Licence=6 | P5 Series A=6 | P6=7 | P7 Incumbent Unknown=3 | P8 Cloud modern, Not API-first=4 | P9 Existing BIN Sponsor Relationship=8 | P10=10 | AL9: Prospect | AM9: No | AO9: Live, Migration Window | AP9: =IF(AO9="","Not set",IF(OR(AO9="Q1 2027",AO9="Q2 2027",AO9="Q3 2027",AO9="Q4 2027",AO9="Live, Migration Window"),"OK",IF(AO9="Live, Urgent Need","Deferred","Watch"))) -> OK | AQ9: Commercial and B2B
A10: ACC-PL-006 | B10: Smartney (Grupa Oney) | C10: Poland | D10: FinTech | E10: Lending (Consumer) | F10: 400 | G10: BIN Sponsor Agreement In Place | H10: PE-controlled | I10: PE-controlled Stable | K10: Oney Group internal | L10: Existing BIN Sponsor Relationship | M10: Incumbent Unknown | N10: No | O10: Cloud modern, Not API-first | P10: 0 | Q10: 250000 | R10: Yes | S10: Second-pass agent research | T10: 46216 | U10: 25%+ Polish long-term loan market share; 250k+ clients; PLN 1B+ active credit; Cashless Fintech Roku 2026 nominee; card-adjacent lending business | V10: =IF(E10="","",IFERROR(VLOOKUP(E10,Scoring_Lookups!$A$5:$B$18,2,FALSE()),0)) -> 7 | W10: =IF(F10="","",IF(AND(F10>=50,F10<=1000),10,IF(OR(AND(F10>=20,F10<=49),AND(F10>=1001,F10<=2000)),7,IF(OR(AND(F10>=10,F10<=19),AND(F10>=2001,F10<=5000)),4,0)))) -> 10 | X10: =IF(C10="","",IFERROR(VLOOKUP(C10,Scoring_Lookups!$D$5:$E$35,2,FALSE()),0)) -> 12 | Y10: =IF(G10="","",IFERROR(VLOOKUP(G10,Scoring_Lookups!$G$5:$H$16,2,FALSE()),0)) -> 6 | Z10: =IF(I10="","",IF(OR(I10="Administration/Insolvency",I10="Pending Wind-down",I10="Sanctions Exposure"),0,IF(OR(AND(OR(I10="Series B",I10="Series C",I10="Series D+"),J10<>"",J10>=TODAY()-730),I10="PE-controlled Growth Mandate",I10="Listed with Growth Profile"),8,IF(OR(I10="Series A",I10="Bootstrapped Profitable",I10="PE-controlled Stable",AND(OR(I10="Series B",I10="Series C",I10="Series D+"),J10<>"",J10<TODAY()-730)),6,IF(OR(I10="Seed",I10="Bootstrapped",I10="Listed Stable",I10="Established Private Flat"),3,0))))) -> 6 | AA10: =IF(N10="Yes",0,IF(A10="",0,IF(COUNTIFS('04_Triggers'!B:B,A10,'04_Triggers'!D:D,">="&(TODAY()-365))>=2,20,IF(COUNTIFS('04_Triggers'!B:B,A10,'04_Triggers'!D:D,">="&(TODAY()-365),'04_Triggers'!G:G,"High")>=1,14,IF(COUNTIFS('04_Triggers'!B:B,A10,'04_Triggers'!D:D,">="&(TODAY()-365))>=1,7,IF(COUNTIFS('04_Triggers'!B:B,A10,'04_Triggers'!D:D,">="&(TODAY()-1095),'04_Triggers'!D:D,"<"&(TODAY()-365))>=1,7,0)))))) -> 7 | AB10: =IF(M10="","",IFERROR(VLOOKUP(M10,Scoring_Lookups!$J$5:$K$16,2,FALSE()),0)) -> 3 | AC10: =IF(O10="","",IFERROR(VLOOKUP(O10,Scoring_Lookups!$M$5:$N$8,2,FALSE()),0)) -> 4 | AD10: =IF(L10="","",IFERROR(VLOOKUP(L10,Scoring_Lookups!$P$5:$Q$9,2,FALSE()),0)) -> 8 | AE10: =IF(AND(P10="",Q10="",R10=""),"",IF(OR(IFERROR(MAX(P10,Q10),0)>=500000,R10="Yes"),10,IF(IFERROR(MAX(P10,Q10),0)>=100000,7,IF(IFERROR(MAX(P10,Q10),0)>=10000,4,0)))) -> 10 | AF10: =IFERROR(N(V10)+N(W10)+N(X10)+N(Y10)+N(Z10)+N(AA10)+N(AB10)+N(AC10)+N(AD10)+N(AE10),0) -> 73 | AG10: =IF(OR(E10="",C10="",G10=""),"Not scored",IF(OR(V10=0,X10=0,Y10=0,N10="Yes"),"DQ Gating","OK")) -> OK | AH10: No | AI10: =IF(AG10="Not scored","",IF(OR(AG10="DQ Gating",AH10="Yes"),"Disqualified",IF(AF10>=80,"Priority 1",IF(AF10>=60,"Priority 2",IF(AF10>=40,"Priority 3","Disqualified"))))) -> Priority 2 | AJ10: =IF(AG10="Not scored","","P1 "&IF(E10="","?",E10)&"="&V10&" | P2 "&IF(F10="","?",F10)&"="&W10&" | P3 "&IF(C10="","?",C10)&"="&X10&" | P4 "&IF(G10="","?",G10)&"="&Y10&" | P5 "&IF(I10="","?",I10)&"="&Z10&" | P6="&AA10&" | P7 "&IF(M10="","?",M10)&"="&AB10&" | P8 "&IF(O10="","?",O10)&"="&AC10&" | P9 "&IF(L10="","?",L10)&"="&AD10&" | P10="&AE10) -> P1 Lending (Consumer)=7 | P2 400=10 | P3 Poland=12 | P4 BIN Sponsor Agreement In Place=6 | P5 PE-controlled Stable=6 | P6=7 | P7 Incumbent Unknown=3 | P8 Cloud modern, Not API-first=4 | P9 Existing BIN Sponsor Relationship=8 | P10=10 | AL10: Prospect | AM10: No | AO10: Q4 2027 | AP10: =IF(AO10="","Not set",IF(OR(AO10="Q1 2027",AO10="Q2 2027",AO10="Q3 2027",AO10="Q4 2027",AO10="Live, Migration Window"),"OK",IF(AO10="Live, Urgent Need","Deferred","Watch"))) -> OK | AQ10: Consumer
A11: ACC-PL-007 | B11: Spingo | C11: Poland | D11: FinTech | E11: Lending (SMB) | F11: 20 | G11: BIN Sponsor Agreement In Place | H11: VC-backed | I11: Seed | J11: 45901 | K11: TBD | L11: No Sponsor, Licensing Suggests Imminent | M11: Planning to Launch (No Incumbent Yet) | N11: No | O11: Cloud-native (AWS/Azure/GCP), API-first, AI signals | P11: 0 | Q11: 30000 | R11: Unknown | S11: Second-pass agent research | T11: 46216 | U11: EUR 4M seed 2025 led by Finch Capital; AI-driven credit scoring; 24-hour SME loan approvals; top Polish fintechs to watch 2026 | V11: =IF(E11="","",IFERROR(VLOOKUP(E11,Scoring_Lookups!$A$5:$B$18,2,FALSE()),0)) -> 7 | W11: =IF(F11="","",IF(AND(F11>=50,F11<=1000),10,IF(OR(AND(F11>=20,F11<=49),AND(F11>=1001,F11<=2000)),7,IF(OR(AND(F11>=10,F11<=19),AND(F11>=2001,F11<=5000)),4,0)))) -> 7 | X11: =IF(C11="","",IFERROR(VLOOKUP(C11,Scoring_Lookups!$D$5:$E$35,2,FALSE()),0)) -> 12 | Y11: =IF(G11="","",IFERROR(VLOOKUP(G11,Scoring_Lookups!$G$5:$H$16,2,FALSE()),0)) -> 6 | Z11: =IF(I11="","",IF(OR(I11="Administration/Insolvency",I11="Pending Wind-down",I11="Sanctions Exposure"),0,IF(OR(AND(OR(I11="Series B",I11="Series C",I11="Series D+"),J11<>"",J11>=TODAY()-730),I11="PE-controlled Growth Mandate",I11="Listed with Growth Profile"),8,IF(OR(I11="Series A",I11="Bootstrapped Profitable",I11="PE-controlled Stable",AND(OR(I11="Series B",I11="Series C",I11="Series D+"),J11<>"",J11<TODAY()-730)),6,IF(OR(I11="Seed",I11="Bootstrapped",I11="Listed Stable",I11="Established Private Flat"),3,0))))) -> 3 | AA11: =IF(N11="Yes",0,IF(A11="",0,IF(COUNTIFS('04_Triggers'!B:B,A11,'04_Triggers'!D:D,">="&(TODAY()-365))>=2,20,IF(COUNTIFS('04_Triggers'!B:B,A11,'04_Triggers'!D:D,">="&(TODAY()-365),'04_Triggers'!G:G,"High")>=1,14,IF(COUNTIFS('04_Triggers'!B:B,A11,'04_Triggers'!D:D,">="&(TODAY()-365))>=1,7,IF(COUNTIFS('04_Triggers'!B:B,A11,'04_Triggers'!D:D,">="&(TODAY()-1095),'04_Triggers'!D:D,"<"&(TODAY()-365))>=1,7,0)))))) -> 14 | AB11: =IF(M11="","",IFERROR(VLOOKUP(M11,Scoring_Lookups!$J$5:$K$16,2,FALSE()),0)) -> 4 | AC11: =IF(O11="","",IFERROR(VLOOKUP(O11,Scoring_Lookups!$M$5:$N$8,2,FALSE()),0)) -> 6 | AD11: =IF(L11="","",IFERROR(VLOOKUP(L11,Scoring_Lookups!$P$5:$Q$9,2,FALSE()),0)) -> 3 | AE11: =IF(AND(P11="",Q11="",R11=""),"",IF(OR(IFERROR(MAX(P11,Q11),0)>=500000,R11="Yes"),10,IF(IFERROR(MAX(P11,Q11),0)>=100000,7,IF(IFERROR(MAX(P11,Q11),0)>=10000,4,0)))) -> 4 | AF11: =IFERROR(N(V11)+N(W11)+N(X11)+N(Y11)+N(Z11)+N(AA11)+N(AB11)+N(AC11)+N(AD11)+N(AE11),0) -> 66 | AG11: =IF(OR(E11="",C11="",G11=""),"Not scored",IF(OR(V11=0,X11=0,Y11=0,N11="Yes"),"DQ Gating","OK")) -> OK | AH11: No | AI11: =IF(AG11="Not scored","",IF(OR(AG11="DQ Gating",AH11="Yes"),"Disqualified",IF(AF11>=80,"Priority 1",IF(AF11>=60,"Priority 2",IF(AF11>=40,"Priority 3","Disqualified"))))) -> Priority 2 | AJ11: =IF(AG11="Not scored","","P1 "&IF(E11="","?",E11)&"="&V11&" | P2 "&IF(F11="","?",F11)&"="&W11&" | P3 "&IF(C11="","?",C11)&"="&X11&" | P4 "&IF(G11="","?",G11)&"="&Y11&" | P5 "&IF(I11="","?",I11)&"="&Z11&" | P6="&AA11&" | P7 "&IF(M11="","?",M11)&"="&AB11&" | P8 "&IF(O11="","?",O11)&"="&AC11&" | P9 "&IF(L11="","?",L11)&"="&AD11&" | P10="&AE11) -> P1 Lending (SMB)=7 | P2 20=7 | P3 Poland=12 | P4 BIN Sponsor Agreement In Place=6 | P5 Seed=3 | P6=14 | P7 Planning to Launch (No Incumbent Yet)=4 | P8 Cloud-native (AWS/Azure/GCP), API-first, AI signals=6 | P9 No Sponsor, Licensing Suggests Imminent=3 | P10=4 | AL11: Prospect | AM11: No | AO11: Q4 2027 | AP11: =IF(AO11="","Not set",IF(OR(AO11="Q1 2027",AO11="Q2 2027",AO11="Q3 2027",AO11="Q4 2027",AO11="Live, Migration Window"),"OK",IF(AO11="Live, Urgent Need","Deferred","Watch"))) -> OK | AQ11: Commercial and B2B
A12: ACC-PL-008 | B12: Symmetrical.ai | C12: Poland | D12: FinTech | E12: Lending (Consumer) | F12: 75 | G12: PI Licence | H12: VC-backed | I12: Series A | J12: 44679 | K12: TBD | L12: No Sponsor, Licensing Suggests Imminent | M12: Planning to Launch (No Incumbent Yet) | N12: No | O12: Cloud-native (AWS/Azure/GCP), API-first, AI signals | P12: 0 | Q12: 40000 | R12: Unknown | S12: First-pass agent research | T12: 46216 | U12: Series A US$18.5M 2022; earned wage access (EWA) provider; card is natural on-demand-payout adjacency (Wagestream/DailyPay pattern); Warsaw engineering hub | V12: =IF(E12="","",IFERROR(VLOOKUP(E12,Scoring_Lookups!$A$5:$B$18,2,FALSE()),0)) -> 7 | W12: =IF(F12="","",IF(AND(F12>=50,F12<=1000),10,IF(OR(AND(F12>=20,F12<=49),AND(F12>=1001,F12<=2000)),7,IF(OR(AND(F12>=10,F12<=19),AND(F12>=2001,F12<=5000)),4,0)))) -> 10 | X12: =IF(C12="","",IFERROR(VLOOKUP(C12,Scoring_Lookups!$D$5:$E$35,2,FALSE()),0)) -> 12 | Y12: =IF(G12="","",IFERROR(VLOOKUP(G12,Scoring_Lookups!$G$5:$H$16,2,FALSE()),0)) -> 6 | Z12: =IF(I12="","",IF(OR(I12="Administration/Insolvency",I12="Pending Wind-down",I12="Sanctions Exposure"),0,IF(OR(AND(OR(I12="Series B",I12="Series C",I12="Series D+"),J12<>"",J12>=TODAY()-730),I12="PE-controlled Growth Mandate",I12="Listed with Growth Profile"),8,IF(OR(I12="Series A",I12="Bootstrapped Profitable",I12="PE-controlled Stable",AND(OR(I12="Series B",I12="Series C",I12="Series D+"),J12<>"",J12<TODAY()-730)),6,IF(OR(I12="Seed",I12="Bootstrapped",I12="Listed Stable",I12="Established Private Flat"),3,0))))) -> 6 | AA12: =IF(N12="Yes",0,IF(A12="",0,IF(COUNTIFS('04_Triggers'!B:B,A12,'04_Triggers'!D:D,">="&(TODAY()-365))>=2,20,IF(COUNTIFS('04_Triggers'!B:B,A12,'04_Triggers'!D:D,">="&(TODAY()-365),'04_Triggers'!G:G,"High")>=1,14,IF(COUNTIFS('04_Triggers'!B:B,A12,'04_Triggers'!D:D,">="&(TODAY()-365))>=1,7,IF(COUNTIFS('04_Triggers'!B:B,A12,'04_Triggers'!D:D,">="&(TODAY()-1095),'04_Triggers'!D:D,"<"&(TODAY()-365))>=1,7,0)))))) -> 0 | AB12: =IF(M12="","",IFERROR(VLOOKUP(M12,Scoring_Lookups!$J$5:$K$16,2,FALSE()),0)) -> 4 | AC12: =IF(O12="","",IFERROR(VLOOKUP(O12,Scoring_Lookups!$M$5:$N$8,2,FALSE()),0)) -> 6 | AD12: =IF(L12="","",IFERROR(VLOOKUP(L12,Scoring_Lookups!$P$5:$Q$9,2,FALSE()),0)) -> 3 | AE12: =IF(AND(P12="",Q12="",R12=""),"",IF(OR(IFERROR(MAX(P12,Q12),0)>=500000,R12="Yes"),10,IF(IFERROR(MAX(P12,Q12),0)>=100000,7,IF(IFERROR(MAX(P12,Q12),0)>=10000,4,0)))) -> 4 | AF12: =IFERROR(N(V12)+N(W12)+N(X12)+N(Y12)+N(Z12)+N(AA12)+N(AB12)+N(AC12)+N(AD12)+N(AE12),0) -> 58 | AG12: =IF(OR(E12="",C12="",G12=""),"Not scored",IF(OR(V12=0,X12=0,Y12=0,N12="Yes"),"DQ Gating","OK")) -> OK | AH12: No | AI12: =IF(AG12="Not scored","",IF(OR(AG12="DQ Gating",AH12="Yes"),"Disqualified",IF(AF12>=80,"Priority 1",IF(AF12>=60,"Priority 2",IF(AF12>=40,"Priority 3","Disqualified"))))) -> Priority 3 | AJ12: =IF(AG12="Not scored","","P1 "&IF(E12="","?",E12)&"="&V12&" | P2 "&IF(F12="","?",F12)&"="&W12&" | P3 "&IF(C12="","?",C12)&"="&X12&" | P4 "&IF(G12="","?",G12)&"="&Y12&" | P5 "&IF(I12="","?",I12)&"="&Z12&" | P6="&AA12&" | P7 "&IF(M12="","?",M12)&"="&AB12&" | P8 "&IF(O12="","?",O12)&"="&AC12&" | P9 "&IF(L12="","?",L12)&"="&AD12&" | P10="&AE12) -> P1 Lending (Consumer)=7 | P2 75=10 | P3 Poland=12 | P4 PI Licence=6 | P5 Series A=6 | P6=0 | P7 Planning to Launch (No Incumbent Yet)=4 | P8 Cloud-native (AWS/Azure/GCP), API-first, AI signals=6 | P9 No Sponsor, Licensing Suggests Imminent=3 | P10=4 | AL12: Prospect | AM12: No | AO12: Q3 2027 | AP12: =IF(AO12="","Not set",IF(OR(AO12="Q1 2027",AO12="Q2 2027",AO12="Q3 2027",AO12="Q4 2027",AO12="Live, Migration Window"),"OK",IF(AO12="Live, Urgent Need","Deferred","Watch"))) -> OK | AQ12: Disbursement and Payout
A13: ACC-PL-009 | B13: Currency One | C13: Poland | D13: FinTech | E13: FX Payments | F13: 125 | G13: PI Licence | H13: Private | I13: Bootstrapped Profitable | K13: TBD | L13: No Sponsor, Licensing Suggests Imminent | M13: Planning to Launch (No Incumbent Yet) | N13: No | O13: Cloud modern, Not API-first | P13: 0 | Q13: 80000 | R13: Unknown | S13: First-pass agent research | T13: 46216 | U13: KNF PI licence since Jul 2015, extended to acquiring plus AIS/PIS in 2022; strategic alliance with Przelewy24; long-established Polish FX player | V13: =IF(E13="","",IFERROR(VLOOKUP(E13,Scoring_Lookups!$A$5:$B$18,2,FALSE()),0)) -> 7 | W13: =IF(F13="","",IF(AND(F13>=50,F13<=1000),10,IF(OR(AND(F13>=20,F13<=49),AND(F13>=1001,F13<=2000)),7,IF(OR(AND(F13>=10,F13<=19),AND(F13>=2001,F13<=5000)),4,0)))) -> 10 | X13: =IF(C13="","",IFERROR(VLOOKUP(C13,Scoring_Lookups!$D$5:$E$35,2,FALSE()),0)) -> 12 | Y13: =IF(G13="","",IFERROR(VLOOKUP(G13,Scoring_Lookups!$G$5:$H$16,2,FALSE()),0)) -> 6 | Z13: =IF(I13="","",IF(OR(I13="Administration/Insolvency",I13="Pending Wind-down",I13="Sanctions Exposure"),0,IF(OR(AND(OR(I13="Series B",I13="Series C",I13="Series D+"),J13<>"",J13>=TODAY()-730),I13="PE-controlled Growth Mandate",I13="Listed with Growth Profile"),8,IF(OR(I13="Series A",I13="Bootstrapped Profitable",I13="PE-controlled Stable",AND(OR(I13="Series B",I13="Series C",I13="Series D+"),J13<>"",J13<TODAY()-730)),6,IF(OR(I13="Seed",I13="Bootstrapped",I13="Listed Stable",I13="Established Private Flat"),3,0))))) -> 6 | AA13: =IF(N13="Yes",0,IF(A13="",0,IF(COUNTIFS('04_Triggers'!B:B,A13,'04_Triggers'!D:D,">="&(TODAY()-365))>=2,20,IF(COUNTIFS('04_Triggers'!B:B,A13,'04_Triggers'!D:D,">="&(TODAY()-365),'04_Triggers'!G:G,"High")>=1,14,IF(COUNTIFS('04_Triggers'!B:B,A13,'04_Triggers'!D:D,">="&(TODAY()-365))>=1,7,IF(COUNTIFS('04_Triggers'!B:B,A13,'04_Triggers'!D:D,">="&(TODAY()-1095),'04_Triggers'!D:D,"<"&(TODAY()-365))>=1,7,0)))))) -> 0 | AB13: =IF(M13="","",IFERROR(VLOOKUP(M13,Scoring_Lookups!$J$5:$K$16,2,FALSE()),0)) -> 4 | AC13: =IF(O13="","",IFERROR(VLOOKUP(O13,Scoring_Lookups!$M$5:$N$8,2,FALSE()),0)) -> 4 | AD13: =IF(L13="","",IFERROR(VLOOKUP(L13,Scoring_Lookups!$P$5:$Q$9,2,FALSE()),0)) -> 3 | AE13: =IF(AND(P13="",Q13="",R13=""),"",IF(OR(IFERROR(MAX(P13,Q13),0)>=500000,R13="Yes"),10,IF(IFERROR(MAX(P13,Q13),0)>=100000,7,IF(IFERROR(MAX(P13,Q13),0)>=10000,4,0)))) -> 4 | AF13: =IFERROR(N(V13)+N(W13)+N(X13)+N(Y13)+N(Z13)+N(AA13)+N(AB13)+N(AC13)+N(AD13)+N(AE13),0) -> 56 | AG13: =IF(OR(E13="",C13="",G13=""),"Not scored",IF(OR(V13=0,X13=0,Y13=0,N13="Yes"),"DQ Gating","OK")) -> OK | AH13: No | AI13: =IF(AG13="Not scored","",IF(OR(AG13="DQ Gating",AH13="Yes"),"Disqualified",IF(AF13>=80,"Priority 1",IF(AF13>=60,"Priority 2",IF(AF13>=40,"Priority 3","Disqualified"))))) -> Priority 3 | AJ13: =IF(AG13="Not scored","","P1 "&IF(E13="","?",E13)&"="&V13&" | P2 "&IF(F13="","?",F13)&"="&W13&" | P3 "&IF(C13="","?",C13)&"="&X13&" | P4 "&IF(G13="","?",G13)&"="&Y13&" | P5 "&IF(I13="","?",I13)&"="&Z13&" | P6="&AA13&" | P7 "&IF(M13="","?",M13)&"="&AB13&" | P8 "&IF(O13="","?",O13)&"="&AC13&" | P9 "&IF(L13="","?",L13)&"="&AD13&" | P10="&AE13) -> P1 FX Payments=7 | P2 125=10 | P3 Poland=12 | P4 PI Licence=6 | P5 Bootstrapped Profitable=6 | P6=0 | P7 Planning to Launch (No Incumbent Yet)=4 | P8 Cloud modern, Not API-first=4 | P9 No Sponsor, Licensing Suggests Imminent=3 | P10=4 | AL13: Prospect | AM13: No | AO13: Q4 2027 | AP13: =IF(AO13="","Not set",IF(OR(AO13="Q1 2027",AO13="Q2 2027",AO13="Q3 2027",AO13="Q4 2027",AO13="Live, Migration Window"),"OK",IF(AO13="Live, Urgent Need","Deferred","Watch"))) -> OK | AQ13: Consumer
A14: ACC-PL-010 | B14: Autopay (ex-Blue Media) | C14: Poland | D14: FinTech | E14: Payments | F14: 281 | G14: PI Licence | H14: Private | I14: Bootstrapped Profitable | K14: TBD | L14: Scheme Participation Visible | M14: Planning to Launch (No Incumbent Yet) | N14: No | O14: Cloud modern, Not API-first | P14: 0 | Q14: 150000 | R14: Yes | S14: First-pass agent research | T14: 46216 | U14: Blue Media to Autopay rebrand 2024; PCI DSS plus 3DS certified; Click-to-Pay live with Mastercard; Jul 2025 eSIM launch; scope expansion | V14: =IF(E14="","",IFERROR(VLOOKUP(E14,Scoring_Lookups!$A$5:$B$18,2,FALSE()),0)) -> 4 | W14: =IF(F14="","",IF(AND(F14>=50,F14<=1000),10,IF(OR(AND(F14>=20,F14<=49),AND(F14>=1001,F14<=2000)),7,IF(OR(AND(F14>=10,F14<=19),AND(F14>=2001,F14<=5000)),4,0)))) -> 10 | X14: =IF(C14="","",IFERROR(VLOOKUP(C14,Scoring_Lookups!$D$5:$E$35,2,FALSE()),0)) -> 12 | Y14: =IF(G14="","",IFERROR(VLOOKUP(G14,Scoring_Lookups!$G$5:$H$16,2,FALSE()),0)) -> 6 | Z14: =IF(I14="","",IF(OR(I14="Administration/Insolvency",I14="Pending Wind-down",I14="Sanctions Exposure"),0,IF(OR(AND(OR(I14="Series B",I14="Series C",I14="Series D+"),J14<>"",J14>=TODAY()-730),I14="PE-controlled Growth Mandate",I14="Listed with Growth Profile"),8,IF(OR(I14="Series A",I14="Bootstrapped Profitable",I14="PE-controlled Stable",AND(OR(I14="Series B",I14="Series C",I14="Series D+"),J14<>"",J14<TODAY()-730)),6,IF(OR(I14="Seed",I14="Bootstrapped",I14="Listed Stable",I14="Established Private Flat"),3,0))))) -> 6 | AA14: =IF(N14="Yes",0,IF(A14="",0,IF(COUNTIFS('04_Triggers'!B:B,A14,'04_Triggers'!D:D,">="&(TODAY()-365))>=2,20,IF(COUNTIFS('04_Triggers'!B:B,A14,'04_Triggers'!D:D,">="&(TODAY()-365),'04_Triggers'!G:G,"High")>=1,14,IF(COUNTIFS('04_Triggers'!B:B,A14,'04_Triggers'!D:D,">="&(TODAY()-365))>=1,7,IF(COUNTIFS('04_Triggers'!B:B,A14,'04_Triggers'!D:D,">="&(TODAY()-1095),'04_Triggers'!D:D,"<"&(TODAY()-365))>=1,7,0)))))) -> 7 | AB14: =IF(M14="","",IFERROR(VLOOKUP(M14,Scoring_Lookups!$J$5:$K$16,2,FALSE()),0)) -> 4 | AC14: =IF(O14="","",IFERROR(VLOOKUP(O14,Scoring_Lookups!$M$5:$N$8,2,FALSE()),0)) -> 4 | AD14: =IF(L14="","",IFERROR(VLOOKUP(L14,Scoring_Lookups!$P$5:$Q$9,2,FALSE()),0)) -> 6 | AE14: =IF(AND(P14="",Q14="",R14=""),"",IF(OR(IFERROR(MAX(P14,Q14),0)>=500000,R14="Yes"),10,IF(IFERROR(MAX(P14,Q14),0)>=100000,7,IF(IFERROR(MAX(P14,Q14),0)>=10000,4,0)))) -> 10 | AF14: =IFERROR(N(V14)+N(W14)+N(X14)+N(Y14)+N(Z14)+N(AA14)+N(AB14)+N(AC14)+N(AD14)+N(AE14),0) -> 69 | AG14: =IF(OR(E14="",C14="",G14=""),"Not scored",IF(OR(V14=0,X14=0,Y14=0,N14="Yes"),"DQ Gating","OK")) -> OK | AH14: No | AI14: =IF(AG14="Not scored","",IF(OR(AG14="DQ Gating",AH14="Yes"),"Disqualified",IF(AF14>=80,"Priority 1",IF(AF14>=60,"Priority 2",IF(AF14>=40,"Priority 3","Disqualified"))))) -> Priority 2 | AJ14: =IF(AG14="Not scored","","P1 "&IF(E14="","?",E14)&"="&V14&" | P2 "&IF(F14="","?",F14)&"="&W14&" | P3 "&IF(C14="","?",C14)&"="&X14&" | P4 "&IF(G14="","?",G14)&"="&Y14&" | P5 "&IF(I14="","?",I14)&"="&Z14&" | P6="&AA14&" | P7 "&IF(M14="","?",M14)&"="&AB14&" | P8 "&IF(O14="","?",O14)&"="&AC14&" | P9 "&IF(L14="","?",L14)&"="&AD14&" | P10="&AE14) -> P1 Payments=4 | P2 281=10 | P3 Poland=12 | P4 PI Licence=6 | P5 Bootstrapped Profitable=6 | P6=7 | P7 Planning to Launch (No Incumbent Yet)=4 | P8 Cloud modern, Not API-first=4 | P9 Scheme Participation Visible=6 | P10=10 | AL14: Prospect | AM14: No | AO14: Q2 2027 | AP14: =IF(AO14="","Not set",IF(OR(AO14="Q1 2027",AO14="Q2 2027",AO14="Q3 2027",AO14="Q4 2027",AO14="Live, Migration Window"),"OK",IF(AO14="Live, Urgent Need","Deferred","Watch"))) -> OK | AQ14: Consumer
A15: ACC-PL-011 | B15: LOANDO Group | C15: Poland | D15: FinTech | E15: Lending (Consumer) | F15: 125 | G15: No Licence, BIN Sponsor Engaged | H15: Private | I15: Bootstrapped Profitable | K15: TBD | L15: No Sponsor, Licensing Suggests Imminent | M15: Planning to Launch (No Incumbent Yet) | N15: No | O15: Cloud modern, Not API-first | P15: 0 | Q15: 100000 | R15: Unknown | S15: Second-pass agent research | T15: 46216 | U15: Multi-market operations (PL, ES, CZ, UA); 50+ financial partners; 1M+ customers annually; broker to own product evolution potential | V15: =IF(E15="","",IFERROR(VLOOKUP(E15,Scoring_Lookups!$A$5:$B$18,2,FALSE()),0)) -> 7 | W15: =IF(F15="","",IF(AND(F15>=50,F15<=1000),10,IF(OR(AND(F15>=20,F15<=49),AND(F15>=1001,F15<=2000)),7,IF(OR(AND(F15>=10,F15<=19),AND(F15>=2001,F15<=5000)),4,0)))) -> 10 | X15: =IF(C15="","",IFERROR(VLOOKUP(C15,Scoring_Lookups!$D$5:$E$35,2,FALSE()),0)) -> 12 | Y15: =IF(G15="","",IFERROR(VLOOKUP(G15,Scoring_Lookups!$G$5:$H$16,2,FALSE()),0)) -> 3 | Z15: =IF(I15="","",IF(OR(I15="Administration/Insolvency",I15="Pending Wind-down",I15="Sanctions Exposure"),0,IF(OR(AND(OR(I15="Series B",I15="Series C",I15="Series D+"),J15<>"",J15>=TODAY()-730),I15="PE-controlled Growth Mandate",I15="Listed with Growth Profile"),8,IF(OR(I15="Series A",I15="Bootstrapped Profitable",I15="PE-controlled Stable",AND(OR(I15="Series B",I15="Series C",I15="Series D+"),J15<>"",J15<TODAY()-730)),6,IF(OR(I15="Seed",I15="Bootstrapped",I15="Listed Stable",I15="Established Private Flat"),3,0))))) -> 6 | AA15: =IF(N15="Yes",0,IF(A15="",0,IF(COUNTIFS('04_Triggers'!B:B,A15,'04_Triggers'!D:D,">="&(TODAY()-365))>=2,20,IF(COUNTIFS('04_Triggers'!B:B,A15,'04_Triggers'!D:D,">="&(TODAY()-365),'04_Triggers'!G:G,"High")>=1,14,IF(COUNTIFS('04_Triggers'!B:B,A15,'04_Triggers'!D:D,">="&(TODAY()-365))>=1,7,IF(COUNTIFS('04_Triggers'!B:B,A15,'04_Triggers'!D:D,">="&(TODAY()-1095),'04_Triggers'!D:D,"<"&(TODAY()-365))>=1,7,0)))))) -> 0 | AB15: =IF(M15="","",IFERROR(VLOOKUP(M15,Scoring_Lookups!$J$5:$K$16,2,FALSE()),0)) -> 4 | AC15: =IF(O15="","",IFERROR(VLOOKUP(O15,Scoring_Lookups!$M$5:$N$8,2,FALSE()),0)) -> 4 | AD15: =IF(L15="","",IFERROR(VLOOKUP(L15,Scoring_Lookups!$P$5:$Q$9,2,FALSE()),0)) -> 3 | AE15: =IF(AND(P15="",Q15="",R15=""),"",IF(OR(IFERROR(MAX(P15,Q15),0)>=500000,R15="Yes"),10,IF(IFERROR(MAX(P15,Q15),0)>=100000,7,IF(IFERROR(MAX(P15,Q15),0)>=10000,4,0)))) -> 7 | AF15: =IFERROR(N(V15)+N(W15)+N(X15)+N(Y15)+N(Z15)+N(AA15)+N(AB15)+N(AC15)+N(AD15)+N(AE15),0) -> 56 | AG15: =IF(OR(E15="",C15="",G15=""),"Not scored",IF(OR(V15=0,X15=0,Y15=0,N15="Yes"),"DQ Gating","OK")) -> OK | AH15: No | AI15: =IF(AG15="Not scored","",IF(OR(AG15="DQ Gating",AH15="Yes"),"Disqualified",IF(AF15>=80,"Priority 1",IF(AF15>=60,"Priority 2",IF(AF15>=40,"Priority 3","Disqualified"))))) -> Priority 3 | AJ15: =IF(AG15="Not scored","","P1 "&IF(E15="","?",E15)&"="&V15&" | P2 "&IF(F15="","?",F15)&"="&W15&" | P3 "&IF(C15="","?",C15)&"="&X15&" | P4 "&IF(G15="","?",G15)&"="&Y15&" | P5 "&IF(I15="","?",I15)&"="&Z15&" | P6="&AA15&" | P7 "&IF(M15="","?",M15)&"="&AB15&" | P8 "&IF(O15="","?",O15)&"="&AC15&" | P9 "&IF(L15="","?",L15)&"="&AD15&" | P10="&AE15) -> P1 Lending (Consumer)=7 | P2 125=10 | P3 Poland=12 | P4 No Licence, BIN Sponsor Engaged=3 | P5 Bootstrapped Profitable=6 | P6=0 | P7 Planning to Launch (No Incumbent Yet)=4 | P8 Cloud modern, Not API-first=4 | P9 No Sponsor, Licensing Suggests Imminent=3 | P10=7 | AL15: Prospect | AM15: No | AO15: Q4 2027 | AP15: =IF(AO15="","Not set",IF(OR(AO15="Q1 2027",AO15="Q2 2027",AO15="Q3 2027",AO15="Q4 2027",AO15="Live, Migration Window"),"OK",IF(AO15="Live, Urgent Need","Deferred","Watch"))) -> OK | AQ15: Consumer
A16: ACC-PL-012 | B16: Plenti | C16: Poland | D16: FinTech | E16: Payments | F16: 30 | G16: PI Licence | H16: VC-backed | I16: Seed | J16: 45292 | K16: TBD | L16: No Sponsor, Licensing Suggests Imminent | M16: Planning to Launch (No Incumbent Yet) | N16: No | O16: Cloud-native (AWS/Azure/GCP), API-first, AI signals | P16: 0 | Q16: 25000 | R16: Unknown | S16: Second-pass agent research | T16: 46216 | U16: EUR 3M seed, ~EUR 12M valuation; 200k+ Polish users; social payments / group expenses; card would extend the model | V16: =IF(E16="","",IFERROR(VLOOKUP(E16,Scoring_Lookups!$A$5:$B$18,2,FALSE()),0)) -> 4 | W16: =IF(F16="","",IF(AND(F16>=50,F16<=1000),10,IF(OR(AND(F16>=20,F16<=49),AND(F16>=1001,F16<=2000)),7,IF(OR(AND(F16>=10,F16<=19),AND(F16>=2001,F16<=5000)),4,0)))) -> 7 | X16: =IF(C16="","",IFERROR(VLOOKUP(C16,Scoring_Lookups!$D$5:$E$35,2,FALSE()),0)) -> 12 | Y16: =IF(G16="","",IFERROR(VLOOKUP(G16,Scoring_Lookups!$G$5:$H$16,2,FALSE()),0)) -> 6 | Z16: =IF(I16="","",IF(OR(I16="Administration/Insolvency",I16="Pending Wind-down",I16="Sanctions Exposure"),0,IF(OR(AND(OR(I16="Series B",I16="Series C",I16="Series D+"),J16<>"",J16>=TODAY()-730),I16="PE-controlled Growth Mandate",I16="Listed with Growth Profile"),8,IF(OR(I16="Series A",I16="Bootstrapped Profitable",I16="PE-controlled Stable",AND(OR(I16="Series B",I16="Series C",I16="Series D+"),J16<>"",J16<TODAY()-730)),6,IF(OR(I16="Seed",I16="Bootstrapped",I16="Listed Stable",I16="Established Private Flat"),3,0))))) -> 3 | AA16: =IF(N16="Yes",0,IF(A16="",0,IF(COUNTIFS('04_Triggers'!B:B,A16,'04_Triggers'!D:D,">="&(TODAY()-365))>=2,20,IF(COUNTIFS('04_Triggers'!B:B,A16,'04_Triggers'!D:D,">="&(TODAY()-365),'04_Triggers'!G:G,"High")>=1,14,IF(COUNTIFS('04_Triggers'!B:B,A16,'04_Triggers'!D:D,">="&(TODAY()-365))>=1,7,IF(COUNTIFS('04_Triggers'!B:B,A16,'04_Triggers'!D:D,">="&(TODAY()-1095),'04_Triggers'!D:D,"<"&(TODAY()-365))>=1,7,0)))))) -> 0 | AB16: =IF(M16="","",IFERROR(VLOOKUP(M16,Scoring_Lookups!$J$5:$K$16,2,FALSE()),0)) -> 4 | AC16: =IF(O16="","",IFERROR(VLOOKUP(O16,Scoring_Lookups!$M$5:$N$8,2,FALSE()),0)) -> 6 | AD16: =IF(L16="","",IFERROR(VLOOKUP(L16,Scoring_Lookups!$P$5:$Q$9,2,FALSE()),0)) -> 3 | AE16: =IF(AND(P16="",Q16="",R16=""),"",IF(OR(IFERROR(MAX(P16,Q16),0)>=500000,R16="Yes"),10,IF(IFERROR(MAX(P16,Q16),0)>=100000,7,IF(IFERROR(MAX(P16,Q16),0)>=10000,4,0)))) -> 4 | AF16: =IFERROR(N(V16)+N(W16)+N(X16)+N(Y16)+N(Z16)+N(AA16)+N(AB16)+N(AC16)+N(AD16)+N(AE16),0) -> 49 | AG16: =IF(OR(E16="",C16="",G16=""),"Not scored",IF(OR(V16=0,X16=0,Y16=0,N16="Yes"),"DQ Gating","OK")) -> OK | AH16: No | AI16: =IF(AG16="Not scored","",IF(OR(AG16="DQ Gating",AH16="Yes"),"Disqualified",IF(AF16>=80,"Priority 1",IF(AF16>=60,"Priority 2",IF(AF16>=40,"Priority 3","Disqualified"))))) -> Priority 3 | AJ16: =IF(AG16="Not scored","","P1 "&IF(E16="","?",E16)&"="&V16&" | P2 "&IF(F16="","?",F16)&"="&W16&" | P3 "&IF(C16="","?",C16)&"="&X16&" | P4 "&IF(G16="","?",G16)&"="&Y16&" | P5 "&IF(I16="","?",I16)&"="&Z16&" | P6="&AA16&" | P7 "&IF(M16="","?",M16)&"="&AB16&" | P8 "&IF(O16="","?",O16)&"="&AC16&" | P9 "&IF(L16="","?",L16)&"="&AD16&" | P10="&AE16) -> P1 Payments=4 | P2 30=7 | P3 Poland=12 | P4 PI Licence=6 | P5 Seed=3 | P6=0 | P7 Planning to Launch (No Incumbent Yet)=4 | P8 Cloud-native (AWS/Azure/GCP), API-first, AI signals=6 | P9 No Sponsor, Licensing Suggests Imminent=3 | P10=4 | AL16: Prospect | AM16: No | AO16: Q3 2027 | AP16: =IF(AO16="","Not set",IF(OR(AO16="Q1 2027",AO16="Q2 2027",AO16="Q3 2027",AO16="Q4 2027",AO16="Live, Migration Window"),"OK",IF(AO16="Live, Urgent Need","Deferred","Watch"))) -> OK | AQ16: Consumer
A17: ACC-PL-013 | B17: PayPo | C17: Poland | D17: FinTech | E17: Lending (Consumer) | F17: 199 | G17: BIN Sponsor Agreement In Place | H17: VC-backed | I17: Series A | K17: TBD | L17: Existing BIN Sponsor Relationship | M17: Incumbent Unknown | N17: No | O17: Cloud modern, Not API-first | P17: 200000 | Q17: 400000 | R17: Yes | S17: First-pass agent research | T17: 46216 | U17: 200k+ cardholders by mid-2025; offline volumes +11-15% MoM; Mar 2025 offline expansion (accepted wherever Mastercard is); mObywatel in-app verification launched | V17: =IF(E17="","",IFERROR(VLOOKUP(E17,Scoring_Lookups!$A$5:$B$18,2,FALSE()),0)) -> 7 | W17: =IF(F17="","",IF(AND(F17>=50,F17<=1000),10,IF(OR(AND(F17>=20,F17<=49),AND(F17>=1001,F17<=2000)),7,IF(OR(AND(F17>=10,F17<=19),AND(F17>=2001,F17<=5000)),4,0)))) -> 10 | X17: =IF(C17="","",IFERROR(VLOOKUP(C17,Scoring_Lookups!$D$5:$E$35,2,FALSE()),0)) -> 12 | Y17: =IF(G17="","",IFERROR(VLOOKUP(G17,Scoring_Lookups!$G$5:$H$16,2,FALSE()),0)) -> 6 | Z17: =IF(I17="","",IF(OR(I17="Administration/Insolvency",I17="Pending Wind-down",I17="Sanctions Exposure"),0,IF(OR(AND(OR(I17="Series B",I17="Series C",I17="Series D+"),J17<>"",J17>=TODAY()-730),I17="PE-controlled Growth Mandate",I17="Listed with Growth Profile"),8,IF(OR(I17="Series A",I17="Bootstrapped Profitable",I17="PE-controlled Stable",AND(OR(I17="Series B",I17="Series C",I17="Series D+"),J17<>"",J17<TODAY()-730)),6,IF(OR(I17="Seed",I17="Bootstrapped",I17="Listed Stable",I17="Established Private Flat"),3,0))))) -> 6 | AA17: =IF(N17="Yes",0,IF(A17="",0,IF(COUNTIFS('04_Triggers'!B:B,A17,'04_Triggers'!D:D,">="&(TODAY()-365))>=2,20,IF(COUNTIFS('04_Triggers'!B:B,A17,'04_Triggers'!D:D,">="&(TODAY()-365),'04_Triggers'!G:G,"High")>=1,14,IF(COUNTIFS('04_Triggers'!B:B,A17,'04_Triggers'!D:D,">="&(TODAY()-365))>=1,7,IF(COUNTIFS('04_Triggers'!B:B,A17,'04_Triggers'!D:D,">="&(TODAY()-1095),'04_Triggers'!D:D,"<"&(TODAY()-365))>=1,7,0)))))) -> 7 | AB17: =IF(M17="","",IFERROR(VLOOKUP(M17,Scoring_Lookups!$J$5:$K$16,2,FALSE()),0)) -> 3 | AC17: =IF(O17="","",IFERROR(VLOOKUP(O17,Scoring_Lookups!$M$5:$N$8,2,FALSE()),0)) -> 4 | AD17: =IF(L17="","",IFERROR(VLOOKUP(L17,Scoring_Lookups!$P$5:$Q$9,2,FALSE()),0)) -> 8 | AE17: =IF(AND(P17="",Q17="",R17=""),"",IF(OR(IFERROR(MAX(P17,Q17),0)>=500000,R17="Yes"),10,IF(IFERROR(MAX(P17,Q17),0)>=100000,7,IF(IFERROR(MAX(P17,Q17),0)>=10000,4,0)))) -> 10 | AF17: =IFERROR(N(V17)+N(W17)+N(X17)+N(Y17)+N(Z17)+N(AA17)+N(AB17)+N(AC17)+N(AD17)+N(AE17),0) -> 73 | AG17: =IF(OR(E17="",C17="",G17=""),"Not scored",IF(OR(V17=0,X17=0,Y17=0,N17="Yes"),"DQ Gating","OK")) -> OK | AH17: No | AI17: =IF(AG17="Not scored","",IF(OR(AG17="DQ Gating",AH17="Yes"),"Disqualified",IF(AF17>=80,"Priority 1",IF(AF17>=60,"Priority 2",IF(AF17>=40,"Priority 3","Disqualified"))))) -> Priority 2 | AJ17: =IF(AG17="Not scored","","P1 "&IF(E17="","?",E17)&"="&V17&" | P2 "&IF(F17="","?",F17)&"="&W17&" | P3 "&IF(C17="","?",C17)&"="&X17&" | P4 "&IF(G17="","?",G17)&"="&Y17&" | P5 "&IF(I17="","?",I17)&"="&Z17&" | P6="&AA17&" | P7 "&IF(M17="","?",M17)&"="&AB17&" | P8 "&IF(O17="","?",O17)&"="&AC17&" | P9 "&IF(L17="","?",L17)&"="&AD17&" | P10="&AE17) -> P1 Lending (Consumer)=7 | P2 199=10 | P3 Poland=12 | P4 BIN Sponsor Agreement In Place=6 | P5 Series A=6 | P6=7 | P7 Incumbent Unknown=3 | P8 Cloud modern, Not API-first=4 | P9 Existing BIN Sponsor Relationship=8 | P10=10 | AL17: Prospect | AM17: No | AO17: Live, Migration Window | AP17: =IF(AO17="","Not set",IF(OR(AO17="Q1 2027",AO17="Q2 2027",AO17="Q3 2027",AO17="Q4 2027",AO17="Live, Migration Window"),"OK",IF(AO17="Live, Urgent Need","Deferred","Watch"))) -> OK | AQ17: Consumer
A18: ACC-PL-014 | B18: XTB | C18: Poland | D18: FinTech | E18: Investment Management | F18: 1315 | G18: PI Licence | H18: Listed | I18: Listed Stable | K18: DiPocket UAB | L18: Existing BIN Sponsor Relationship | M18: In-house Legacy Processor | N18: No | O18: Cloud-native (AWS/Azure/GCP), API-first, AI signals | P18: 50000 | Q18: 200000 | R18: Yes | S18: First-pass agent research | T18: 46216 | U18: DiPocket UAB issuer of record; multi-currency virtual Mastercard debit live in PT/CZ; rolling out CEE 2025; card + IKE/IKZE retirement accounts launched 2025; clean DiPocket displacement play | V18: =IF(E18="","",IFERROR(VLOOKUP(E18,Scoring_Lookups!$A$5:$B$18,2,FALSE()),0)) -> 4 | W18: =IF(F18="","",IF(AND(F18>=50,F18<=1000),10,IF(OR(AND(F18>=20,F18<=49),AND(F18>=1001,F18<=2000)),7,IF(OR(AND(F18>=10,F18<=19),AND(F18>=2001,F18<=5000)),4,0)))) -> 7 | X18: =IF(C18="","",IFERROR(VLOOKUP(C18,Scoring_Lookups!$D$5:$E$35,2,FALSE()),0)) -> 12 | Y18: =IF(G18="","",IFERROR(VLOOKUP(G18,Scoring_Lookups!$G$5:$H$16,2,FALSE()),0)) -> 6 | Z18: =IF(I18="","",IF(OR(I18="Administration/Insolvency",I18="Pending Wind-down",I18="Sanctions Exposure"),0,IF(OR(AND(OR(I18="Series B",I18="Series C",I18="Series D+"),J18<>"",J18>=TODAY()-730),I18="PE-controlled Growth Mandate",I18="Listed with Growth Profile"),8,IF(OR(I18="Series A",I18="Bootstrapped Profitable",I18="PE-controlled Stable",AND(OR(I18="Series B",I18="Series C",I18="Series D+"),J18<>"",J18<TODAY()-730)),6,IF(OR(I18="Seed",I18="Bootstrapped",I18="Listed Stable",I18="Established Private Flat"),3,0))))) -> 3 | AA18: =IF(N18="Yes",0,IF(A18="",0,IF(COUNTIFS('04_Triggers'!B:B,A18,'04_Triggers'!D:D,">="&(TODAY()-365))>=2,20,IF(COUNTIFS('04_Triggers'!B:B,A18,'04_Triggers'!D:D,">="&(TODAY()-365),'04_Triggers'!G:G,"High")>=1,14,IF(COUNTIFS('04_Triggers'!B:B,A18,'04_Triggers'!D:D,">="&(TODAY()-365))>=1,7,IF(COUNTIFS('04_Triggers'!B:B,A18,'04_Triggers'!D:D,">="&(TODAY()-1095),'04_Triggers'!D:D,"<"&(TODAY()-365))>=1,7,0)))))) -> 20 | AB18: =IF(M18="","",IFERROR(VLOOKUP(M18,Scoring_Lookups!$J$5:$K$16,2,FALSE()),0)) -> 8 | AC18: =IF(O18="","",IFERROR(VLOOKUP(O18,Scoring_Lookups!$M$5:$N$8,2,FALSE()),0)) -> 6 | AD18: =IF(L18="","",IFERROR(VLOOKUP(L18,Scoring_Lookups!$P$5:$Q$9,2,FALSE()),0)) -> 8 | AE18: =IF(AND(P18="",Q18="",R18=""),"",IF(OR(IFERROR(MAX(P18,Q18),0)>=500000,R18="Yes"),10,IF(IFERROR(MAX(P18,Q18),0)>=100000,7,IF(IFERROR(MAX(P18,Q18),0)>=10000,4,0)))) -> 10 | AF18: =IFERROR(N(V18)+N(W18)+N(X18)+N(Y18)+N(Z18)+N(AA18)+N(AB18)+N(AC18)+N(AD18)+N(AE18),0) -> 84 | AG18: =IF(OR(E18="",C18="",G18=""),"Not scored",IF(OR(V18=0,X18=0,Y18=0,N18="Yes"),"DQ Gating","OK")) -> OK | AH18: No | AI18: =IF(AG18="Not scored","",IF(OR(AG18="DQ Gating",AH18="Yes"),"Disqualified",IF(AF18>=80,"Priority 1",IF(AF18>=60,"Priority 2",IF(AF18>=40,"Priority 3","Disqualified"))))) -> Priority 1 | AJ18: =IF(AG18="Not scored","","P1 "&IF(E18="","?",E18)&"="&V18&" | P2 "&IF(F18="","?",F18)&"="&W18&" | P3 "&IF(C18="","?",C18)&"="&X18&" | P4 "&IF(G18="","?",G18)&"="&Y18&" | P5 "&IF(I18="","?",I18)&"="&Z18&" | P6="&AA18&" | P7 "&IF(M18="","?",M18)&"="&AB18&" | P8 "&IF(O18="","?",O18)&"="&AC18&" | P9 "&IF(L18="","?",L18)&"="&AD18&" | P10="&AE18) -> P1 Investment Management=4 | P2 1315=7 | P3 Poland=12 | P4 PI Licence=6 | P5 Listed Stable=3 | P6=20 | P7 In-house Legacy Processor=8 | P8 Cloud-native (AWS/Azure/GCP), API-first, AI signals=6 | P9 Existing BIN Sponsor Relationship=8 | P10=10 | AL18: Prospect | AM18: No | AO18: Live, Migration Window | AP18: =IF(AO18="","Not set",IF(OR(AO18="Q1 2027",AO18="Q2 2027",AO18="Q3 2027",AO18="Q4 2027",AO18="Live, Migration Window"),"OK",IF(AO18="Live, Urgent Need","Deferred","Watch"))) -> OK | AQ18: Consumer
A19: ACC-PL-015 | B19: Nest Bank | C19: Poland | D19: Banking | E19: Digital Banking | F19: 728 | G19: Credit Institution Licence | H19: PE-controlled | I19: PE-controlled Stable | K19: None (direct scheme) | L19: Scheme Principal | M19: Legacy Processor (Named) | N19: No | O19: Cloud modern, Not API-first | P19: 300000 | Q19: 500000 | R19: Yes | S19: First-pass agent research | T19: 46216 | U19: 2025 net profit PLN 152M; VP Janusz Mieloszyk named CE Digital Banker of the Year 2025 (Global Retail Banking Innovation Awards); AnaCap-owned; Fiserv incumbent - contract renewal displacement play | V19: =IF(E19="","",IFERROR(VLOOKUP(E19,Scoring_Lookups!$A$5:$B$18,2,FALSE()),0)) -> 10 | W19: =IF(F19="","",IF(AND(F19>=50,F19<=1000),10,IF(OR(AND(F19>=20,F19<=49),AND(F19>=1001,F19<=2000)),7,IF(OR(AND(F19>=10,F19<=19),AND(F19>=2001,F19<=5000)),4,0)))) -> 10 | X19: =IF(C19="","",IFERROR(VLOOKUP(C19,Scoring_Lookups!$D$5:$E$35,2,FALSE()),0)) -> 12 | Y19: =IF(G19="","",IFERROR(VLOOKUP(G19,Scoring_Lookups!$G$5:$H$16,2,FALSE()),0)) -> 8 | Z19: =IF(I19="","",IF(OR(I19="Administration/Insolvency",I19="Pending Wind-down",I19="Sanctions Exposure"),0,IF(OR(AND(OR(I19="Series B",I19="Series C",I19="Series D+"),J19<>"",J19>=TODAY()-730),I19="PE-controlled Growth Mandate",I19="Listed with Growth Profile"),8,IF(OR(I19="Series A",I19="Bootstrapped Profitable",I19="PE-controlled Stable",AND(OR(I19="Series B",I19="Series C",I19="Series D+"),J19<>"",J19<TODAY()-730)),6,IF(OR(I19="Seed",I19="Bootstrapped",I19="Listed Stable",I19="Established Private Flat"),3,0))))) -> 6 | AA19: =IF(N19="Yes",0,IF(A19="",0,IF(COUNTIFS('04_Triggers'!B:B,A19,'04_Triggers'!D:D,">="&(TODAY()-365))>=2,20,IF(COUNTIFS('04_Triggers'!B:B,A19,'04_Triggers'!D:D,">="&(TODAY()-365),'04_Triggers'!G:G,"High")>=1,14,IF(COUNTIFS('04_Triggers'!B:B,A19,'04_Triggers'!D:D,">="&(TODAY()-365))>=1,7,IF(COUNTIFS('04_Triggers'!B:B,A19,'04_Triggers'!D:D,">="&(TODAY()-1095),'04_Triggers'!D:D,"<"&(TODAY()-365))>=1,7,0)))))) -> 20 | AB19: =IF(M19="","",IFERROR(VLOOKUP(M19,Scoring_Lookups!$J$5:$K$16,2,FALSE()),0)) -> 8 | AC19: =IF(O19="","",IFERROR(VLOOKUP(O19,Scoring_Lookups!$M$5:$N$8,2,FALSE()),0)) -> 4 | AD19: =IF(L19="","",IFERROR(VLOOKUP(L19,Scoring_Lookups!$P$5:$Q$9,2,FALSE()),0)) -> 8 | AE19: =IF(AND(P19="",Q19="",R19=""),"",IF(OR(IFERROR(MAX(P19,Q19),0)>=500000,R19="Yes"),10,IF(IFERROR(MAX(P19,Q19),0)>=100000,7,IF(IFERROR(MAX(P19,Q19),0)>=10000,4,0)))) -> 10 | AF19: =IFERROR(N(V19)+N(W19)+N(X19)+N(Y19)+N(Z19)+N(AA19)+N(AB19)+N(AC19)+N(AD19)+N(AE19),0) -> 96 | AG19: =IF(OR(E19="",C19="",G19=""),"Not scored",IF(OR(V19=0,X19=0,Y19=0,N19="Yes"),"DQ Gating","OK")) -> OK | AH19: No | AI19: =IF(AG19="Not scored","",IF(OR(AG19="DQ Gating",AH19="Yes"),"Disqualified",IF(AF19>=80,"Priority 1",IF(AF19>=60,"Priority 2",IF(AF19>=40,"Priority 3","Disqualified"))))) -> Priority 1 | AJ19: =IF(AG19="Not scored","","P1 "&IF(E19="","?",E19)&"="&V19&" | P2 "&IF(F19="","?",F19)&"="&W19&" | P3 "&IF(C19="","?",C19)&"="&X19&" | P4 "&IF(G19="","?",G19)&"="&Y19&" | P5 "&IF(I19="","?",I19)&"="&Z19&" | P6="&AA19&" | P7 "&IF(M19="","?",M19)&"="&AB19&" | P8 "&IF(O19="","?",O19)&"="&AC19&" | P9 "&IF(L19="","?",L19)&"="&AD19&" | P10="&AE19) -> P1 Digital Banking=10 | P2 728=10 | P3 Poland=12 | P4 Credit Institution Licence=8 | P5 PE-controlled Stable=6 | P6=20 | P7 Legacy Processor (Named)=8 | P8 Cloud modern, Not API-first=4 | P9 Scheme Principal=8 | P10=10 | AL19: Prospect | AM19: No | AO19: Live, Migration Window | AP19: =IF(AO19="","Not set",IF(OR(AO19="Q1 2027",AO19="Q2 2027",AO19="Q3 2027",AO19="Q4 2027",AO19="Live, Migration Window"),"OK",IF(AO19="Live, Urgent Need","Deferred","Watch"))) -> OK | AQ19: Consumer
A20: ACC-PL-016 | B20: Twisto Polska | C20: Poland | D20: FinTech | E20: Lending (Consumer) | F20: 100 | G20: BIN Sponsor Agreement In Place | H20: PE-controlled | I20: PE-controlled Growth Mandate | J20: 45153 | K20: TBD | L20: Existing BIN Sponsor Relationship | M20: Marqeta | N20: No | O20: Cloud-native (AWS/Azure/GCP), API-first, AI signals | P20: 100000 | Q20: 250000 | R20: Yes | S20: First-pass agent research | T20: 46216 | U20: 2023 acquired by Turkey Param group; Param publicly targeting Poland with prepaid cards, SME lending, embedded finance; multi-currency Mastercard live; ownership change usually triggers processor review | V20: =IF(E20="","",IFERROR(VLOOKUP(E20,Scoring_Lookups!$A$5:$B$18,2,FALSE()),0)) -> 7 | W20: =IF(F20="","",IF(AND(F20>=50,F20<=1000),10,IF(OR(AND(F20>=20,F20<=49),AND(F20>=1001,F20<=2000)),7,IF(OR(AND(F20>=10,F20<=19),AND(F20>=2001,F20<=5000)),4,0)))) -> 10 | X20: =IF(C20="","",IFERROR(VLOOKUP(C20,Scoring_Lookups!$D$5:$E$35,2,FALSE()),0)) -> 12 | Y20: =IF(G20="","",IFERROR(VLOOKUP(G20,Scoring_Lookups!$G$5:$H$16,2,FALSE()),0)) -> 6 | Z20: =IF(I20="","",IF(OR(I20="Administration/Insolvency",I20="Pending Wind-down",I20="Sanctions Exposure"),0,IF(OR(AND(OR(I20="Series B",I20="Series C",I20="Series D+"),J20<>"",J20>=TODAY()-730),I20="PE-controlled Growth Mandate",I20="Listed with Growth Profile"),8,IF(OR(I20="Series A",I20="Bootstrapped Profitable",I20="PE-controlled Stable",AND(OR(I20="Series B",I20="Series C",I20="Series D+"),J20<>"",J20<TODAY()-730)),6,IF(OR(I20="Seed",I20="Bootstrapped",I20="Listed Stable",I20="Established Private Flat"),3,0))))) -> 8 | AA20: =IF(N20="Yes",0,IF(A20="",0,IF(COUNTIFS('04_Triggers'!B:B,A20,'04_Triggers'!D:D,">="&(TODAY()-365))>=2,20,IF(COUNTIFS('04_Triggers'!B:B,A20,'04_Triggers'!D:D,">="&(TODAY()-365),'04_Triggers'!G:G,"High")>=1,14,IF(COUNTIFS('04_Triggers'!B:B,A20,'04_Triggers'!D:D,">="&(TODAY()-365))>=1,7,IF(COUNTIFS('04_Triggers'!B:B,A20,'04_Triggers'!D:D,">="&(TODAY()-1095),'04_Triggers'!D:D,"<"&(TODAY()-365))>=1,7,0)))))) -> 0 | AB20: =IF(M20="","",IFERROR(VLOOKUP(M20,Scoring_Lookups!$J$5:$K$16,2,FALSE()),0)) -> 8 | AC20: =IF(O20="","",IFERROR(VLOOKUP(O20,Scoring_Lookups!$M$5:$N$8,2,FALSE()),0)) -> 6 | AD20: =IF(L20="","",IFERROR(VLOOKUP(L20,Scoring_Lookups!$P$5:$Q$9,2,FALSE()),0)) -> 8 | AE20: =IF(AND(P20="",Q20="",R20=""),"",IF(OR(IFERROR(MAX(P20,Q20),0)>=500000,R20="Yes"),10,IF(IFERROR(MAX(P20,Q20),0)>=100000,7,IF(IFERROR(MAX(P20,Q20),0)>=10000,4,0)))) -> 10 | AF20: =IFERROR(N(V20)+N(W20)+N(X20)+N(Y20)+N(Z20)+N(AA20)+N(AB20)+N(AC20)+N(AD20)+N(AE20),0) -> 75 | AG20: =IF(OR(E20="",C20="",G20=""),"Not scored",IF(OR(V20=0,X20=0,Y20=0,N20="Yes"),"DQ Gating","OK")) -> OK | AH20: No | AI20: =IF(AG20="Not scored","",IF(OR(AG20="DQ Gating",AH20="Yes"),"Disqualified",IF(AF20>=80,"Priority 1",IF(AF20>=60,"Priority 2",IF(AF20>=40,"Priority 3","Disqualified"))))) -> Priority 2 | AJ20: =IF(AG20="Not scored","","P1 "&IF(E20="","?",E20)&"="&V20&" | P2 "&IF(F20="","?",F20)&"="&W20&" | P3 "&IF(C20="","?",C20)&"="&X20&" | P4 "&IF(G20="","?",G20)&"="&Y20&" | P5 "&IF(I20="","?",I20)&"="&Z20&" | P6="&AA20&" | P7 "&IF(M20="","?",M20)&"="&AB20&" | P8 "&IF(O20="","?",O20)&"="&AC20&" | P9 "&IF(L20="","?",L20)&"="&AD20&" | P10="&AE20) -> P1 Lending (Consumer)=7 | P2 100=10 | P3 Poland=12 | P4 BIN Sponsor Agreement In Place=6 | P5 PE-controlled Growth Mandate=8 | P6=0 | P7 Marqeta=8 | P8 Cloud-native (AWS/Azure/GCP), API-first, AI signals=6 | P9 Existing BIN Sponsor Relationship=8 | P10=10 | AL20: Prospect | AM20: No | AO20: Live, Migration Window | AP20: =IF(AO20="","Not set",IF(OR(AO20="Q1 2027",AO20="Q2 2027",AO20="Q3 2027",AO20="Q4 2027",AO20="Live, Migration Window"),"OK",IF(AO20="Live, Urgent Need","Deferred","Watch"))) -> OK | AQ20: Consumer
A21: ACC-PL-017 | B21: Aasa Polska | C21: Poland | D21: FinTech | E21: Lending (Consumer) | F21: 175 | G21: BIN Sponsor Agreement In Place | H21: PE-controlled | I21: PE-controlled Stable | K21: TBD | L21: Existing BIN Sponsor Relationship | M21: Incumbent Unknown | N21: No | O21: Cloud modern, Not API-first | P21: 50000 | Q21: 100000 | R21: Yes | S21: First-pass agent research | T21: 46216 | U21: Live Karta Aasa virtual credit card (PLN 10k limit, 3% cashback for 3 months); Aasa24 app development; Scandinavian-owned Aasa Group; opaque incumbent | V21: =IF(E21="","",IFERROR(VLOOKUP(E21,Scoring_Lookups!$A$5:$B$18,2,FALSE()),0)) -> 7 | W21: =IF(F21="","",IF(AND(F21>=50,F21<=1000),10,IF(OR(AND(F21>=20,F21<=49),AND(F21>=1001,F21<=2000)),7,IF(OR(AND(F21>=10,F21<=19),AND(F21>=2001,F21<=5000)),4,0)))) -> 10 | X21: =IF(C21="","",IFERROR(VLOOKUP(C21,Scoring_Lookups!$D$5:$E$35,2,FALSE()),0)) -> 12 | Y21: =IF(G21="","",IFERROR(VLOOKUP(G21,Scoring_Lookups!$G$5:$H$16,2,FALSE()),0)) -> 6 | Z21: =IF(I21="","",IF(OR(I21="Administration/Insolvency",I21="Pending Wind-down",I21="Sanctions Exposure"),0,IF(OR(AND(OR(I21="Series B",I21="Series C",I21="Series D+"),J21<>"",J21>=TODAY()-730),I21="PE-controlled Growth Mandate",I21="Listed with Growth Profile"),8,IF(OR(I21="Series A",I21="Bootstrapped Profitable",I21="PE-controlled Stable",AND(OR(I21="Series B",I21="Series C",I21="Series D+"),J21<>"",J21<TODAY()-730)),6,IF(OR(I21="Seed",I21="Bootstrapped",I21="Listed Stable",I21="Established Private Flat"),3,0))))) -> 6 | AA21: =IF(N21="Yes",0,IF(A21="",0,IF(COUNTIFS('04_Triggers'!B:B,A21,'04_Triggers'!D:D,">="&(TODAY()-365))>=2,20,IF(COUNTIFS('04_Triggers'!B:B,A21,'04_Triggers'!D:D,">="&(TODAY()-365),'04_Triggers'!G:G,"High")>=1,14,IF(COUNTIFS('04_Triggers'!B:B,A21,'04_Triggers'!D:D,">="&(TODAY()-365))>=1,7,IF(COUNTIFS('04_Triggers'!B:B,A21,'04_Triggers'!D:D,">="&(TODAY()-1095),'04_Triggers'!D:D,"<"&(TODAY()-365))>=1,7,0)))))) -> 0 | AB21: =IF(M21="","",IFERROR(VLOOKUP(M21,Scoring_Lookups!$J$5:$K$16,2,FALSE()),0)) -> 3 | AC21: =IF(O21="","",IFERROR(VLOOKUP(O21,Scoring_Lookups!$M$5:$N$8,2,FALSE()),0)) -> 4 | AD21: =IF(L21="","",IFERROR(VLOOKUP(L21,Scoring_Lookups!$P$5:$Q$9,2,FALSE()),0)) -> 8 | AE21: =IF(AND(P21="",Q21="",R21=""),"",IF(OR(IFERROR(MAX(P21,Q21),0)>=500000,R21="Yes"),10,IF(IFERROR(MAX(P21,Q21),0)>=100000,7,IF(IFERROR(MAX(P21,Q21),0)>=10000,4,0)))) -> 10 | AF21: =IFERROR(N(V21)+N(W21)+N(X21)+N(Y21)+N(Z21)+N(AA21)+N(AB21)+N(AC21)+N(AD21)+N(AE21),0) -> 66 | AG21: =IF(OR(E21="",C21="",G21=""),"Not scored",IF(OR(V21=0,X21=0,Y21=0,N21="Yes"),"DQ Gating","OK")) -> OK | AH21: No | AI21: =IF(AG21="Not scored","",IF(OR(AG21="DQ Gating",AH21="Yes"),"Disqualified",IF(AF21>=80,"Priority 1",IF(AF21>=60,"Priority 2",IF(AF21>=40,"Priority 3","Disqualified"))))) -> Priority 2 | AJ21: =IF(AG21="Not scored","","P1 "&IF(E21="","?",E21)&"="&V21&" | P2 "&IF(F21="","?",F21)&"="&W21&" | P3 "&IF(C21="","?",C21)&"="&X21&" | P4 "&IF(G21="","?",G21)&"="&Y21&" | P5 "&IF(I21="","?",I21)&"="&Z21&" | P6="&AA21&" | P7 "&IF(M21="","?",M21)&"="&AB21&" | P8 "&IF(O21="","?",O21)&"="&AC21&" | P9 "&IF(L21="","?",L21)&"="&AD21&" | P10="&AE21) -> P1 Lending (Consumer)=7 | P2 175=10 | P3 Poland=12 | P4 BIN Sponsor Agreement In Place=6 | P5 PE-controlled Stable=6 | P6=0 | P7 Incumbent Unknown=3 | P8 Cloud modern, Not API-first=4 | P9 Existing BIN Sponsor Relationship=8 | P10=10 | AL21: Prospect | AM21: No | AO21: Live, Migration Window | AP21: =IF(AO21="","Not set",IF(OR(AO21="Q1 2027",AO21="Q2 2027",AO21="Q3 2027",AO21="Q4 2027",AO21="Live, Migration Window"),"OK",IF(AO21="Live, Urgent Need","Deferred","Watch"))) -> OK | AQ21: Consumer
A22: ACC-PL-018 | B22: Fenige | C22: Poland | D22: FinTech | E22: FX Payments | F22: 81 | G22: Scheme Principal Member | H22: Private | I22: Bootstrapped Profitable | K22: None (direct scheme) | L22: Scheme Principal | M22: In-house Legacy Processor | N22: No | O22: Cloud modern, Not API-first | P22: 30000 | Q22: 100000 | R22: Yes | S22: First-pass agent research | T22: 46216 | U22: KNF PI reg IP42/2017; Visa + Mastercard principal member; Jul 2025 EU grant for Settlement Center project; +201% net sales growth 2025 | V22: =IF(E22="","",IFERROR(VLOOKUP(E22,Scoring_Lookups!$A$5:$B$18,2,FALSE()),0)) -> 7 | W22: =IF(F22="","",IF(AND(F22>=50,F22<=1000),10,IF(OR(AND(F22>=20,F22<=49),AND(F22>=1001,F22<=2000)),7,IF(OR(AND(F22>=10,F22<=19),AND(F22>=2001,F22<=5000)),4,0)))) -> 10 | X22: =IF(C22="","",IFERROR(VLOOKUP(C22,Scoring_Lookups!$D$5:$E$35,2,FALSE()),0)) -> 12 | Y22: =IF(G22="","",IFERROR(VLOOKUP(G22,Scoring_Lookups!$G$5:$H$16,2,FALSE()),0)) -> 8 | Z22: =IF(I22="","",IF(OR(I22="Administration/Insolvency",I22="Pending Wind-down",I22="Sanctions Exposure"),0,IF(OR(AND(OR(I22="Series B",I22="Series C",I22="Series D+"),J22<>"",J22>=TODAY()-730),I22="PE-controlled Growth Mandate",I22="Listed with Growth Profile"),8,IF(OR(I22="Series A",I22="Bootstrapped Profitable",I22="PE-controlled Stable",AND(OR(I22="Series B",I22="Series C",I22="Series D+"),J22<>"",J22<TODAY()-730)),6,IF(OR(I22="Seed",I22="Bootstrapped",I22="Listed Stable",I22="Established Private Flat"),3,0))))) -> 6 | AA22: =IF(N22="Yes",0,IF(A22="",0,IF(COUNTIFS('04_Triggers'!B:B,A22,'04_Triggers'!D:D,">="&(TODAY()-365))>=2,20,IF(COUNTIFS('04_Triggers'!B:B,A22,'04_Triggers'!D:D,">="&(TODAY()-365),'04_Triggers'!G:G,"High")>=1,14,IF(COUNTIFS('04_Triggers'!B:B,A22,'04_Triggers'!D:D,">="&(TODAY()-365))>=1,7,IF(COUNTIFS('04_Triggers'!B:B,A22,'04_Triggers'!D:D,">="&(TODAY()-1095),'04_Triggers'!D:D,"<"&(TODAY()-365))>=1,7,0)))))) -> 7 | AB22: =IF(M22="","",IFERROR(VLOOKUP(M22,Scoring_Lookups!$J$5:$K$16,2,FALSE()),0)) -> 8 | AC22: =IF(O22="","",IFERROR(VLOOKUP(O22,Scoring_Lookups!$M$5:$N$8,2,FALSE()),0)) -> 4 | AD22: =IF(L22="","",IFERROR(VLOOKUP(L22,Scoring_Lookups!$P$5:$Q$9,2,FALSE()),0)) -> 8 | AE22: =IF(AND(P22="",Q22="",R22=""),"",IF(OR(IFERROR(MAX(P22,Q22),0)>=500000,R22="Yes"),10,IF(IFERROR(MAX(P22,Q22),0)>=100000,7,IF(IFERROR(MAX(P22,Q22),0)>=10000,4,0)))) -> 10 | AF22: =IFERROR(N(V22)+N(W22)+N(X22)+N(Y22)+N(Z22)+N(AA22)+N(AB22)+N(AC22)+N(AD22)+N(AE22),0) -> 80 | AG22: =IF(OR(E22="",C22="",G22=""),"Not scored",IF(OR(V22=0,X22=0,Y22=0,N22="Yes"),"DQ Gating","OK")) -> OK | AH22: No | AI22: =IF(AG22="Not scored","",IF(OR(AG22="DQ Gating",AH22="Yes"),"Disqualified",IF(AF22>=80,"Priority 1",IF(AF22>=60,"Priority 2",IF(AF22>=40,"Priority 3","Disqualified"))))) -> Priority 1 | AJ22: =IF(AG22="Not scored","","P1 "&IF(E22="","?",E22)&"="&V22&" | P2 "&IF(F22="","?",F22)&"="&W22&" | P3 "&IF(C22="","?",C22)&"="&X22&" | P4 "&IF(G22="","?",G22)&"="&Y22&" | P5 "&IF(I22="","?",I22)&"="&Z22&" | P6="&AA22&" | P7 "&IF(M22="","?",M22)&"="&AB22&" | P8 "&IF(O22="","?",O22)&"="&AC22&" | P9 "&IF(L22="","?",L22)&"="&AD22&" | P10="&AE22) -> P1 FX Payments=7 | P2 81=10 | P3 Poland=12 | P4 Scheme Principal Member=8 | P5 Bootstrapped Profitable=6 | P6=7 | P7 In-house Legacy Processor=8 | P8 Cloud modern, Not API-first=4 | P9 Scheme Principal=8 | P10=10 | AL22: Prospect | AM22: No | AO22: Live, Migration Window | AP22: =IF(AO22="","Not set",IF(OR(AO22="Q1 2027",AO22="Q2 2027",AO22="Q3 2027",AO22="Q4 2027",AO22="Live, Migration Window"),"OK",IF(AO22="Live, Urgent Need","Deferred","Watch"))) -> OK | AQ22: Consumer
A23: ACC-PL-019 | B23: ITCARD (Planet Pay) | C23: Poland | D23: FinTech | E23: Payments | F23: 470 | G23: Scheme Principal Member | H23: Private | I23: PE-controlled Growth Mandate | J23: 45901 | K23: None (own scheme licence) | L23: Scheme Principal | M23: In-house Legacy Processor | N23: No | O23: Cloud modern, Not API-first | P23: 500000 | Q23: 800000 | R23: Yes | S23: First-pass agent research | T23: 46216 | U23: Sep 2025 SIBS (Portugal) announced acquisition, pending regulatory approval; 7,000+ POS terminals; full Visa/Mastercard issuing; M&A creates decision window - approach pre-close | V23: =IF(E23="","",IFERROR(VLOOKUP(E23,Scoring_Lookups!$A$5:$B$18,2,FALSE()),0)) -> 4 | W23: =IF(F23="","",IF(AND(F23>=50,F23<=1000),10,IF(OR(AND(F23>=20,F23<=49),AND(F23>=1001,F23<=2000)),7,IF(OR(AND(F23>=10,F23<=19),AND(F23>=2001,F23<=5000)),4,0)))) -> 10 | X23: =IF(C23="","",IFERROR(VLOOKUP(C23,Scoring_Lookups!$D$5:$E$35,2,FALSE()),0)) -> 12 | Y23: =IF(G23="","",IFERROR(VLOOKUP(G23,Scoring_Lookups!$G$5:$H$16,2,FALSE()),0)) -> 8 | Z23: =IF(I23="","",IF(OR(I23="Administration/Insolvency",I23="Pending Wind-down",I23="Sanctions Exposure"),0,IF(OR(AND(OR(I23="Series B",I23="Series C",I23="Series D+"),J23<>"",J23>=TODAY()-730),I23="PE-controlled Growth Mandate",I23="Listed with Growth Profile"),8,IF(OR(I23="Series A",I23="Bootstrapped Profitable",I23="PE-controlled Stable",AND(OR(I23="Series B",I23="Series C",I23="Series D+"),J23<>"",J23<TODAY()-730)),6,IF(OR(I23="Seed",I23="Bootstrapped",I23="Listed Stable",I23="Established Private Flat"),3,0))))) -> 8 | AA23: =IF(N23="Yes",0,IF(A23="",0,IF(COUNTIFS('04_Triggers'!B:B,A23,'04_Triggers'!D:D,">="&(TODAY()-365))>=2,20,IF(COUNTIFS('04_Triggers'!B:B,A23,'04_Triggers'!D:D,">="&(TODAY()-365),'04_Triggers'!G:G,"High")>=1,14,IF(COUNTIFS('04_Triggers'!B:B,A23,'04_Triggers'!D:D,">="&(TODAY()-365))>=1,7,IF(COUNTIFS('04_Triggers'!B:B,A23,'04_Triggers'!D:D,">="&(TODAY()-1095),'04_Triggers'!D:D,"<"&(TODAY()-365))>=1,7,0)))))) -> 14 | AB23: =IF(M23="","",IFERROR(VLOOKUP(M23,Scoring_Lookups!$J$5:$K$16,2,FALSE()),0)) -> 8 | AC23: =IF(O23="","",IFERROR(VLOOKUP(O23,Scoring_Lookups!$M$5:$N$8,2,FALSE()),0)) -> 4 | AD23: =IF(L23="","",IFERROR(VLOOKUP(L23,Scoring_Lookups!$P$5:$Q$9,2,FALSE()),0)) -> 8 | AE23: =IF(AND(P23="",Q23="",R23=""),"",IF(OR(IFERROR(MAX(P23,Q23),0)>=500000,R23="Yes"),10,IF(IFERROR(MAX(P23,Q23),0)>=100000,7,IF(IFERROR(MAX(P23,Q23),0)>=10000,4,0)))) -> 10 | AF23: =IFERROR(N(V23)+N(W23)+N(X23)+N(Y23)+N(Z23)+N(AA23)+N(AB23)+N(AC23)+N(AD23)+N(AE23),0) -> 86 | AG23: =IF(OR(E23="",C23="",G23=""),"Not scored",IF(OR(V23=0,X23=0,Y23=0,N23="Yes"),"DQ Gating","OK")) -> OK | AH23: No | AI23: =IF(AG23="Not scored","",IF(OR(AG23="DQ Gating",AH23="Yes"),"Disqualified",IF(AF23>=80,"Priority 1",IF(AF23>=60,"Priority 2",IF(AF23>=40,"Priority 3","Disqualified"))))) -> Priority 1 | AJ23: =IF(AG23="Not scored","","P1 "&IF(E23="","?",E23)&"="&V23&" | P2 "&IF(F23="","?",F23)&"="&W23&" | P3 "&IF(C23="","?",C23)&"="&X23&" | P4 "&IF(G23="","?",G23)&"="&Y23&" | P5 "&IF(I23="","?",I23)&"="&Z23&" | P6="&AA23&" | P7 "&IF(M23="","?",M23)&"="&AB23&" | P8 "&IF(O23="","?",O23)&"="&AC23&" | P9 "&IF(L23="","?",L23)&"="&AD23&" | P10="&AE23) -> P1 Payments=4 | P2 470=10 | P3 Poland=12 | P4 Scheme Principal Member=8 | P5 PE-controlled Growth Mandate=8 | P6=14 | P7 In-house Legacy Processor=8 | P8 Cloud modern, Not API-first=4 | P9 Scheme Principal=8 | P10=10 | AL23: Prospect | AM23: No | AO23: Live, Migration Window | AP23: =IF(AO23="","Not set",IF(OR(AO23="Q1 2027",AO23="Q2 2027",AO23="Q3 2027",AO23="Q4 2027",AO23="Live, Migration Window"),"OK",IF(AO23="Live, Urgent Need","Deferred","Watch"))) -> OK | AQ23: Commercial and B2B
A24: ACC-PL-020 | B24: PayU Polska | C24: Poland | D24: FinTech | E24: Payments | F24: 250 | G24: PI Licence | H24: PE-controlled | I24: PE-controlled Stable | K24: TBD | L24: Existing BIN Sponsor Relationship | M24: Smaller/Less-known Processor | N24: No | O24: Cloud modern, Not API-first | P24: 100000 | Q24: 250000 | R24: Yes | S24: First-pass agent research | T24: 46216 | U24: Twisto virtual + physical Mastercard live in Poland; PayU Credit ~$1B volume, 2,500+ merchants; Polish BNPL market $1.74B projected 2025; Prosus parent - decision autonomy on processor selection to verify | V24: =IF(E24="","",IFERROR(VLOOKUP(E24,Scoring_Lookups!$A$5:$B$18,2,FALSE()),0)) -> 4 | W24: =IF(F24="","",IF(AND(F24>=50,F24<=1000),10,IF(OR(AND(F24>=20,F24<=49),AND(F24>=1001,F24<=2000)),7,IF(OR(AND(F24>=10,F24<=19),AND(F24>=2001,F24<=5000)),4,0)))) -> 10 | X24: =IF(C24="","",IFERROR(VLOOKUP(C24,Scoring_Lookups!$D$5:$E$35,2,FALSE()),0)) -> 12 | Y24: =IF(G24="","",IFERROR(VLOOKUP(G24,Scoring_Lookups!$G$5:$H$16,2,FALSE()),0)) -> 6 | Z24: =IF(I24="","",IF(OR(I24="Administration/Insolvency",I24="Pending Wind-down",I24="Sanctions Exposure"),0,IF(OR(AND(OR(I24="Series B",I24="Series C",I24="Series D+"),J24<>"",J24>=TODAY()-730),I24="PE-controlled Growth Mandate",I24="Listed with Growth Profile"),8,IF(OR(I24="Series A",I24="Bootstrapped Profitable",I24="PE-controlled Stable",AND(OR(I24="Series B",I24="Series C",I24="Series D+"),J24<>"",J24<TODAY()-730)),6,IF(OR(I24="Seed",I24="Bootstrapped",I24="Listed Stable",I24="Established Private Flat"),3,0))))) -> 6 | AA24: =IF(N24="Yes",0,IF(A24="",0,IF(COUNTIFS('04_Triggers'!B:B,A24,'04_Triggers'!D:D,">="&(TODAY()-365))>=2,20,IF(COUNTIFS('04_Triggers'!B:B,A24,'04_Triggers'!D:D,">="&(TODAY()-365),'04_Triggers'!G:G,"High")>=1,14,IF(COUNTIFS('04_Triggers'!B:B,A24,'04_Triggers'!D:D,">="&(TODAY()-365))>=1,7,IF(COUNTIFS('04_Triggers'!B:B,A24,'04_Triggers'!D:D,">="&(TODAY()-1095),'04_Triggers'!D:D,"<"&(TODAY()-365))>=1,7,0)))))) -> 0 | AB24: =IF(M24="","",IFERROR(VLOOKUP(M24,Scoring_Lookups!$J$5:$K$16,2,FALSE()),0)) -> 6 | AC24: =IF(O24="","",IFERROR(VLOOKUP(O24,Scoring_Lookups!$M$5:$N$8,2,FALSE()),0)) -> 4 | AD24: =IF(L24="","",IFERROR(VLOOKUP(L24,Scoring_Lookups!$P$5:$Q$9,2,FALSE()),0)) -> 8 | AE24: =IF(AND(P24="",Q24="",R24=""),"",IF(OR(IFERROR(MAX(P24,Q24),0)>=500000,R24="Yes"),10,IF(IFERROR(MAX(P24,Q24),0)>=100000,7,IF(IFERROR(MAX(P24,Q24),0)>=10000,4,0)))) -> 10 | AF24: =IFERROR(N(V24)+N(W24)+N(X24)+N(Y24)+N(Z24)+N(AA24)+N(AB24)+N(AC24)+N(AD24)+N(AE24),0) -> 66 | AG24: =IF(OR(E24="",C24="",G24=""),"Not scored",IF(OR(V24=0,X24=0,Y24=0,N24="Yes"),"DQ Gating","OK")) -> OK | AH24: No | AI24: =IF(AG24="Not scored","",IF(OR(AG24="DQ Gating",AH24="Yes"),"Disqualified",IF(AF24>=80,"Priority 1",IF(AF24>=60,"Priority 2",IF(AF24>=40,"Priority 3","Disqualified"))))) -> Priority 2 | AJ24: =IF(AG24="Not scored","","P1 "&IF(E24="","?",E24)&"="&V24&" | P2 "&IF(F24="","?",F24)&"="&W24&" | P3 "&IF(C24="","?",C24)&"="&X24&" | P4 "&IF(G24="","?",G24)&"="&Y24&" | P5 "&IF(I24="","?",I24)&"="&Z24&" | P6="&AA24&" | P7 "&IF(M24="","?",M24)&"="&AB24&" | P8 "&IF(O24="","?",O24)&"="&AC24&" | P9 "&IF(L24="","?",L24)&"="&AD24&" | P10="&AE24) -> P1 Payments=4 | P2 250=10 | P3 Poland=12 | P4 PI Licence=6 | P5 PE-controlled Stable=6 | P6=0 | P7 Smaller/Less-known Processor=6 | P8 Cloud modern, Not API-first=4 | P9 Existing BIN Sponsor Relationship=8 | P10=10 | AL24: Prospect | AM24: No | AO24: Live, Migration Window | AP24: =IF(AO24="","Not set",IF(OR(AO24="Q1 2027",AO24="Q2 2027",AO24="Q3 2027",AO24="Q4 2027",AO24="Live, Migration Window"),"OK",IF(AO24="Live, Urgent Need","Deferred","Watch"))) -> OK | AQ24: Consumer
A25: ACC-PL-021 | B25: Provident Polska | C25: Poland | D25: FinTech | E25: Lending (Consumer) | F25: 848 | G25: BIN Sponsor Agreement In Place | H25: Listed | I25: Listed Stable | K25: TBD | L25: Existing BIN Sponsor Relationship | M25: Incumbent Unknown | N25: No | O25: Cloud modern, Not API-first | P25: 500000 | Q25: 700000 | R25: Yes | S25: First-pass agent research | T25: 46216 | U25: 4.5M+ historical customers; PLN 1k-30k credit cards + installment loans; IPF plc parent group London; large Polish operational entity; IPF decision leverage question | V25: =IF(E25="","",IFERROR(VLOOKUP(E25,Scoring_Lookups!$A$5:$B$18,2,FALSE()),0)) -> 7 | W25: =IF(F25="","",IF(AND(F25>=50,F25<=1000),10,IF(OR(AND(F25>=20,F25<=49),AND(F25>=1001,F25<=2000)),7,IF(OR(AND(F25>=10,F25<=19),AND(F25>=2001,F25<=5000)),4,0)))) -> 10 | X25: =IF(C25="","",IFERROR(VLOOKUP(C25,Scoring_Lookups!$D$5:$E$35,2,FALSE()),0)) -> 12 | Y25: =IF(G25="","",IFERROR(VLOOKUP(G25,Scoring_Lookups!$G$5:$H$16,2,FALSE()),0)) -> 6 | Z25: =IF(I25="","",IF(OR(I25="Administration/Insolvency",I25="Pending Wind-down",I25="Sanctions Exposure"),0,IF(OR(AND(OR(I25="Series B",I25="Series C",I25="Series D+"),J25<>"",J25>=TODAY()-730),I25="PE-controlled Growth Mandate",I25="Listed with Growth Profile"),8,IF(OR(I25="Series A",I25="Bootstrapped Profitable",I25="PE-controlled Stable",AND(OR(I25="Series B",I25="Series C",I25="Series D+"),J25<>"",J25<TODAY()-730)),6,IF(OR(I25="Seed",I25="Bootstrapped",I25="Listed Stable",I25="Established Private Flat"),3,0))))) -> 3 | AA25: =IF(N25="Yes",0,IF(A25="",0,IF(COUNTIFS('04_Triggers'!B:B,A25,'04_Triggers'!D:D,">="&(TODAY()-365))>=2,20,IF(COUNTIFS('04_Triggers'!B:B,A25,'04_Triggers'!D:D,">="&(TODAY()-365),'04_Triggers'!G:G,"High")>=1,14,IF(COUNTIFS('04_Triggers'!B:B,A25,'04_Triggers'!D:D,">="&(TODAY()-365))>=1,7,IF(COUNTIFS('04_Triggers'!B:B,A25,'04_Triggers'!D:D,">="&(TODAY()-1095),'04_Triggers'!D:D,"<"&(TODAY()-365))>=1,7,0)))))) -> 0 | AB25: =IF(M25="","",IFERROR(VLOOKUP(M25,Scoring_Lookups!$J$5:$K$16,2,FALSE()),0)) -> 3 | AC25: =IF(O25="","",IFERROR(VLOOKUP(O25,Scoring_Lookups!$M$5:$N$8,2,FALSE()),0)) -> 4 | AD25: =IF(L25="","",IFERROR(VLOOKUP(L25,Scoring_Lookups!$P$5:$Q$9,2,FALSE()),0)) -> 8 | AE25: =IF(AND(P25="",Q25="",R25=""),"",IF(OR(IFERROR(MAX(P25,Q25),0)>=500000,R25="Yes"),10,IF(IFERROR(MAX(P25,Q25),0)>=100000,7,IF(IFERROR(MAX(P25,Q25),0)>=10000,4,0)))) -> 10 | AF25: =IFERROR(N(V25)+N(W25)+N(X25)+N(Y25)+N(Z25)+N(AA25)+N(AB25)+N(AC25)+N(AD25)+N(AE25),0) -> 63 | AG25: =IF(OR(E25="",C25="",G25=""),"Not scored",IF(OR(V25=0,X25=0,Y25=0,N25="Yes"),"DQ Gating","OK")) -> OK | AH25: No | AI25: =IF(AG25="Not scored","",IF(OR(AG25="DQ Gating",AH25="Yes"),"Disqualified",IF(AF25>=80,"Priority 1",IF(AF25>=60,"Priority 2",IF(AF25>=40,"Priority 3","Disqualified"))))) -> Priority 2 | AJ25: =IF(AG25="Not scored","","P1 "&IF(E25="","?",E25)&"="&V25&" | P2 "&IF(F25="","?",F25)&"="&W25&" | P3 "&IF(C25="","?",C25)&"="&X25&" | P4 "&IF(G25="","?",G25)&"="&Y25&" | P5 "&IF(I25="","?",I25)&"="&Z25&" | P6="&AA25&" | P7 "&IF(M25="","?",M25)&"="&AB25&" | P8 "&IF(O25="","?",O25)&"="&AC25&" | P9 "&IF(L25="","?",L25)&"="&AD25&" | P10="&AE25) -> P1 Lending (Consumer)=7 | P2 848=10 | P3 Poland=12 | P4 BIN Sponsor Agreement In Place=6 | P5 Listed Stable=3 | P6=0 | P7 Incumbent Unknown=3 | P8 Cloud modern, Not API-first=4 | P9 Existing BIN Sponsor Relationship=8 | P10=10 | AL25: Prospect | AM25: No | AO25: Live, Migration Window | AP25: =IF(AO25="","Not set",IF(OR(AO25="Q1 2027",AO25="Q2 2027",AO25="Q3 2027",AO25="Q4 2027",AO25="Live, Migration Window"),"OK",IF(AO25="Live, Urgent Need","Deferred","Watch"))) -> OK | AQ25: Consumer
A26: ACC-PL-022 | B26: Kanga Exchange | C26: Poland | D26: FinTech | E26: Crypto | F26: 78 | G26: BIN Sponsor Agreement In Place | H26: Private | I26: Bootstrapped Profitable | K26: Zen.com | L26: Existing BIN Sponsor Relationship | M26: Smaller/Less-known Processor | N26: No | O26: Cloud modern, Not API-first | P26: 30000 | Q26: 100000 | R26: No | S26: First-pass agent research | T26: 46216 | U26: MiCA Class 3 CASP granted 18 Jun 2026 via Bank of Latvia, passportable EU-wide; live Kanga Card via Zen.com; 250+ physical exchange kiosks; Polish MiCA law vetoed 3x by President - structural migration under way | V26: =IF(E26="","",IFERROR(VLOOKUP(E26,Scoring_Lookups!$A$5:$B$18,2,FALSE()),0)) -> 4 | W26: =IF(F26="","",IF(AND(F26>=50,F26<=1000),10,IF(OR(AND(F26>=20,F26<=49),AND(F26>=1001,F26<=2000)),7,IF(OR(AND(F26>=10,F26<=19),AND(F26>=2001,F26<=5000)),4,0)))) -> 10 | X26: =IF(C26="","",IFERROR(VLOOKUP(C26,Scoring_Lookups!$D$5:$E$35,2,FALSE()),0)) -> 12 | Y26: =IF(G26="","",IFERROR(VLOOKUP(G26,Scoring_Lookups!$G$5:$H$16,2,FALSE()),0)) -> 6 | Z26: =IF(I26="","",IF(OR(I26="Administration/Insolvency",I26="Pending Wind-down",I26="Sanctions Exposure"),0,IF(OR(AND(OR(I26="Series B",I26="Series C",I26="Series D+"),J26<>"",J26>=TODAY()-730),I26="PE-controlled Growth Mandate",I26="Listed with Growth Profile"),8,IF(OR(I26="Series A",I26="Bootstrapped Profitable",I26="PE-controlled Stable",AND(OR(I26="Series B",I26="Series C",I26="Series D+"),J26<>"",J26<TODAY()-730)),6,IF(OR(I26="Seed",I26="Bootstrapped",I26="Listed Stable",I26="Established Private Flat"),3,0))))) -> 6 | AA26: =IF(N26="Yes",0,IF(A26="",0,IF(COUNTIFS('04_Triggers'!B:B,A26,'04_Triggers'!D:D,">="&(TODAY()-365))>=2,20,IF(COUNTIFS('04_Triggers'!B:B,A26,'04_Triggers'!D:D,">="&(TODAY()-365),'04_Triggers'!G:G,"High")>=1,14,IF(COUNTIFS('04_Triggers'!B:B,A26,'04_Triggers'!D:D,">="&(TODAY()-365))>=1,7,IF(COUNTIFS('04_Triggers'!B:B,A26,'04_Triggers'!D:D,">="&(TODAY()-1095),'04_Triggers'!D:D,"<"&(TODAY()-365))>=1,7,0)))))) -> 14 | AB26: =IF(M26="","",IFERROR(VLOOKUP(M26,Scoring_Lookups!$J$5:$K$16,2,FALSE()),0)) -> 6 | AC26: =IF(O26="","",IFERROR(VLOOKUP(O26,Scoring_Lookups!$M$5:$N$8,2,FALSE()),0)) -> 4 | AD26: =IF(L26="","",IFERROR(VLOOKUP(L26,Scoring_Lookups!$P$5:$Q$9,2,FALSE()),0)) -> 8 | AE26: =IF(AND(P26="",Q26="",R26=""),"",IF(OR(IFERROR(MAX(P26,Q26),0)>=500000,R26="Yes"),10,IF(IFERROR(MAX(P26,Q26),0)>=100000,7,IF(IFERROR(MAX(P26,Q26),0)>=10000,4,0)))) -> 7 | AF26: =IFERROR(N(V26)+N(W26)+N(X26)+N(Y26)+N(Z26)+N(AA26)+N(AB26)+N(AC26)+N(AD26)+N(AE26),0) -> 77 | AG26: =IF(OR(E26="",C26="",G26=""),"Not scored",IF(OR(V26=0,X26=0,Y26=0,N26="Yes"),"DQ Gating","OK")) -> OK | AH26: No | AI26: =IF(AG26="Not scored","",IF(OR(AG26="DQ Gating",AH26="Yes"),"Disqualified",IF(AF26>=80,"Priority 1",IF(AF26>=60,"Priority 2",IF(AF26>=40,"Priority 3","Disqualified"))))) -> Priority 2 | AJ26: =IF(AG26="Not scored","","P1 "&IF(E26="","?",E26)&"="&V26&" | P2 "&IF(F26="","?",F26)&"="&W26&" | P3 "&IF(C26="","?",C26)&"="&X26&" | P4 "&IF(G26="","?",G26)&"="&Y26&" | P5 "&IF(I26="","?",I26)&"="&Z26&" | P6="&AA26&" | P7 "&IF(M26="","?",M26)&"="&AB26&" | P8 "&IF(O26="","?",O26)&"="&AC26&" | P9 "&IF(L26="","?",L26)&"="&AD26&" | P10="&AE26) -> P1 Crypto=4 | P2 78=10 | P3 Poland=12 | P4 BIN Sponsor Agreement In Place=6 | P5 Bootstrapped Profitable=6 | P6=14 | P7 Smaller/Less-known Processor=6 | P8 Cloud modern, Not API-first=4 | P9 Existing BIN Sponsor Relationship=8 | P10=7 | AL26: Prospect | AM26: No | AO26: Live, Migration Window | AP26: =IF(AO26="","Not set",IF(OR(AO26="Q1 2027",AO26="Q2 2027",AO26="Q3 2027",AO26="Q4 2027",AO26="Live, Migration Window"),"OK",IF(AO26="Live, Urgent Need","Deferred","Watch"))) -> OK | AQ26: Consumer
A27: ACC-PL-023 | B27: Verestro | C27: Poland | D27: FinTech | E27: BaaS | F27: 150 | G27: BIN Sponsor Agreement In Place | H27: Private | I27: Bootstrapped Profitable | K27: Multiple (Quicko defunct) | L27: Existing BIN Sponsor Relationship | M27: Hybrid In-house Solution | N27: No | O27: Cloud-native (AWS/Azure/GCP), API-first, AI signals | P27: 200000 | Q27: 400000 | R27: Yes | S27: First-pass agent research | T27: 46216 | U27: Quicko licence revoked Jan 2026 - Verestro largest Polish BIN partner offline, actively hunting alternatives; 100k+ Mastercards issued with Quicko in Q1 2024; Mastercard shareholder since 2020; POSITIONING FLAG - potential channel partner or competitor | V27: =IF(E27="","",IFERROR(VLOOKUP(E27,Scoring_Lookups!$A$5:$B$18,2,FALSE()),0)) -> 7 | W27: =IF(F27="","",IF(AND(F27>=50,F27<=1000),10,IF(OR(AND(F27>=20,F27<=49),AND(F27>=1001,F27<=2000)),7,IF(OR(AND(F27>=10,F27<=19),AND(F27>=2001,F27<=5000)),4,0)))) -> 10 | X27: =IF(C27="","",IFERROR(VLOOKUP(C27,Scoring_Lookups!$D$5:$E$35,2,FALSE()),0)) -> 12 | Y27: =IF(G27="","",IFERROR(VLOOKUP(G27,Scoring_Lookups!$G$5:$H$16,2,FALSE()),0)) -> 6 | Z27: =IF(I27="","",IF(OR(I27="Administration/Insolvency",I27="Pending Wind-down",I27="Sanctions Exposure"),0,IF(OR(AND(OR(I27="Series B",I27="Series C",I27="Series D+"),J27<>"",J27>=TODAY()-730),I27="PE-controlled Growth Mandate",I27="Listed with Growth Profile"),8,IF(OR(I27="Series A",I27="Bootstrapped Profitable",I27="PE-controlled Stable",AND(OR(I27="Series B",I27="Series C",I27="Series D+"),J27<>"",J27<TODAY()-730)),6,IF(OR(I27="Seed",I27="Bootstrapped",I27="Listed Stable",I27="Established Private Flat"),3,0))))) -> 6 | AA27: =IF(N27="Yes",0,IF(A27="",0,IF(COUNTIFS('04_Triggers'!B:B,A27,'04_Triggers'!D:D,">="&(TODAY()-365))>=2,20,IF(COUNTIFS('04_Triggers'!B:B,A27,'04_Triggers'!D:D,">="&(TODAY()-365),'04_Triggers'!G:G,"High")>=1,14,IF(COUNTIFS('04_Triggers'!B:B,A27,'04_Triggers'!D:D,">="&(TODAY()-365))>=1,7,IF(COUNTIFS('04_Triggers'!B:B,A27,'04_Triggers'!D:D,">="&(TODAY()-1095),'04_Triggers'!D:D,"<"&(TODAY()-365))>=1,7,0)))))) -> 14 | AB27: =IF(M27="","",IFERROR(VLOOKUP(M27,Scoring_Lookups!$J$5:$K$16,2,FALSE()),0)) -> 6 | AC27: =IF(O27="","",IFERROR(VLOOKUP(O27,Scoring_Lookups!$M$5:$N$8,2,FALSE()),0)) -> 6 | AD27: =IF(L27="","",IFERROR(VLOOKUP(L27,Scoring_Lookups!$P$5:$Q$9,2,FALSE()),0)) -> 8 | AE27: =IF(AND(P27="",Q27="",R27=""),"",IF(OR(IFERROR(MAX(P27,Q27),0)>=500000,R27="Yes"),10,IF(IFERROR(MAX(P27,Q27),0)>=100000,7,IF(IFERROR(MAX(P27,Q27),0)>=10000,4,0)))) -> 10 | AF27: =IFERROR(N(V27)+N(W27)+N(X27)+N(Y27)+N(Z27)+N(AA27)+N(AB27)+N(AC27)+N(AD27)+N(AE27),0) -> 85 | AG27: =IF(OR(E27="",C27="",G27=""),"Not scored",IF(OR(V27=0,X27=0,Y27=0,N27="Yes"),"DQ Gating","OK")) -> OK | AH27: No | AI27: =IF(AG27="Not scored","",IF(OR(AG27="DQ Gating",AH27="Yes"),"Disqualified",IF(AF27>=80,"Priority 1",IF(AF27>=60,"Priority 2",IF(AF27>=40,"Priority 3","Disqualified"))))) -> Priority 1 | AJ27: =IF(AG27="Not scored","","P1 "&IF(E27="","?",E27)&"="&V27&" | P2 "&IF(F27="","?",F27)&"="&W27&" | P3 "&IF(C27="","?",C27)&"="&X27&" | P4 "&IF(G27="","?",G27)&"="&Y27&" | P5 "&IF(I27="","?",I27)&"="&Z27&" | P6="&AA27&" | P7 "&IF(M27="","?",M27)&"="&AB27&" | P8 "&IF(O27="","?",O27)&"="&AC27&" | P9 "&IF(L27="","?",L27)&"="&AD27&" | P10="&AE27) -> P1 BaaS=7 | P2 150=10 | P3 Poland=12 | P4 BIN Sponsor Agreement In Place=6 | P5 Bootstrapped Profitable=6 | P6=14 | P7 Hybrid In-house Solution=6 | P8 Cloud-native (AWS/Azure/GCP), API-first, AI signals=6 | P9 Existing BIN Sponsor Relationship=8 | P10=10 | AL27: Prospect | AM27: No | AO27: Live, Migration Window | AP27: =IF(AO27="","Not set",IF(OR(AO27="Q1 2027",AO27="Q2 2027",AO27="Q3 2027",AO27="Q4 2027",AO27="Live, Migration Window"),"OK",IF(AO27="Live, Urgent Need","Deferred","Watch"))) -> OK | AQ27: Commercial and B2B
A28: ACC-PL-024 | B28: Zen.com | C28: Poland | D28: FinTech | E28: BaaS | F28: 600 | G28: EMI Licence | H28: Private | I28: Bootstrapped Profitable | K28: None (own BIN) | L28: Scheme Principal | M28: In-house Legacy Processor | N28: No | O28: Cloud-native (AWS/Azure/GCP), API-first, AI signals | P28: 200000 | Q28: 500000 | R28: Yes | S28: First-pass agent research | T28: 46216 | U28: EMI issued by Bank of Lithuania 24 May 2018; BIN-Sponsoring line launched 2025 (Flexee first client, STRABAG/Erste Polska/Coca-Cola HBC downstream); +250 Poland hires 2025; POSITIONING FLAG - potential BaaS competitor, decision authority in Lithuania | V28: =IF(E28="","",IFERROR(VLOOKUP(E28,Scoring_Lookups!$A$5:$B$18,2,FALSE()),0)) -> 7 | W28: =IF(F28="","",IF(AND(F28>=50,F28<=1000),10,IF(OR(AND(F28>=20,F28<=49),AND(F28>=1001,F28<=2000)),7,IF(OR(AND(F28>=10,F28<=19),AND(F28>=2001,F28<=5000)),4,0)))) -> 10 | X28: =IF(C28="","",IFERROR(VLOOKUP(C28,Scoring_Lookups!$D$5:$E$35,2,FALSE()),0)) -> 12 | Y28: =IF(G28="","",IFERROR(VLOOKUP(G28,Scoring_Lookups!$G$5:$H$16,2,FALSE()),0)) -> 8 | Z28: =IF(I28="","",IF(OR(I28="Administration/Insolvency",I28="Pending Wind-down",I28="Sanctions Exposure"),0,IF(OR(AND(OR(I28="Series B",I28="Series C",I28="Series D+"),J28<>"",J28>=TODAY()-730),I28="PE-controlled Growth Mandate",I28="Listed with Growth Profile"),8,IF(OR(I28="Series A",I28="Bootstrapped Profitable",I28="PE-controlled Stable",AND(OR(I28="Series B",I28="Series C",I28="Series D+"),J28<>"",J28<TODAY()-730)),6,IF(OR(I28="Seed",I28="Bootstrapped",I28="Listed Stable",I28="Established Private Flat"),3,0))))) -> 6 | AA28: =IF(N28="Yes",0,IF(A28="",0,IF(COUNTIFS('04_Triggers'!B:B,A28,'04_Triggers'!D:D,">="&(TODAY()-365))>=2,20,IF(COUNTIFS('04_Triggers'!B:B,A28,'04_Triggers'!D:D,">="&(TODAY()-365),'04_Triggers'!G:G,"High")>=1,14,IF(COUNTIFS('04_Triggers'!B:B,A28,'04_Triggers'!D:D,">="&(TODAY()-365))>=1,7,IF(COUNTIFS('04_Triggers'!B:B,A28,'04_Triggers'!D:D,">="&(TODAY()-1095),'04_Triggers'!D:D,"<"&(TODAY()-365))>=1,7,0)))))) -> 7 | AB28: =IF(M28="","",IFERROR(VLOOKUP(M28,Scoring_Lookups!$J$5:$K$16,2,FALSE()),0)) -> 8 | AC28: =IF(O28="","",IFERROR(VLOOKUP(O28,Scoring_Lookups!$M$5:$N$8,2,FALSE()),0)) -> 6 | AD28: =IF(L28="","",IFERROR(VLOOKUP(L28,Scoring_Lookups!$P$5:$Q$9,2,FALSE()),0)) -> 8 | AE28: =IF(AND(P28="",Q28="",R28=""),"",IF(OR(IFERROR(MAX(P28,Q28),0)>=500000,R28="Yes"),10,IF(IFERROR(MAX(P28,Q28),0)>=100000,7,IF(IFERROR(MAX(P28,Q28),0)>=10000,4,0)))) -> 10 | AF28: =IFERROR(N(V28)+N(W28)+N(X28)+N(Y28)+N(Z28)+N(AA28)+N(AB28)+N(AC28)+N(AD28)+N(AE28),0) -> 82 | AG28: =IF(OR(E28="",C28="",G28=""),"Not scored",IF(OR(V28=0,X28=0,Y28=0,N28="Yes"),"DQ Gating","OK")) -> OK | AH28: No | AI28: =IF(AG28="Not scored","",IF(OR(AG28="DQ Gating",AH28="Yes"),"Disqualified",IF(AF28>=80,"Priority 1",IF(AF28>=60,"Priority 2",IF(AF28>=40,"Priority 3","Disqualified"))))) -> Priority 1 | AJ28: =IF(AG28="Not scored","","P1 "&IF(E28="","?",E28)&"="&V28&" | P2 "&IF(F28="","?",F28)&"="&W28&" | P3 "&IF(C28="","?",C28)&"="&X28&" | P4 "&IF(G28="","?",G28)&"="&Y28&" | P5 "&IF(I28="","?",I28)&"="&Z28&" | P6="&AA28&" | P7 "&IF(M28="","?",M28)&"="&AB28&" | P8 "&IF(O28="","?",O28)&"="&AC28&" | P9 "&IF(L28="","?",L28)&"="&AD28&" | P10="&AE28) -> P1 BaaS=7 | P2 600=10 | P3 Poland=12 | P4 EMI Licence=8 | P5 Bootstrapped Profitable=6 | P6=7 | P7 In-house Legacy Processor=8 | P8 Cloud-native (AWS/Azure/GCP), API-first, AI signals=6 | P9 Scheme Principal=8 | P10=10 | AL28: Prospect | AM28: No | AO28: Live, Migration Window | AP28: =IF(AO28="","Not set",IF(OR(AO28="Q1 2027",AO28="Q2 2027",AO28="Q3 2027",AO28="Q4 2027",AO28="Live, Migration Window"),"OK",IF(AO28="Live, Urgent Need","Deferred","Watch"))) -> OK | AQ28: Commercial and B2B
A29: ACC-PL-025 | B29: Modivo | C29: Poland | D29: Retail | E29: Ecommerce | F29: 1090 | G29: Unlicensed, No Sponsor | H29: Private | I29: Established Private Flat | K29: None | L29: No Scheme Participation Path | M29: No Card Program, No Plan | N29: No | O29: Cloud modern, Not API-first | P29: 0 | Q29: 50000 | R29: No | S29: First-pass agent research | T29: 46216 | U29: CCC Group current report 58/2025 on MODIVO platform; closed-loop MODIVO gift card across CCC/eobuwie/HalfPrice; live Visa Benefit Program promo; MODIVOclub GOLD cashback tier; open-loop card white space but no licence path yet | V29: =IF(E29="","",IFERROR(VLOOKUP(E29,Scoring_Lookups!$A$5:$B$18,2,FALSE()),0)) -> 4 | W29: =IF(F29="","",IF(AND(F29>=50,F29<=1000),10,IF(OR(AND(F29>=20,F29<=49),AND(F29>=1001,F29<=2000)),7,IF(OR(AND(F29>=10,F29<=19),AND(F29>=2001,F29<=5000)),4,0)))) -> 7 | X29: =IF(C29="","",IFERROR(VLOOKUP(C29,Scoring_Lookups!$D$5:$E$35,2,FALSE()),0)) -> 12 | Y29: =IF(G29="","",IFERROR(VLOOKUP(G29,Scoring_Lookups!$G$5:$H$16,2,FALSE()),0)) -> 0 | Z29: =IF(I29="","",IF(OR(I29="Administration/Insolvency",I29="Pending Wind-down",I29="Sanctions Exposure"),0,IF(OR(AND(OR(I29="Series B",I29="Series C",I29="Series D+"),J29<>"",J29>=TODAY()-730),I29="PE-controlled Growth Mandate",I29="Listed with Growth Profile"),8,IF(OR(I29="Series A",I29="Bootstrapped Profitable",I29="PE-controlled Stable",AND(OR(I29="Series B",I29="Series C",I29="Series D+"),J29<>"",J29<TODAY()-730)),6,IF(OR(I29="Seed",I29="Bootstrapped",I29="Listed Stable",I29="Established Private Flat"),3,0))))) -> 3 | AA29: =IF(N29="Yes",0,IF(A29="",0,IF(COUNTIFS('04_Triggers'!B:B,A29,'04_Triggers'!D:D,">="&(TODAY()-365))>=2,20,IF(COUNTIFS('04_Triggers'!B:B,A29,'04_Triggers'!D:D,">="&(TODAY()-365),'04_Triggers'!G:G,"High")>=1,14,IF(COUNTIFS('04_Triggers'!B:B,A29,'04_Triggers'!D:D,">="&(TODAY()-365))>=1,7,IF(COUNTIFS('04_Triggers'!B:B,A29,'04_Triggers'!D:D,">="&(TODAY()-1095),'04_Triggers'!D:D,"<"&(TODAY()-365))>=1,7,0)))))) -> 0 | AB29: =IF(M29="","",IFERROR(VLOOKUP(M29,Scoring_Lookups!$J$5:$K$16,2,FALSE()),0)) -> 0 | AC29: =IF(O29="","",IFERROR(VLOOKUP(O29,Scoring_Lookups!$M$5:$N$8,2,FALSE()),0)) -> 4 | AD29: =IF(L29="","",IFERROR(VLOOKUP(L29,Scoring_Lookups!$P$5:$Q$9,2,FALSE()),0)) -> 0 | AE29: =IF(AND(P29="",Q29="",R29=""),"",IF(OR(IFERROR(MAX(P29,Q29),0)>=500000,R29="Yes"),10,IF(IFERROR(MAX(P29,Q29),0)>=100000,7,IF(IFERROR(MAX(P29,Q29),0)>=10000,4,0)))) -> 4 | AF29: =IFERROR(N(V29)+N(W29)+N(X29)+N(Y29)+N(Z29)+N(AA29)+N(AB29)+N(AC29)+N(AD29)+N(AE29),0) -> 34 | AG29: =IF(OR(E29="",C29="",G29=""),"Not scored",IF(OR(V29=0,X29=0,Y29=0,N29="Yes"),"DQ Gating","OK")) -> DQ Gating | AH29: No | AI29: =IF(AG29="Not scored","",IF(OR(AG29="DQ Gating",AH29="Yes"),"Disqualified",IF(AF29>=80,"Priority 1",IF(AF29>=60,"Priority 2",IF(AF29>=40,"Priority 3","Disqualified"))))) -> Disqualified | AJ29: =IF(AG29="Not scored","","P1 "&IF(E29="","?",E29)&"="&V29&" | P2 "&IF(F29="","?",F29)&"="&W29&" | P3 "&IF(C29="","?",C29)&"="&X29&" | P4 "&IF(G29="","?",G29)&"="&Y29&" | P5 "&IF(I29="","?",I29)&"="&Z29&" | P6="&AA29&" | P7 "&IF(M29="","?",M29)&"="&AB29&" | P8 "&IF(O29="","?",O29)&"="&AC29&" | P9 "&IF(L29="","?",L29)&"="&AD29&" | P10="&AE29) -> P1 Ecommerce=4 | P2 1090=7 | P3 Poland=12 | P4 Unlicensed, No Sponsor=0 | P5 Established Private Flat=3 | P6=0 | P7 No Card Program, No Plan=0 | P8 Cloud modern, Not API-first=4 | P9 No Scheme Participation Path=0 | P10=4 | AL29: Prospect | AM29: No | AO29: Unknown / TBD | AP29: =IF(AO29="","Not set",IF(OR(AO29="Q1 2027",AO29="Q2 2027",AO29="Q3 2027",AO29="Q4 2027",AO29="Live, Migration Window"),"OK",IF(AO29="Live, Urgent Need","Deferred","Watch"))) -> Watch | AQ29: Consumer
A30: ACC-PL-026 | B30: Ramp Network | C30: Poland | D30: FinTech | E30: Crypto | F30: 160 | G30: No Licence, BIN Sponsor Engaged | H30: VC-backed | I30: Series A | K30: TBD | L30: No Sponsor, Licensing Suggests Imminent | M30: No Card Program, No Plan | N30: No | O30: Cloud-native (AWS/Azure/GCP), API-first, AI signals | P30: 0 | Q30: 0 | R30: Unknown | S30: First-pass agent research | T30: 46216 | U30: FCA crypto registration UK; PL Register of Virtual Currency Activities; MiCA CASP application in progress; 40+ new fiat currencies added; Poland main engineering hub (22 open PL roles Jun 2026); on-ramp providers moving to own cards trend; VERIFICATION-FIRST - Poland decision authority to confirm | V30: =IF(E30="","",IFERROR(VLOOKUP(E30,Scoring_Lookups!$A$5:$B$18,2,FALSE()),0)) -> 4 | W30: =IF(F30="","",IF(AND(F30>=50,F30<=1000),10,IF(OR(AND(F30>=20,F30<=49),AND(F30>=1001,F30<=2000)),7,IF(OR(AND(F30>=10,F30<=19),AND(F30>=2001,F30<=5000)),4,0)))) -> 10 | X30: =IF(C30="","",IFERROR(VLOOKUP(C30,Scoring_Lookups!$D$5:$E$35,2,FALSE()),0)) -> 12 | Y30: =IF(G30="","",IFERROR(VLOOKUP(G30,Scoring_Lookups!$G$5:$H$16,2,FALSE()),0)) -> 3 | Z30: =IF(I30="","",IF(OR(I30="Administration/Insolvency",I30="Pending Wind-down",I30="Sanctions Exposure"),0,IF(OR(AND(OR(I30="Series B",I30="Series C",I30="Series D+"),J30<>"",J30>=TODAY()-730),I30="PE-controlled Growth Mandate",I30="Listed with Growth Profile"),8,IF(OR(I30="Series A",I30="Bootstrapped Profitable",I30="PE-controlled Stable",AND(OR(I30="Series B",I30="Series C",I30="Series D+"),J30<>"",J30<TODAY()-730)),6,IF(OR(I30="Seed",I30="Bootstrapped",I30="Listed Stable",I30="Established Private Flat"),3,0))))) -> 6 | AA30: =IF(N30="Yes",0,IF(A30="",0,IF(COUNTIFS('04_Triggers'!B:B,A30,'04_Triggers'!D:D,">="&(TODAY()-365))>=2,20,IF(COUNTIFS('04_Triggers'!B:B,A30,'04_Triggers'!D:D,">="&(TODAY()-365),'04_Triggers'!G:G,"High")>=1,14,IF(COUNTIFS('04_Triggers'!B:B,A30,'04_Triggers'!D:D,">="&(TODAY()-365))>=1,7,IF(COUNTIFS('04_Triggers'!B:B,A30,'04_Triggers'!D:D,">="&(TODAY()-1095),'04_Triggers'!D:D,"<"&(TODAY()-365))>=1,7,0)))))) -> 20 | AB30: =IF(M30="","",IFERROR(VLOOKUP(M30,Scoring_Lookups!$J$5:$K$16,2,FALSE()),0)) -> 0 | AC30: =IF(O30="","",IFERROR(VLOOKUP(O30,Scoring_Lookups!$M$5:$N$8,2,FALSE()),0)) -> 6 | AD30: =IF(L30="","",IFERROR(VLOOKUP(L30,Scoring_Lookups!$P$5:$Q$9,2,FALSE()),0)) -> 3 | AE30: =IF(AND(P30="",Q30="",R30=""),"",IF(OR(IFERROR(MAX(P30,Q30),0)>=500000,R30="Yes"),10,IF(IFERROR(MAX(P30,Q30),0)>=100000,7,IF(IFERROR(MAX(P30,Q30),0)>=10000,4,0)))) -> 0 | AF30: =IFERROR(N(V30)+N(W30)+N(X30)+N(Y30)+N(Z30)+N(AA30)+N(AB30)+N(AC30)+N(AD30)+N(AE30),0) -> 64 | AG30: =IF(OR(E30="",C30="",G30=""),"Not scored",IF(OR(V30=0,X30=0,Y30=0,N30="Yes"),"DQ Gating","OK")) -> OK | AH30: No | AI30: =IF(AG30="Not scored","",IF(OR(AG30="DQ Gating",AH30="Yes"),"Disqualified",IF(AF30>=80,"Priority 1",IF(AF30>=60,"Priority 2",IF(AF30>=40,"Priority 3","Disqualified"))))) -> Priority 2 | AJ30: =IF(AG30="Not scored","","P1 "&IF(E30="","?",E30)&"="&V30&" | P2 "&IF(F30="","?",F30)&"="&W30&" | P3 "&IF(C30="","?",C30)&"="&X30&" | P4 "&IF(G30="","?",G30)&"="&Y30&" | P5 "&IF(I30="","?",I30)&"="&Z30&" | P6="&AA30&" | P7 "&IF(M30="","?",M30)&"="&AB30&" | P8 "&IF(O30="","?",O30)&"="&AC30&" | P9 "&IF(L30="","?",L30)&"="&AD30&" | P10="&AE30) -> P1 Crypto=4 | P2 160=10 | P3 Poland=12 | P4 No Licence, BIN Sponsor Engaged=3 | P5 Series A=6 | P6=20 | P7 No Card Program, No Plan=0 | P8 Cloud-native (AWS/Azure/GCP), API-first, AI signals=6 | P9 No Sponsor, Licensing Suggests Imminent=3 | P10=0 | AL30: Prospect | AM30: No | AO30: Unknown / TBD | AP30: =IF(AO30="","Not set",IF(OR(AO30="Q1 2027",AO30="Q2 2027",AO30="Q3 2027",AO30="Q4 2027",AO30="Live, Migration Window"),"OK",IF(AO30="Live, Urgent Need","Deferred","Watch"))) -> Watch | AQ30: Consumer
A31: ACC-PL-027 | B31: IN1 | C31: Poland | D31: FinTech | E31: Crypto | F31: 15 | G31: No Licence, BIN Sponsor Engaged | H31: Private | I31: Bootstrapped | K31: Quicko (defunct) | L31: No Sponsor, Licensing Suggests Imminent | M31: Smaller/Less-known Processor | N31: No | O31: Cloud-native (AWS/Azure/GCP), API-first, AI signals | P31: 5000 | Q31: 25000 | R31: No | S31: Second-pass agent research | T31: 46216 | U31: Post-Quicko fallout; live product "world first card for both fiat and crypto with easy switch"; rails broken since 21 Jan 2026 KNF revocation of Quicko; needs new issuer now; DEFERRED per TXN Dec 2026 GA - approach Q2 2027 for post-bridge check-in | V31: =IF(E31="","",IFERROR(VLOOKUP(E31,Scoring_Lookups!$A$5:$B$18,2,FALSE()),0)) -> 4 | W31: =IF(F31="","",IF(AND(F31>=50,F31<=1000),10,IF(OR(AND(F31>=20,F31<=49),AND(F31>=1001,F31<=2000)),7,IF(OR(AND(F31>=10,F31<=19),AND(F31>=2001,F31<=5000)),4,0)))) -> 4 | X31: =IF(C31="","",IFERROR(VLOOKUP(C31,Scoring_Lookups!$D$5:$E$35,2,FALSE()),0)) -> 12 | Y31: =IF(G31="","",IFERROR(VLOOKUP(G31,Scoring_Lookups!$G$5:$H$16,2,FALSE()),0)) -> 3 | Z31: =IF(I31="","",IF(OR(I31="Administration/Insolvency",I31="Pending Wind-down",I31="Sanctions Exposure"),0,IF(OR(AND(OR(I31="Series B",I31="Series C",I31="Series D+"),J31<>"",J31>=TODAY()-730),I31="PE-controlled Growth Mandate",I31="Listed with Growth Profile"),8,IF(OR(I31="Series A",I31="Bootstrapped Profitable",I31="PE-controlled Stable",AND(OR(I31="Series B",I31="Series C",I31="Series D+"),J31<>"",J31<TODAY()-730)),6,IF(OR(I31="Seed",I31="Bootstrapped",I31="Listed Stable",I31="Established Private Flat"),3,0))))) -> 3 | AA31: =IF(N31="Yes",0,IF(A31="",0,IF(COUNTIFS('04_Triggers'!B:B,A31,'04_Triggers'!D:D,">="&(TODAY()-365))>=2,20,IF(COUNTIFS('04_Triggers'!B:B,A31,'04_Triggers'!D:D,">="&(TODAY()-365),'04_Triggers'!G:G,"High")>=1,14,IF(COUNTIFS('04_Triggers'!B:B,A31,'04_Triggers'!D:D,">="&(TODAY()-365))>=1,7,IF(COUNTIFS('04_Triggers'!B:B,A31,'04_Triggers'!D:D,">="&(TODAY()-1095),'04_Triggers'!D:D,"<"&(TODAY()-365))>=1,7,0)))))) -> 14 | AB31: =IF(M31="","",IFERROR(VLOOKUP(M31,Scoring_Lookups!$J$5:$K$16,2,FALSE()),0)) -> 6 | AC31: =IF(O31="","",IFERROR(VLOOKUP(O31,Scoring_Lookups!$M$5:$N$8,2,FALSE()),0)) -> 6 | AD31: =IF(L31="","",IFERROR(VLOOKUP(L31,Scoring_Lookups!$P$5:$Q$9,2,FALSE()),0)) -> 3 | AE31: =IF(AND(P31="",Q31="",R31=""),"",IF(OR(IFERROR(MAX(P31,Q31),0)>=500000,R31="Yes"),10,IF(IFERROR(MAX(P31,Q31),0)>=100000,7,IF(IFERROR(MAX(P31,Q31),0)>=10000,4,0)))) -> 4 | AF31: =IFERROR(N(V31)+N(W31)+N(X31)+N(Y31)+N(Z31)+N(AA31)+N(AB31)+N(AC31)+N(AD31)+N(AE31),0) -> 59 | AG31: =IF(OR(E31="",C31="",G31=""),"Not scored",IF(OR(V31=0,X31=0,Y31=0,N31="Yes"),"DQ Gating","OK")) -> OK | AH31: No | AI31: =IF(AG31="Not scored","",IF(OR(AG31="DQ Gating",AH31="Yes"),"Disqualified",IF(AF31>=80,"Priority 1",IF(AF31>=60,"Priority 2",IF(AF31>=40,"Priority 3","Disqualified"))))) -> Priority 3 | AJ31: =IF(AG31="Not scored","","P1 "&IF(E31="","?",E31)&"="&V31&" | P2 "&IF(F31="","?",F31)&"="&W31&" | P3 "&IF(C31="","?",C31)&"="&X31&" | P4 "&IF(G31="","?",G31)&"="&Y31&" | P5 "&IF(I31="","?",I31)&"="&Z31&" | P6="&AA31&" | P7 "&IF(M31="","?",M31)&"="&AB31&" | P8 "&IF(O31="","?",O31)&"="&AC31&" | P9 "&IF(L31="","?",L31)&"="&AD31&" | P10="&AE31) -> P1 Crypto=4 | P2 15=4 | P3 Poland=12 | P4 No Licence, BIN Sponsor Engaged=3 | P5 Bootstrapped=3 | P6=14 | P7 Smaller/Less-known Processor=6 | P8 Cloud-native (AWS/Azure/GCP), API-first, AI signals=6 | P9 No Sponsor, Licensing Suggests Imminent=3 | P10=4 | AL31: Prospect | AM31: No | AO31: Live, Urgent Need | AP31: =IF(AO31="","Not set",IF(OR(AO31="Q1 2027",AO31="Q2 2027",AO31="Q3 2027",AO31="Q4 2027",AO31="Live, Migration Window"),"OK",IF(AO31="Live, Urgent Need","Deferred","Watch"))) -> Deferred | AQ31: Consumer
A32: ACC-PL-028 | B32: NovaPay EU | C32: Poland | D32: FinTech | E32: Payments | F32: 25 | G32: No Licence, BIN Sponsor Engaged | H32: Private | I32: Bootstrapped | K32: Quicko (defunct) | L32: No Sponsor, Licensing Suggests Imminent | M32: Smaller/Less-known Processor | N32: No | O32: Cloud-native (AWS/Azure/GCP), API-first, AI signals | P32: 10000 | Q32: 50000 | R32: No | S32: Second-pass agent research | T32: 46216 | U32: Post-Quicko fallout; public customer notice "onboarding of new customers is suspended, and registration, opening new accounts and issuing new cards are currently unavailable"; Ukrainian parent NovaPay 500+; DEFERRED per TXN Dec 2026 GA | V32: =IF(E32="","",IFERROR(VLOOKUP(E32,Scoring_Lookups!$A$5:$B$18,2,FALSE()),0)) -> 4 | W32: =IF(F32="","",IF(AND(F32>=50,F32<=1000),10,IF(OR(AND(F32>=20,F32<=49),AND(F32>=1001,F32<=2000)),7,IF(OR(AND(F32>=10,F32<=19),AND(F32>=2001,F32<=5000)),4,0)))) -> 7 | X32: =IF(C32="","",IFERROR(VLOOKUP(C32,Scoring_Lookups!$D$5:$E$35,2,FALSE()),0)) -> 12 | Y32: =IF(G32="","",IFERROR(VLOOKUP(G32,Scoring_Lookups!$G$5:$H$16,2,FALSE()),0)) -> 3 | Z32: =IF(I32="","",IF(OR(I32="Administration/Insolvency",I32="Pending Wind-down",I32="Sanctions Exposure"),0,IF(OR(AND(OR(I32="Series B",I32="Series C",I32="Series D+"),J32<>"",J32>=TODAY()-730),I32="PE-controlled Growth Mandate",I32="Listed with Growth Profile"),8,IF(OR(I32="Series A",I32="Bootstrapped Profitable",I32="PE-controlled Stable",AND(OR(I32="Series B",I32="Series C",I32="Series D+"),J32<>"",J32<TODAY()-730)),6,IF(OR(I32="Seed",I32="Bootstrapped",I32="Listed Stable",I32="Established Private Flat"),3,0))))) -> 3 | AA32: =IF(N32="Yes",0,IF(A32="",0,IF(COUNTIFS('04_Triggers'!B:B,A32,'04_Triggers'!D:D,">="&(TODAY()-365))>=2,20,IF(COUNTIFS('04_Triggers'!B:B,A32,'04_Triggers'!D:D,">="&(TODAY()-365),'04_Triggers'!G:G,"High")>=1,14,IF(COUNTIFS('04_Triggers'!B:B,A32,'04_Triggers'!D:D,">="&(TODAY()-365))>=1,7,IF(COUNTIFS('04_Triggers'!B:B,A32,'04_Triggers'!D:D,">="&(TODAY()-1095),'04_Triggers'!D:D,"<"&(TODAY()-365))>=1,7,0)))))) -> 14 | AB32: =IF(M32="","",IFERROR(VLOOKUP(M32,Scoring_Lookups!$J$5:$K$16,2,FALSE()),0)) -> 6 | AC32: =IF(O32="","",IFERROR(VLOOKUP(O32,Scoring_Lookups!$M$5:$N$8,2,FALSE()),0)) -> 6 | AD32: =IF(L32="","",IFERROR(VLOOKUP(L32,Scoring_Lookups!$P$5:$Q$9,2,FALSE()),0)) -> 3 | AE32: =IF(AND(P32="",Q32="",R32=""),"",IF(OR(IFERROR(MAX(P32,Q32),0)>=500000,R32="Yes"),10,IF(IFERROR(MAX(P32,Q32),0)>=100000,7,IF(IFERROR(MAX(P32,Q32),0)>=10000,4,0)))) -> 4 | AF32: =IFERROR(N(V32)+N(W32)+N(X32)+N(Y32)+N(Z32)+N(AA32)+N(AB32)+N(AC32)+N(AD32)+N(AE32),0) -> 62 | AG32: =IF(OR(E32="",C32="",G32=""),"Not scored",IF(OR(V32=0,X32=0,Y32=0,N32="Yes"),"DQ Gating","OK")) -> OK | AH32: No | AI32: =IF(AG32="Not scored","",IF(OR(AG32="DQ Gating",AH32="Yes"),"Disqualified",IF(AF32>=80,"Priority 1",IF(AF32>=60,"Priority 2",IF(AF32>=40,"Priority 3","Disqualified"))))) -> Priority 2 | AJ32: =IF(AG32="Not scored","","P1 "&IF(E32="","?",E32)&"="&V32&" | P2 "&IF(F32="","?",F32)&"="&W32&" | P3 "&IF(C32="","?",C32)&"="&X32&" | P4 "&IF(G32="","?",G32)&"="&Y32&" | P5 "&IF(I32="","?",I32)&"="&Z32&" | P6="&AA32&" | P7 "&IF(M32="","?",M32)&"="&AB32&" | P8 "&IF(O32="","?",O32)&"="&AC32&" | P9 "&IF(L32="","?",L32)&"="&AD32&" | P10="&AE32) -> P1 Payments=4 | P2 25=7 | P3 Poland=12 | P4 No Licence, BIN Sponsor Engaged=3 | P5 Bootstrapped=3 | P6=14 | P7 Smaller/Less-known Processor=6 | P8 Cloud-native (AWS/Azure/GCP), API-first, AI signals=6 | P9 No Sponsor, Licensing Suggests Imminent=3 | P10=4 | AL32: Prospect | AM32: No | AO32: Live, Urgent Need | AP32: =IF(AO32="","Not set",IF(OR(AO32="Q1 2027",AO32="Q2 2027",AO32="Q3 2027",AO32="Q4 2027",AO32="Live, Migration Window"),"OK",IF(AO32="Live, Urgent Need","Deferred","Watch"))) -> Deferred | AQ32: Consumer
A33: ACC-CZ-001 | B33: Partners Banka | C33: Czech Republic | D33: Banking | E33: Digital Banking | F33: 200 | G33: Credit Institution Licence | H33: Private | I33: Bootstrapped Profitable | K33: None (direct scheme) | L33: Scheme Principal | M33: Smaller/Less-known Processor | N33: No | O33: Cloud-native (AWS/Azure/GCP), API-first, AI signals | P33: 50000 | Q33: 200000 | R33: Yes | S33: Czech Republic discovery | T33: 46216 | U33: Public launch March 2024; 2025 target 200k clients + CZK 20bn deposits + CZK 10bn loans; greenfield credit institution built on Tapix partner platform; Partners Financial Services parent (advisor network) | V33: =IF(E33="","",IFERROR(VLOOKUP(E33,Scoring_Lookups!$A$5:$B$18,2,FALSE()),0)) -> 10 | W33: =IF(F33="","",IF(AND(F33>=50,F33<=1000),10,IF(OR(AND(F33>=20,F33<=49),AND(F33>=1001,F33<=2000)),7,IF(OR(AND(F33>=10,F33<=19),AND(F33>=2001,F33<=5000)),4,0)))) -> 10 | X33: =IF(C33="","",IFERROR(VLOOKUP(C33,Scoring_Lookups!$D$5:$E$35,2,FALSE()),0)) -> 12 | Y33: =IF(G33="","",IFERROR(VLOOKUP(G33,Scoring_Lookups!$G$5:$H$16,2,FALSE()),0)) -> 8 | Z33: =IF(I33="","",IF(OR(I33="Administration/Insolvency",I33="Pending Wind-down",I33="Sanctions Exposure"),0,IF(OR(AND(OR(I33="Series B",I33="Series C",I33="Series D+"),J33<>"",J33>=TODAY()-730),I33="PE-controlled Growth Mandate",I33="Listed with Growth Profile"),8,IF(OR(I33="Series A",I33="Bootstrapped Profitable",I33="PE-controlled Stable",AND(OR(I33="Series B",I33="Series C",I33="Series D+"),J33<>"",J33<TODAY()-730)),6,IF(OR(I33="Seed",I33="Bootstrapped",I33="Listed Stable",I33="Established Private Flat"),3,0))))) -> 6 | AA33: =IF(N33="Yes",0,IF(A33="",0,IF(COUNTIFS('04_Triggers'!B:B,A33,'04_Triggers'!D:D,">="&(TODAY()-365))>=2,20,IF(COUNTIFS('04_Triggers'!B:B,A33,'04_Triggers'!D:D,">="&(TODAY()-365),'04_Triggers'!G:G,"High")>=1,14,IF(COUNTIFS('04_Triggers'!B:B,A33,'04_Triggers'!D:D,">="&(TODAY()-365))>=1,7,IF(COUNTIFS('04_Triggers'!B:B,A33,'04_Triggers'!D:D,">="&(TODAY()-1095),'04_Triggers'!D:D,"<"&(TODAY()-365))>=1,7,0)))))) -> 7 | AB33: =IF(M33="","",IFERROR(VLOOKUP(M33,Scoring_Lookups!$J$5:$K$16,2,FALSE()),0)) -> 6 | AC33: =IF(O33="","",IFERROR(VLOOKUP(O33,Scoring_Lookups!$M$5:$N$8,2,FALSE()),0)) -> 6 | AD33: =IF(L33="","",IFERROR(VLOOKUP(L33,Scoring_Lookups!$P$5:$Q$9,2,FALSE()),0)) -> 8 | AE33: =IF(AND(P33="",Q33="",R33=""),"",IF(OR(IFERROR(MAX(P33,Q33),0)>=500000,R33="Yes"),10,IF(IFERROR(MAX(P33,Q33),0)>=100000,7,IF(IFERROR(MAX(P33,Q33),0)>=10000,4,0)))) -> 10 | AF33: =IFERROR(N(V33)+N(W33)+N(X33)+N(Y33)+N(Z33)+N(AA33)+N(AB33)+N(AC33)+N(AD33)+N(AE33),0) -> 83 | AG33: =IF(OR(E33="",C33="",G33=""),"Not scored",IF(OR(V33=0,X33=0,Y33=0,N33="Yes"),"DQ Gating","OK")) -> OK | AH33: No | AI33: =IF(AG33="Not scored","",IF(OR(AG33="DQ Gating",AH33="Yes"),"Disqualified",IF(AF33>=80,"Priority 1",IF(AF33>=60,"Priority 2",IF(AF33>=40,"Priority 3","Disqualified"))))) -> Priority 1 | AJ33: =IF(AG33="Not scored","","P1 "&IF(E33="","?",E33)&"="&V33&" | P2 "&IF(F33="","?",F33)&"="&W33&" | P3 "&IF(C33="","?",C33)&"="&X33&" | P4 "&IF(G33="","?",G33)&"="&Y33&" | P5 "&IF(I33="","?",I33)&"="&Z33&" | P6="&AA33&" | P7 "&IF(M33="","?",M33)&"="&AB33&" | P8 "&IF(O33="","?",O33)&"="&AC33&" | P9 "&IF(L33="","?",L33)&"="&AD33&" | P10="&AE33) -> P1 Digital Banking=10 | P2 200=10 | P3 Czech Republic=12 | P4 Credit Institution Licence=8 | P5 Bootstrapped Profitable=6 | P6=7 | P7 Smaller/Less-known Processor=6 | P8 Cloud-native (AWS/Azure/GCP), API-first, AI signals=6 | P9 Scheme Principal=8 | P10=10 | AL33: Prospect | AM33: No | AO33: Live, Migration Window | AP33: =IF(AO33="","Not set",IF(OR(AO33="Q1 2027",AO33="Q2 2027",AO33="Q3 2027",AO33="Q4 2027",AO33="Live, Migration Window"),"OK",IF(AO33="Live, Urgent Need","Deferred","Watch"))) -> OK | AQ33: Consumer
A34: ACC-CZ-002 | B34: Trinity Bank | C34: Czech Republic | D34: Banking | E34: Digital Banking | F34: 200 | G34: Credit Institution Licence | H34: Private | I34: Bootstrapped | K34: None (direct scheme) | L34: Scheme Principal | M34: Planning to Launch (No Incumbent Yet) | N34: No | O34: Cloud modern, Not API-first | P34: 0 | Q34: 30000 | R34: Yes | S34: Czech Republic discovery | T34: 46216 | U34: Formerly Moravský peněžní ústav; mobile app launched 2024; publicly stated plan to launch cards in 2025-2026; greenfield card program build - no legacy processor | V34: =IF(E34="","",IFERROR(VLOOKUP(E34,Scoring_Lookups!$A$5:$B$18,2,FALSE()),0)) -> 10 | W34: =IF(F34="","",IF(AND(F34>=50,F34<=1000),10,IF(OR(AND(F34>=20,F34<=49),AND(F34>=1001,F34<=2000)),7,IF(OR(AND(F34>=10,F34<=19),AND(F34>=2001,F34<=5000)),4,0)))) -> 10 | X34: =IF(C34="","",IFERROR(VLOOKUP(C34,Scoring_Lookups!$D$5:$E$35,2,FALSE()),0)) -> 12 | Y34: =IF(G34="","",IFERROR(VLOOKUP(G34,Scoring_Lookups!$G$5:$H$16,2,FALSE()),0)) -> 8 | Z34: =IF(I34="","",IF(OR(I34="Administration/Insolvency",I34="Pending Wind-down",I34="Sanctions Exposure"),0,IF(OR(AND(OR(I34="Series B",I34="Series C",I34="Series D+"),J34<>"",J34>=TODAY()-730),I34="PE-controlled Growth Mandate",I34="Listed with Growth Profile"),8,IF(OR(I34="Series A",I34="Bootstrapped Profitable",I34="PE-controlled Stable",AND(OR(I34="Series B",I34="Series C",I34="Series D+"),J34<>"",J34<TODAY()-730)),6,IF(OR(I34="Seed",I34="Bootstrapped",I34="Listed Stable",I34="Established Private Flat"),3,0))))) -> 3 | AA34: =IF(N34="Yes",0,IF(A34="",0,IF(COUNTIFS('04_Triggers'!B:B,A34,'04_Triggers'!D:D,">="&(TODAY()-365))>=2,20,IF(COUNTIFS('04_Triggers'!B:B,A34,'04_Triggers'!D:D,">="&(TODAY()-365),'04_Triggers'!G:G,"High")>=1,14,IF(COUNTIFS('04_Triggers'!B:B,A34,'04_Triggers'!D:D,">="&(TODAY()-365))>=1,7,IF(COUNTIFS('04_Triggers'!B:B,A34,'04_Triggers'!D:D,">="&(TODAY()-1095),'04_Triggers'!D:D,"<"&(TODAY()-365))>=1,7,0)))))) -> 0 | AB34: =IF(M34="","",IFERROR(VLOOKUP(M34,Scoring_Lookups!$J$5:$K$16,2,FALSE()),0)) -> 4 | AC34: =IF(O34="","",IFERROR(VLOOKUP(O34,Scoring_Lookups!$M$5:$N$8,2,FALSE()),0)) -> 4 | AD34: =IF(L34="","",IFERROR(VLOOKUP(L34,Scoring_Lookups!$P$5:$Q$9,2,FALSE()),0)) -> 8 | AE34: =IF(AND(P34="",Q34="",R34=""),"",IF(OR(IFERROR(MAX(P34,Q34),0)>=500000,R34="Yes"),10,IF(IFERROR(MAX(P34,Q34),0)>=100000,7,IF(IFERROR(MAX(P34,Q34),0)>=10000,4,0)))) -> 10 | AF34: =IFERROR(N(V34)+N(W34)+N(X34)+N(Y34)+N(Z34)+N(AA34)+N(AB34)+N(AC34)+N(AD34)+N(AE34),0) -> 69 | AG34: =IF(OR(E34="",C34="",G34=""),"Not scored",IF(OR(V34=0,X34=0,Y34=0,N34="Yes"),"DQ Gating","OK")) -> OK | AH34: No | AI34: =IF(AG34="Not scored","",IF(OR(AG34="DQ Gating",AH34="Yes"),"Disqualified",IF(AF34>=80,"Priority 1",IF(AF34>=60,"Priority 2",IF(AF34>=40,"Priority 3","Disqualified"))))) -> Priority 2 | AJ34: =IF(AG34="Not scored","","P1 "&IF(E34="","?",E34)&"="&V34&" | P2 "&IF(F34="","?",F34)&"="&W34&" | P3 "&IF(C34="","?",C34)&"="&X34&" | P4 "&IF(G34="","?",G34)&"="&Y34&" | P5 "&IF(I34="","?",I34)&"="&Z34&" | P6="&AA34&" | P7 "&IF(M34="","?",M34)&"="&AB34&" | P8 "&IF(O34="","?",O34)&"="&AC34&" | P9 "&IF(L34="","?",L34)&"="&AD34&" | P10="&AE34) -> P1 Digital Banking=10 | P2 200=10 | P3 Czech Republic=12 | P4 Credit Institution Licence=8 | P5 Bootstrapped=3 | P6=0 | P7 Planning to Launch (No Incumbent Yet)=4 | P8 Cloud modern, Not API-first=4 | P9 Scheme Principal=8 | P10=10 | AL34: Prospect | AM34: No | AO34: Q4 2026 | AP34: =IF(AO34="","Not set",IF(OR(AO34="Q1 2027",AO34="Q2 2027",AO34="Q3 2027",AO34="Q4 2027",AO34="Live, Migration Window"),"OK",IF(AO34="Live, Urgent Need","Deferred","Watch"))) -> Watch | AQ34: Consumer
A35: ACC-CZ-003 | B35: Banka CREDITAS | C35: Czech Republic | D35: Banking | E35: Digital Banking | F35: 452 | G35: Credit Institution Licence | H35: Private | I35: Established Private Flat | K35: None (direct scheme) | L35: Scheme Principal | M35: In-house Legacy Processor | N35: No | O35: Cloud modern, Not API-first | P35: 300000 | Q35: 500000 | R35: Yes | S35: Czech Republic discovery | T35: 46216 | U35: Oct 2024 merger with Max banka; assets +50.6%; 10th-largest Czech bank at 2.57% share; Western European expansion announced; post-merger platform consolidation is natural processor re-evaluation moment | V35: =IF(E35="","",IFERROR(VLOOKUP(E35,Scoring_Lookups!$A$5:$B$18,2,FALSE()),0)) -> 10 | W35: =IF(F35="","",IF(AND(F35>=50,F35<=1000),10,IF(OR(AND(F35>=20,F35<=49),AND(F35>=1001,F35<=2000)),7,IF(OR(AND(F35>=10,F35<=19),AND(F35>=2001,F35<=5000)),4,0)))) -> 10 | X35: =IF(C35="","",IFERROR(VLOOKUP(C35,Scoring_Lookups!$D$5:$E$35,2,FALSE()),0)) -> 12 | Y35: =IF(G35="","",IFERROR(VLOOKUP(G35,Scoring_Lookups!$G$5:$H$16,2,FALSE()),0)) -> 8 | Z35: =IF(I35="","",IF(OR(I35="Administration/Insolvency",I35="Pending Wind-down",I35="Sanctions Exposure"),0,IF(OR(AND(OR(I35="Series B",I35="Series C",I35="Series D+"),J35<>"",J35>=TODAY()-730),I35="PE-controlled Growth Mandate",I35="Listed with Growth Profile"),8,IF(OR(I35="Series A",I35="Bootstrapped Profitable",I35="PE-controlled Stable",AND(OR(I35="Series B",I35="Series C",I35="Series D+"),J35<>"",J35<TODAY()-730)),6,IF(OR(I35="Seed",I35="Bootstrapped",I35="Listed Stable",I35="Established Private Flat"),3,0))))) -> 3 | AA35: =IF(N35="Yes",0,IF(A35="",0,IF(COUNTIFS('04_Triggers'!B:B,A35,'04_Triggers'!D:D,">="&(TODAY()-365))>=2,20,IF(COUNTIFS('04_Triggers'!B:B,A35,'04_Triggers'!D:D,">="&(TODAY()-365),'04_Triggers'!G:G,"High")>=1,14,IF(COUNTIFS('04_Triggers'!B:B,A35,'04_Triggers'!D:D,">="&(TODAY()-365))>=1,7,IF(COUNTIFS('04_Triggers'!B:B,A35,'04_Triggers'!D:D,">="&(TODAY()-1095),'04_Triggers'!D:D,"<"&(TODAY()-365))>=1,7,0)))))) -> 7 | AB35: =IF(M35="","",IFERROR(VLOOKUP(M35,Scoring_Lookups!$J$5:$K$16,2,FALSE()),0)) -> 8 | AC35: =IF(O35="","",IFERROR(VLOOKUP(O35,Scoring_Lookups!$M$5:$N$8,2,FALSE()),0)) -> 4 | AD35: =IF(L35="","",IFERROR(VLOOKUP(L35,Scoring_Lookups!$P$5:$Q$9,2,FALSE()),0)) -> 8 | AE35: =IF(AND(P35="",Q35="",R35=""),"",IF(OR(IFERROR(MAX(P35,Q35),0)>=500000,R35="Yes"),10,IF(IFERROR(MAX(P35,Q35),0)>=100000,7,IF(IFERROR(MAX(P35,Q35),0)>=10000,4,0)))) -> 10 | AF35: =IFERROR(N(V35)+N(W35)+N(X35)+N(Y35)+N(Z35)+N(AA35)+N(AB35)+N(AC35)+N(AD35)+N(AE35),0) -> 80 | AG35: =IF(OR(E35="",C35="",G35=""),"Not scored",IF(OR(V35=0,X35=0,Y35=0,N35="Yes"),"DQ Gating","OK")) -> OK | AH35: No | AI35: =IF(AG35="Not scored","",IF(OR(AG35="DQ Gating",AH35="Yes"),"Disqualified",IF(AF35>=80,"Priority 1",IF(AF35>=60,"Priority 2",IF(AF35>=40,"Priority 3","Disqualified"))))) -> Priority 1 | AJ35: =IF(AG35="Not scored","","P1 "&IF(E35="","?",E35)&"="&V35&" | P2 "&IF(F35="","?",F35)&"="&W35&" | P3 "&IF(C35="","?",C35)&"="&X35&" | P4 "&IF(G35="","?",G35)&"="&Y35&" | P5 "&IF(I35="","?",I35)&"="&Z35&" | P6="&AA35&" | P7 "&IF(M35="","?",M35)&"="&AB35&" | P8 "&IF(O35="","?",O35)&"="&AC35&" | P9 "&IF(L35="","?",L35)&"="&AD35&" | P10="&AE35) -> P1 Digital Banking=10 | P2 452=10 | P3 Czech Republic=12 | P4 Credit Institution Licence=8 | P5 Established Private Flat=3 | P6=7 | P7 In-house Legacy Processor=8 | P8 Cloud modern, Not API-first=4 | P9 Scheme Principal=8 | P10=10 | AL35: Prospect | AM35: No | AO35: Live, Migration Window | AP35: =IF(AO35="","Not set",IF(OR(AO35="Q1 2027",AO35="Q2 2027",AO35="Q3 2027",AO35="Q4 2027",AO35="Live, Migration Window"),"OK",IF(AO35="Live, Urgent Need","Deferred","Watch"))) -> OK | AQ35: Consumer
A36: ACC-CZ-004 | B36: Twisto Payments (CZ) | C36: Czech Republic | D36: FinTech | E36: Lending (Consumer) | F36: 150 | G36: PI Licence | H36: PE-controlled | I36: PE-controlled Growth Mandate | J36: 45153 | K36: TBD | L36: Existing BIN Sponsor Relationship | M36: Thredd | N36: No | O36: Cloud-native (AWS/Azure/GCP), API-first, AI signals | P36: 250000 | Q36: 500000 | R36: Yes | S36: Czech Republic discovery | T36: 46216 | U36: 2023 Param acquisition; virtual and physical cards live across CZ, PL, RO with 2.5M customers; historical incumbent GPS (now Thredd) - needs verification post-Param; note: Poland entity separately scored, verify CZ decision authority | V36: =IF(E36="","",IFERROR(VLOOKUP(E36,Scoring_Lookups!$A$5:$B$18,2,FALSE()),0)) -> 7 | W36: =IF(F36="","",IF(AND(F36>=50,F36<=1000),10,IF(OR(AND(F36>=20,F36<=49),AND(F36>=1001,F36<=2000)),7,IF(OR(AND(F36>=10,F36<=19),AND(F36>=2001,F36<=5000)),4,0)))) -> 10 | X36: =IF(C36="","",IFERROR(VLOOKUP(C36,Scoring_Lookups!$D$5:$E$35,2,FALSE()),0)) -> 12 | Y36: =IF(G36="","",IFERROR(VLOOKUP(G36,Scoring_Lookups!$G$5:$H$16,2,FALSE()),0)) -> 6 | Z36: =IF(I36="","",IF(OR(I36="Administration/Insolvency",I36="Pending Wind-down",I36="Sanctions Exposure"),0,IF(OR(AND(OR(I36="Series B",I36="Series C",I36="Series D+"),J36<>"",J36>=TODAY()-730),I36="PE-controlled Growth Mandate",I36="Listed with Growth Profile"),8,IF(OR(I36="Series A",I36="Bootstrapped Profitable",I36="PE-controlled Stable",AND(OR(I36="Series B",I36="Series C",I36="Series D+"),J36<>"",J36<TODAY()-730)),6,IF(OR(I36="Seed",I36="Bootstrapped",I36="Listed Stable",I36="Established Private Flat"),3,0))))) -> 8 | AA36: =IF(N36="Yes",0,IF(A36="",0,IF(COUNTIFS('04_Triggers'!B:B,A36,'04_Triggers'!D:D,">="&(TODAY()-365))>=2,20,IF(COUNTIFS('04_Triggers'!B:B,A36,'04_Triggers'!D:D,">="&(TODAY()-365),'04_Triggers'!G:G,"High")>=1,14,IF(COUNTIFS('04_Triggers'!B:B,A36,'04_Triggers'!D:D,">="&(TODAY()-365))>=1,7,IF(COUNTIFS('04_Triggers'!B:B,A36,'04_Triggers'!D:D,">="&(TODAY()-1095),'04_Triggers'!D:D,"<"&(TODAY()-365))>=1,7,0)))))) -> 0 | AB36: =IF(M36="","",IFERROR(VLOOKUP(M36,Scoring_Lookups!$J$5:$K$16,2,FALSE()),0)) -> 8 | AC36: =IF(O36="","",IFERROR(VLOOKUP(O36,Scoring_Lookups!$M$5:$N$8,2,FALSE()),0)) -> 6 | AD36: =IF(L36="","",IFERROR(VLOOKUP(L36,Scoring_Lookups!$P$5:$Q$9,2,FALSE()),0)) -> 8 | AE36: =IF(AND(P36="",Q36="",R36=""),"",IF(OR(IFERROR(MAX(P36,Q36),0)>=500000,R36="Yes"),10,IF(IFERROR(MAX(P36,Q36),0)>=100000,7,IF(IFERROR(MAX(P36,Q36),0)>=10000,4,0)))) -> 10 | AF36: =IFERROR(N(V36)+N(W36)+N(X36)+N(Y36)+N(Z36)+N(AA36)+N(AB36)+N(AC36)+N(AD36)+N(AE36),0) -> 75 | AG36: =IF(OR(E36="",C36="",G36=""),"Not scored",IF(OR(V36=0,X36=0,Y36=0,N36="Yes"),"DQ Gating","OK")) -> OK | AH36: No | AI36: =IF(AG36="Not scored","",IF(OR(AG36="DQ Gating",AH36="Yes"),"Disqualified",IF(AF36>=80,"Priority 1",IF(AF36>=60,"Priority 2",IF(AF36>=40,"Priority 3","Disqualified"))))) -> Priority 2 | AJ36: =IF(AG36="Not scored","","P1 "&IF(E36="","?",E36)&"="&V36&" | P2 "&IF(F36="","?",F36)&"="&W36&" | P3 "&IF(C36="","?",C36)&"="&X36&" | P4 "&IF(G36="","?",G36)&"="&Y36&" | P5 "&IF(I36="","?",I36)&"="&Z36&" | P6="&AA36&" | P7 "&IF(M36="","?",M36)&"="&AB36&" | P8 "&IF(O36="","?",O36)&"="&AC36&" | P9 "&IF(L36="","?",L36)&"="&AD36&" | P10="&AE36) -> P1 Lending (Consumer)=7 | P2 150=10 | P3 Czech Republic=12 | P4 PI Licence=6 | P5 PE-controlled Growth Mandate=8 | P6=0 | P7 Thredd=8 | P8 Cloud-native (AWS/Azure/GCP), API-first, AI signals=6 | P9 Existing BIN Sponsor Relationship=8 | P10=10 | AL36: Prospect | AM36: No | AO36: Live, Migration Window | AP36: =IF(AO36="","Not set",IF(OR(AO36="Q1 2027",AO36="Q2 2027",AO36="Q3 2027",AO36="Q4 2027",AO36="Live, Migration Window"),"OK",IF(AO36="Live, Urgent Need","Deferred","Watch"))) -> OK | AQ36: Consumer
A37: ACC-CZ-005 | B37: Air Bank | C37: Czech Republic | D37: Banking | E37: Digital Banking | F37: 900 | G37: Credit Institution Licence | H37: PE-controlled | I37: PE-controlled Stable | K37: None (direct scheme) | L37: Scheme Principal | M37: In-house Legacy Processor | N37: No | O37: Cloud modern, Not API-first | P37: 800000 | Q37: 1000000 | R37: Yes | S37: Czech Republic discovery | T37: 46216 | U37: PPF-owned digital bank; Zonky P2P brand fully absorbed; full retail card portfolio; borderline size (700-1061 range across sources) | V37: =IF(E37="","",IFERROR(VLOOKUP(E37,Scoring_Lookups!$A$5:$B$18,2,FALSE()),0)) -> 10 | W37: =IF(F37="","",IF(AND(F37>=50,F37<=1000),10,IF(OR(AND(F37>=20,F37<=49),AND(F37>=1001,F37<=2000)),7,IF(OR(AND(F37>=10,F37<=19),AND(F37>=2001,F37<=5000)),4,0)))) -> 10 | X37: =IF(C37="","",IFERROR(VLOOKUP(C37,Scoring_Lookups!$D$5:$E$35,2,FALSE()),0)) -> 12 | Y37: =IF(G37="","",IFERROR(VLOOKUP(G37,Scoring_Lookups!$G$5:$H$16,2,FALSE()),0)) -> 8 | Z37: =IF(I37="","",IF(OR(I37="Administration/Insolvency",I37="Pending Wind-down",I37="Sanctions Exposure"),0,IF(OR(AND(OR(I37="Series B",I37="Series C",I37="Series D+"),J37<>"",J37>=TODAY()-730),I37="PE-controlled Growth Mandate",I37="Listed with Growth Profile"),8,IF(OR(I37="Series A",I37="Bootstrapped Profitable",I37="PE-controlled Stable",AND(OR(I37="Series B",I37="Series C",I37="Series D+"),J37<>"",J37<TODAY()-730)),6,IF(OR(I37="Seed",I37="Bootstrapped",I37="Listed Stable",I37="Established Private Flat"),3,0))))) -> 6 | AA37: =IF(N37="Yes",0,IF(A37="",0,IF(COUNTIFS('04_Triggers'!B:B,A37,'04_Triggers'!D:D,">="&(TODAY()-365))>=2,20,IF(COUNTIFS('04_Triggers'!B:B,A37,'04_Triggers'!D:D,">="&(TODAY()-365),'04_Triggers'!G:G,"High")>=1,14,IF(COUNTIFS('04_Triggers'!B:B,A37,'04_Triggers'!D:D,">="&(TODAY()-365))>=1,7,IF(COUNTIFS('04_Triggers'!B:B,A37,'04_Triggers'!D:D,">="&(TODAY()-1095),'04_Triggers'!D:D,"<"&(TODAY()-365))>=1,7,0)))))) -> 0 | AB37: =IF(M37="","",IFERROR(VLOOKUP(M37,Scoring_Lookups!$J$5:$K$16,2,FALSE()),0)) -> 8 | AC37: =IF(O37="","",IFERROR(VLOOKUP(O37,Scoring_Lookups!$M$5:$N$8,2,FALSE()),0)) -> 4 | AD37: =IF(L37="","",IFERROR(VLOOKUP(L37,Scoring_Lookups!$P$5:$Q$9,2,FALSE()),0)) -> 8 | AE37: =IF(AND(P37="",Q37="",R37=""),"",IF(OR(IFERROR(MAX(P37,Q37),0)>=500000,R37="Yes"),10,IF(IFERROR(MAX(P37,Q37),0)>=100000,7,IF(IFERROR(MAX(P37,Q37),0)>=10000,4,0)))) -> 10 | AF37: =IFERROR(N(V37)+N(W37)+N(X37)+N(Y37)+N(Z37)+N(AA37)+N(AB37)+N(AC37)+N(AD37)+N(AE37),0) -> 76 | AG37: =IF(OR(E37="",C37="",G37=""),"Not scored",IF(OR(V37=0,X37=0,Y37=0,N37="Yes"),"DQ Gating","OK")) -> OK | AH37: No | AI37: =IF(AG37="Not scored","",IF(OR(AG37="DQ Gating",AH37="Yes"),"Disqualified",IF(AF37>=80,"Priority 1",IF(AF37>=60,"Priority 2",IF(AF37>=40,"Priority 3","Disqualified"))))) -> Priority 2 | AJ37: =IF(AG37="Not scored","","P1 "&IF(E37="","?",E37)&"="&V37&" | P2 "&IF(F37="","?",F37)&"="&W37&" | P3 "&IF(C37="","?",C37)&"="&X37&" | P4 "&IF(G37="","?",G37)&"="&Y37&" | P5 "&IF(I37="","?",I37)&"="&Z37&" | P6="&AA37&" | P7 "&IF(M37="","?",M37)&"="&AB37&" | P8 "&IF(O37="","?",O37)&"="&AC37&" | P9 "&IF(L37="","?",L37)&"="&AD37&" | P10="&AE37) -> P1 Digital Banking=10 | P2 900=10 | P3 Czech Republic=12 | P4 Credit Institution Licence=8 | P5 PE-controlled Stable=6 | P6=0 | P7 In-house Legacy Processor=8 | P8 Cloud modern, Not API-first=4 | P9 Scheme Principal=8 | P10=10 | AL37: Prospect | AM37: No | AO37: Live, Migration Window | AP37: =IF(AO37="","Not set",IF(OR(AO37="Q1 2027",AO37="Q2 2027",AO37="Q3 2027",AO37="Q4 2027",AO37="Live, Migration Window"),"OK",IF(AO37="Live, Urgent Need","Deferred","Watch"))) -> OK | AQ37: Consumer
A38: ACC-CZ-006 | B38: Home Credit Czech | C38: Czech Republic | D38: FinTech | E38: Lending (Consumer) | F38: 601 | G38: BIN Sponsor Agreement In Place | H38: PE-controlled | I38: PE-controlled Stable | K38: TBD | L38: Existing BIN Sponsor Relationship | M38: In-house Legacy Processor | N38: No | O38: Cloud modern, Not API-first | P38: 300000 | Q38: 400000 | R38: Yes | S38: Czech Republic discovery | T38: 46216 | U38: EUR 200M EIB agreement 2025 for household energy-efficiency financing; PPF group; mature revolving credit card portfolio; group-level platform refresh cycles create migration windows | V38: =IF(E38="","",IFERROR(VLOOKUP(E38,Scoring_Lookups!$A$5:$B$18,2,FALSE()),0)) -> 7 | W38: =IF(F38="","",IF(AND(F38>=50,F38<=1000),10,IF(OR(AND(F38>=20,F38<=49),AND(F38>=1001,F38<=2000)),7,IF(OR(AND(F38>=10,F38<=19),AND(F38>=2001,F38<=5000)),4,0)))) -> 10 | X38: =IF(C38="","",IFERROR(VLOOKUP(C38,Scoring_Lookups!$D$5:$E$35,2,FALSE()),0)) -> 12 | Y38: =IF(G38="","",IFERROR(VLOOKUP(G38,Scoring_Lookups!$G$5:$H$16,2,FALSE()),0)) -> 6 | Z38: =IF(I38="","",IF(OR(I38="Administration/Insolvency",I38="Pending Wind-down",I38="Sanctions Exposure"),0,IF(OR(AND(OR(I38="Series B",I38="Series C",I38="Series D+"),J38<>"",J38>=TODAY()-730),I38="PE-controlled Growth Mandate",I38="Listed with Growth Profile"),8,IF(OR(I38="Series A",I38="Bootstrapped Profitable",I38="PE-controlled Stable",AND(OR(I38="Series B",I38="Series C",I38="Series D+"),J38<>"",J38<TODAY()-730)),6,IF(OR(I38="Seed",I38="Bootstrapped",I38="Listed Stable",I38="Established Private Flat"),3,0))))) -> 6 | AA38: =IF(N38="Yes",0,IF(A38="",0,IF(COUNTIFS('04_Triggers'!B:B,A38,'04_Triggers'!D:D,">="&(TODAY()-365))>=2,20,IF(COUNTIFS('04_Triggers'!B:B,A38,'04_Triggers'!D:D,">="&(TODAY()-365),'04_Triggers'!G:G,"High")>=1,14,IF(COUNTIFS('04_Triggers'!B:B,A38,'04_Triggers'!D:D,">="&(TODAY()-365))>=1,7,IF(COUNTIFS('04_Triggers'!B:B,A38,'04_Triggers'!D:D,">="&(TODAY()-1095),'04_Triggers'!D:D,"<"&(TODAY()-365))>=1,7,0)))))) -> 14 | AB38: =IF(M38="","",IFERROR(VLOOKUP(M38,Scoring_Lookups!$J$5:$K$16,2,FALSE()),0)) -> 8 | AC38: =IF(O38="","",IFERROR(VLOOKUP(O38,Scoring_Lookups!$M$5:$N$8,2,FALSE()),0)) -> 4 | AD38: =IF(L38="","",IFERROR(VLOOKUP(L38,Scoring_Lookups!$P$5:$Q$9,2,FALSE()),0)) -> 8 | AE38: =IF(AND(P38="",Q38="",R38=""),"",IF(OR(IFERROR(MAX(P38,Q38),0)>=500000,R38="Yes"),10,IF(IFERROR(MAX(P38,Q38),0)>=100000,7,IF(IFERROR(MAX(P38,Q38),0)>=10000,4,0)))) -> 10 | AF38: =IFERROR(N(V38)+N(W38)+N(X38)+N(Y38)+N(Z38)+N(AA38)+N(AB38)+N(AC38)+N(AD38)+N(AE38),0) -> 85 | AG38: =IF(OR(E38="",C38="",G38=""),"Not scored",IF(OR(V38=0,X38=0,Y38=0,N38="Yes"),"DQ Gating","OK")) -> OK | AH38: No | AI38: =IF(AG38="Not scored","",IF(OR(AG38="DQ Gating",AH38="Yes"),"Disqualified",IF(AF38>=80,"Priority 1",IF(AF38>=60,"Priority 2",IF(AF38>=40,"Priority 3","Disqualified"))))) -> Priority 1 | AJ38: =IF(AG38="Not scored","","P1 "&IF(E38="","?",E38)&"="&V38&" | P2 "&IF(F38="","?",F38)&"="&W38&" | P3 "&IF(C38="","?",C38)&"="&X38&" | P4 "&IF(G38="","?",G38)&"="&Y38&" | P5 "&IF(I38="","?",I38)&"="&Z38&" | P6="&AA38&" | P7 "&IF(M38="","?",M38)&"="&AB38&" | P8 "&IF(O38="","?",O38)&"="&AC38&" | P9 "&IF(L38="","?",L38)&"="&AD38&" | P10="&AE38) -> P1 Lending (Consumer)=7 | P2 601=10 | P3 Czech Republic=12 | P4 BIN Sponsor Agreement In Place=6 | P5 PE-controlled Stable=6 | P6=14 | P7 In-house Legacy Processor=8 | P8 Cloud modern, Not API-first=4 | P9 Existing BIN Sponsor Relationship=8 | P10=10 | AL38: Prospect | AM38: No | AO38: Live, Migration Window | AP38: =IF(AO38="","Not set",IF(OR(AO38="Q1 2027",AO38="Q2 2027",AO38="Q3 2027",AO38="Q4 2027",AO38="Live, Migration Window"),"OK",IF(AO38="Live, Urgent Need","Deferred","Watch"))) -> OK | AQ38: Consumer
A39: ACC-CZ-007 | B39: Cofidis Czech Republic | C39: Czech Republic | D39: FinTech | E39: Lending (Consumer) | F39: 159 | G39: BIN Sponsor Agreement In Place | H39: PE-controlled | I39: PE-controlled Stable | K39: TBD | L39: Existing BIN Sponsor Relationship | M39: In-house Legacy Processor | N39: No | O39: Cloud modern, Not API-first | P39: 100000 | Q39: 150000 | R39: Yes | S39: Czech Republic discovery | T39: 46216 | U39: CZ branch of Cofidis SA (Crédit Mutuel Alliance Fédérale); Oct 2024 Magyar Cetelem acquisition extends revolving credit into CEE; decision authority likely France - track only | V39: =IF(E39="","",IFERROR(VLOOKUP(E39,Scoring_Lookups!$A$5:$B$18,2,FALSE()),0)) -> 7 | W39: =IF(F39="","",IF(AND(F39>=50,F39<=1000),10,IF(OR(AND(F39>=20,F39<=49),AND(F39>=1001,F39<=2000)),7,IF(OR(AND(F39>=10,F39<=19),AND(F39>=2001,F39<=5000)),4,0)))) -> 10 | X39: =IF(C39="","",IFERROR(VLOOKUP(C39,Scoring_Lookups!$D$5:$E$35,2,FALSE()),0)) -> 12 | Y39: =IF(G39="","",IFERROR(VLOOKUP(G39,Scoring_Lookups!$G$5:$H$16,2,FALSE()),0)) -> 6 | Z39: =IF(I39="","",IF(OR(I39="Administration/Insolvency",I39="Pending Wind-down",I39="Sanctions Exposure"),0,IF(OR(AND(OR(I39="Series B",I39="Series C",I39="Series D+"),J39<>"",J39>=TODAY()-730),I39="PE-controlled Growth Mandate",I39="Listed with Growth Profile"),8,IF(OR(I39="Series A",I39="Bootstrapped Profitable",I39="PE-controlled Stable",AND(OR(I39="Series B",I39="Series C",I39="Series D+"),J39<>"",J39<TODAY()-730)),6,IF(OR(I39="Seed",I39="Bootstrapped",I39="Listed Stable",I39="Established Private Flat"),3,0))))) -> 6 | AA39: =IF(N39="Yes",0,IF(A39="",0,IF(COUNTIFS('04_Triggers'!B:B,A39,'04_Triggers'!D:D,">="&(TODAY()-365))>=2,20,IF(COUNTIFS('04_Triggers'!B:B,A39,'04_Triggers'!D:D,">="&(TODAY()-365),'04_Triggers'!G:G,"High")>=1,14,IF(COUNTIFS('04_Triggers'!B:B,A39,'04_Triggers'!D:D,">="&(TODAY()-365))>=1,7,IF(COUNTIFS('04_Triggers'!B:B,A39,'04_Triggers'!D:D,">="&(TODAY()-1095),'04_Triggers'!D:D,"<"&(TODAY()-365))>=1,7,0)))))) -> 7 | AB39: =IF(M39="","",IFERROR(VLOOKUP(M39,Scoring_Lookups!$J$5:$K$16,2,FALSE()),0)) -> 8 | AC39: =IF(O39="","",IFERROR(VLOOKUP(O39,Scoring_Lookups!$M$5:$N$8,2,FALSE()),0)) -> 4 | AD39: =IF(L39="","",IFERROR(VLOOKUP(L39,Scoring_Lookups!$P$5:$Q$9,2,FALSE()),0)) -> 8 | AE39: =IF(AND(P39="",Q39="",R39=""),"",IF(OR(IFERROR(MAX(P39,Q39),0)>=500000,R39="Yes"),10,IF(IFERROR(MAX(P39,Q39),0)>=100000,7,IF(IFERROR(MAX(P39,Q39),0)>=10000,4,0)))) -> 10 | AF39: =IFERROR(N(V39)+N(W39)+N(X39)+N(Y39)+N(Z39)+N(AA39)+N(AB39)+N(AC39)+N(AD39)+N(AE39),0) -> 78 | AG39: =IF(OR(E39="",C39="",G39=""),"Not scored",IF(OR(V39=0,X39=0,Y39=0,N39="Yes"),"DQ Gating","OK")) -> OK | AH39: No | AI39: =IF(AG39="Not scored","",IF(OR(AG39="DQ Gating",AH39="Yes"),"Disqualified",IF(AF39>=80,"Priority 1",IF(AF39>=60,"Priority 2",IF(AF39>=40,"Priority 3","Disqualified"))))) -> Priority 2 | AJ39: =IF(AG39="Not scored","","P1 "&IF(E39="","?",E39)&"="&V39&" | P2 "&IF(F39="","?",F39)&"="&W39&" | P3 "&IF(C39="","?",C39)&"="&X39&" | P4 "&IF(G39="","?",G39)&"="&Y39&" | P5 "&IF(I39="","?",I39)&"="&Z39&" | P6="&AA39&" | P7 "&IF(M39="","?",M39)&"="&AB39&" | P8 "&IF(O39="","?",O39)&"="&AC39&" | P9 "&IF(L39="","?",L39)&"="&AD39&" | P10="&AE39) -> P1 Lending (Consumer)=7 | P2 159=10 | P3 Czech Republic=12 | P4 BIN Sponsor Agreement In Place=6 | P5 PE-controlled Stable=6 | P6=7 | P7 In-house Legacy Processor=8 | P8 Cloud modern, Not API-first=4 | P9 Existing BIN Sponsor Relationship=8 | P10=10 | AL39: Prospect | AM39: No | AO39: Live, Migration Window | AP39: =IF(AO39="","Not set",IF(OR(AO39="Q1 2027",AO39="Q2 2027",AO39="Q3 2027",AO39="Q4 2027",AO39="Live, Migration Window"),"OK",IF(AO39="Live, Urgent Need","Deferred","Watch"))) -> OK | AQ39: Consumer
A40: ACC-CZ-008 | B40: Trisbee | C40: Czech Republic | D40: FinTech | E40: Payments | F40: 55 | G40: PI Licence | H40: Private | I40: Bootstrapped | K40: None | L40: Scheme Participation Visible | M40: No Card Program, No Plan | N40: No | O40: Cloud modern, Not API-first | P40: 0 | Q40: 0 | R40: No | S40: Czech Republic discovery | T40: 46216 | U40: 9-country expansion in CZ, IT, SK, ES, FR, PT, DE, AT, PE; card acceptance only, no issuing programme disclosed; potential future issuing candidate | V40: =IF(E40="","",IFERROR(VLOOKUP(E40,Scoring_Lookups!$A$5:$B$18,2,FALSE()),0)) -> 4 | W40: =IF(F40="","",IF(AND(F40>=50,F40<=1000),10,IF(OR(AND(F40>=20,F40<=49),AND(F40>=1001,F40<=2000)),7,IF(OR(AND(F40>=10,F40<=19),AND(F40>=2001,F40<=5000)),4,0)))) -> 10 | X40: =IF(C40="","",IFERROR(VLOOKUP(C40,Scoring_Lookups!$D$5:$E$35,2,FALSE()),0)) -> 12 | Y40: =IF(G40="","",IFERROR(VLOOKUP(G40,Scoring_Lookups!$G$5:$H$16,2,FALSE()),0)) -> 6 | Z40: =IF(I40="","",IF(OR(I40="Administration/Insolvency",I40="Pending Wind-down",I40="Sanctions Exposure"),0,IF(OR(AND(OR(I40="Series B",I40="Series C",I40="Series D+"),J40<>"",J40>=TODAY()-730),I40="PE-controlled Growth Mandate",I40="Listed with Growth Profile"),8,IF(OR(I40="Series A",I40="Bootstrapped Profitable",I40="PE-controlled Stable",AND(OR(I40="Series B",I40="Series C",I40="Series D+"),J40<>"",J40<TODAY()-730)),6,IF(OR(I40="Seed",I40="Bootstrapped",I40="Listed Stable",I40="Established Private Flat"),3,0))))) -> 3 | AA40: =IF(N40="Yes",0,IF(A40="",0,IF(COUNTIFS('04_Triggers'!B:B,A40,'04_Triggers'!D:D,">="&(TODAY()-365))>=2,20,IF(COUNTIFS('04_Triggers'!B:B,A40,'04_Triggers'!D:D,">="&(TODAY()-365),'04_Triggers'!G:G,"High")>=1,14,IF(COUNTIFS('04_Triggers'!B:B,A40,'04_Triggers'!D:D,">="&(TODAY()-365))>=1,7,IF(COUNTIFS('04_Triggers'!B:B,A40,'04_Triggers'!D:D,">="&(TODAY()-1095),'04_Triggers'!D:D,"<"&(TODAY()-365))>=1,7,0)))))) -> 0 | AB40: =IF(M40="","",IFERROR(VLOOKUP(M40,Scoring_Lookups!$J$5:$K$16,2,FALSE()),0)) -> 0 | AC40: =IF(O40="","",IFERROR(VLOOKUP(O40,Scoring_Lookups!$M$5:$N$8,2,FALSE()),0)) -> 4 | AD40: =IF(L40="","",IFERROR(VLOOKUP(L40,Scoring_Lookups!$P$5:$Q$9,2,FALSE()),0)) -> 6 | AE40: =IF(AND(P40="",Q40="",R40=""),"",IF(OR(IFERROR(MAX(P40,Q40),0)>=500000,R40="Yes"),10,IF(IFERROR(MAX(P40,Q40),0)>=100000,7,IF(IFERROR(MAX(P40,Q40),0)>=10000,4,0)))) -> 0 | AF40: =IFERROR(N(V40)+N(W40)+N(X40)+N(Y40)+N(Z40)+N(AA40)+N(AB40)+N(AC40)+N(AD40)+N(AE40),0) -> 45 | AG40: =IF(OR(E40="",C40="",G40=""),"Not scored",IF(OR(V40=0,X40=0,Y40=0,N40="Yes"),"DQ Gating","OK")) -> OK | AH40: No | AI40: =IF(AG40="Not scored","",IF(OR(AG40="DQ Gating",AH40="Yes"),"Disqualified",IF(AF40>=80,"Priority 1",IF(AF40>=60,"Priority 2",IF(AF40>=40,"Priority 3","Disqualified"))))) -> Priority 3 | AJ40: =IF(AG40="Not scored","","P1 "&IF(E40="","?",E40)&"="&V40&" | P2 "&IF(F40="","?",F40)&"="&W40&" | P3 "&IF(C40="","?",C40)&"="&X40&" | P4 "&IF(G40="","?",G40)&"="&Y40&" | P5 "&IF(I40="","?",I40)&"="&Z40&" | P6="&AA40&" | P7 "&IF(M40="","?",M40)&"="&AB40&" | P8 "&IF(O40="","?",O40)&"="&AC40&" | P9 "&IF(L40="","?",L40)&"="&AD40&" | P10="&AE40) -> P1 Payments=4 | P2 55=10 | P3 Czech Republic=12 | P4 PI Licence=6 | P5 Bootstrapped=3 | P6=0 | P7 No Card Program, No Plan=0 | P8 Cloud modern, Not API-first=4 | P9 Scheme Participation Visible=6 | P10=0 | AL40: Prospect | AM40: No | AO40: Unknown / TBD | AP40: =IF(AO40="","Not set",IF(OR(AO40="Q1 2027",AO40="Q2 2027",AO40="Q3 2027",AO40="Q4 2027",AO40="Live, Migration Window"),"OK",IF(AO40="Live, Urgent Need","Deferred","Watch"))) -> Watch | AQ40: Consumer
A41: ACC-CZ-009 | B41: Portu | C41: Czech Republic | D41: FinTech | E41: Investment Management | F41: 60 | G41: PI Licence | H41: Private | I41: Bootstrapped Profitable | K41: TBD | L41: No Sponsor, Licensing Suggests Imminent | M41: Planning to Launch (No Incumbent Yet) | N41: No | O41: Cloud-native (AWS/Azure/GCP), API-first, AI signals | P41: 0 | Q41: 50000 | R41: Unknown | S41: Czech Republic discovery | T41: 46216 | U41: 250,000+ clients; CZK 48bn+ AUM; part of WOOD & Company group; wealthtech card pattern (Trade Republic, Scalable Capital DE); card programme intent speculative but plausible | V41: =IF(E41="","",IFERROR(VLOOKUP(E41,Scoring_Lookups!$A$5:$B$18,2,FALSE()),0)) -> 4 | W41: =IF(F41="","",IF(AND(F41>=50,F41<=1000),10,IF(OR(AND(F41>=20,F41<=49),AND(F41>=1001,F41<=2000)),7,IF(OR(AND(F41>=10,F41<=19),AND(F41>=2001,F41<=5000)),4,0)))) -> 10 | X41: =IF(C41="","",IFERROR(VLOOKUP(C41,Scoring_Lookups!$D$5:$E$35,2,FALSE()),0)) -> 12 | Y41: =IF(G41="","",IFERROR(VLOOKUP(G41,Scoring_Lookups!$G$5:$H$16,2,FALSE()),0)) -> 6 | Z41: =IF(I41="","",IF(OR(I41="Administration/Insolvency",I41="Pending Wind-down",I41="Sanctions Exposure"),0,IF(OR(AND(OR(I41="Series B",I41="Series C",I41="Series D+"),J41<>"",J41>=TODAY()-730),I41="PE-controlled Growth Mandate",I41="Listed with Growth Profile"),8,IF(OR(I41="Series A",I41="Bootstrapped Profitable",I41="PE-controlled Stable",AND(OR(I41="Series B",I41="Series C",I41="Series D+"),J41<>"",J41<TODAY()-730)),6,IF(OR(I41="Seed",I41="Bootstrapped",I41="Listed Stable",I41="Established Private Flat"),3,0))))) -> 6 | AA41: =IF(N41="Yes",0,IF(A41="",0,IF(COUNTIFS('04_Triggers'!B:B,A41,'04_Triggers'!D:D,">="&(TODAY()-365))>=2,20,IF(COUNTIFS('04_Triggers'!B:B,A41,'04_Triggers'!D:D,">="&(TODAY()-365),'04_Triggers'!G:G,"High")>=1,14,IF(COUNTIFS('04_Triggers'!B:B,A41,'04_Triggers'!D:D,">="&(TODAY()-365))>=1,7,IF(COUNTIFS('04_Triggers'!B:B,A41,'04_Triggers'!D:D,">="&(TODAY()-1095),'04_Triggers'!D:D,"<"&(TODAY()-365))>=1,7,0)))))) -> 0 | AB41: =IF(M41="","",IFERROR(VLOOKUP(M41,Scoring_Lookups!$J$5:$K$16,2,FALSE()),0)) -> 4 | AC41: =IF(O41="","",IFERROR(VLOOKUP(O41,Scoring_Lookups!$M$5:$N$8,2,FALSE()),0)) -> 6 | AD41: =IF(L41="","",IFERROR(VLOOKUP(L41,Scoring_Lookups!$P$5:$Q$9,2,FALSE()),0)) -> 3 | AE41: =IF(AND(P41="",Q41="",R41=""),"",IF(OR(IFERROR(MAX(P41,Q41),0)>=500000,R41="Yes"),10,IF(IFERROR(MAX(P41,Q41),0)>=100000,7,IF(IFERROR(MAX(P41,Q41),0)>=10000,4,0)))) -> 4 | AF41: =IFERROR(N(V41)+N(W41)+N(X41)+N(Y41)+N(Z41)+N(AA41)+N(AB41)+N(AC41)+N(AD41)+N(AE41),0) -> 55 | AG41: =IF(OR(E41="",C41="",G41=""),"Not scored",IF(OR(V41=0,X41=0,Y41=0,N41="Yes"),"DQ Gating","OK")) -> OK | AH41: No | AI41: =IF(AG41="Not scored","",IF(OR(AG41="DQ Gating",AH41="Yes"),"Disqualified",IF(AF41>=80,"Priority 1",IF(AF41>=60,"Priority 2",IF(AF41>=40,"Priority 3","Disqualified"))))) -> Priority 3 | AJ41: =IF(AG41="Not scored","","P1 "&IF(E41="","?",E41)&"="&V41&" | P2 "&IF(F41="","?",F41)&"="&W41&" | P3 "&IF(C41="","?",C41)&"="&X41&" | P4 "&IF(G41="","?",G41)&"="&Y41&" | P5 "&IF(I41="","?",I41)&"="&Z41&" | P6="&AA41&" | P7 "&IF(M41="","?",M41)&"="&AB41&" | P8 "&IF(O41="","?",O41)&"="&AC41&" | P9 "&IF(L41="","?",L41)&"="&AD41&" | P10="&AE41) -> P1 Investment Management=4 | P2 60=10 | P3 Czech Republic=12 | P4 PI Licence=6 | P5 Bootstrapped Profitable=6 | P6=0 | P7 Planning to Launch (No Incumbent Yet)=4 | P8 Cloud-native (AWS/Azure/GCP), API-first, AI signals=6 | P9 No Sponsor, Licensing Suggests Imminent=3 | P10=4 | AL41: Prospect | AM41: No | AO41: Q3 2027 | AP41: =IF(AO41="","Not set",IF(OR(AO41="Q1 2027",AO41="Q2 2027",AO41="Q3 2027",AO41="Q4 2027",AO41="Live, Migration Window"),"OK",IF(AO41="Live, Urgent Need","Deferred","Watch"))) -> OK | AQ41: Consumer
A42: ACC-CZ-010 | B42: Coinmate | C42: Czech Republic | D42: FinTech | E42: Crypto | F42: 30 | G42: Secondary Regime | H42: Private | I42: Bootstrapped | K42: None | L42: No Sponsor, Licensing Suggests Imminent | M42: No Card Program, No Plan | N42: No | O42: Cloud-native (AWS/Azure/GCP), API-first, AI signals | P42: 0 | Q42: 0 | R42: No | S42: Czech Republic discovery | T42: 46216 | U42: MiCA Class 3 CASP granted by CNB 11 Feb 2026 (first-wave); no confirmed card intent; crypto-linked debit is a common post-MiCA next step | V42: =IF(E42="","",IFERROR(VLOOKUP(E42,Scoring_Lookups!$A$5:$B$18,2,FALSE()),0)) -> 4 | W42: =IF(F42="","",IF(AND(F42>=50,F42<=1000),10,IF(OR(AND(F42>=20,F42<=49),AND(F42>=1001,F42<=2000)),7,IF(OR(AND(F42>=10,F42<=19),AND(F42>=2001,F42<=5000)),4,0)))) -> 7 | X42: =IF(C42="","",IFERROR(VLOOKUP(C42,Scoring_Lookups!$D$5:$E$35,2,FALSE()),0)) -> 12 | Y42: =IF(G42="","",IFERROR(VLOOKUP(G42,Scoring_Lookups!$G$5:$H$16,2,FALSE()),0)) -> 3 | Z42: =IF(I42="","",IF(OR(I42="Administration/Insolvency",I42="Pending Wind-down",I42="Sanctions Exposure"),0,IF(OR(AND(OR(I42="Series B",I42="Series C",I42="Series D+"),J42<>"",J42>=TODAY()-730),I42="PE-controlled Growth Mandate",I42="Listed with Growth Profile"),8,IF(OR(I42="Series A",I42="Bootstrapped Profitable",I42="PE-controlled Stable",AND(OR(I42="Series B",I42="Series C",I42="Series D+"),J42<>"",J42<TODAY()-730)),6,IF(OR(I42="Seed",I42="Bootstrapped",I42="Listed Stable",I42="Established Private Flat"),3,0))))) -> 3 | AA42: =IF(N42="Yes",0,IF(A42="",0,IF(COUNTIFS('04_Triggers'!B:B,A42,'04_Triggers'!D:D,">="&(TODAY()-365))>=2,20,IF(COUNTIFS('04_Triggers'!B:B,A42,'04_Triggers'!D:D,">="&(TODAY()-365),'04_Triggers'!G:G,"High")>=1,14,IF(COUNTIFS('04_Triggers'!B:B,A42,'04_Triggers'!D:D,">="&(TODAY()-365))>=1,7,IF(COUNTIFS('04_Triggers'!B:B,A42,'04_Triggers'!D:D,">="&(TODAY()-1095),'04_Triggers'!D:D,"<"&(TODAY()-365))>=1,7,0)))))) -> 14 | AB42: =IF(M42="","",IFERROR(VLOOKUP(M42,Scoring_Lookups!$J$5:$K$16,2,FALSE()),0)) -> 0 | AC42: =IF(O42="","",IFERROR(VLOOKUP(O42,Scoring_Lookups!$M$5:$N$8,2,FALSE()),0)) -> 6 | AD42: =IF(L42="","",IFERROR(VLOOKUP(L42,Scoring_Lookups!$P$5:$Q$9,2,FALSE()),0)) -> 3 | AE42: =IF(AND(P42="",Q42="",R42=""),"",IF(OR(IFERROR(MAX(P42,Q42),0)>=500000,R42="Yes"),10,IF(IFERROR(MAX(P42,Q42),0)>=100000,7,IF(IFERROR(MAX(P42,Q42),0)>=10000,4,0)))) -> 0 | AF42: =IFERROR(N(V42)+N(W42)+N(X42)+N(Y42)+N(Z42)+N(AA42)+N(AB42)+N(AC42)+N(AD42)+N(AE42),0) -> 52 | AG42: =IF(OR(E42="",C42="",G42=""),"Not scored",IF(OR(V42=0,X42=0,Y42=0,N42="Yes"),"DQ Gating","OK")) -> OK | AH42: No | AI42: =IF(AG42="Not scored","",IF(OR(AG42="DQ Gating",AH42="Yes"),"Disqualified",IF(AF42>=80,"Priority 1",IF(AF42>=60,"Priority 2",IF(AF42>=40,"Priority 3","Disqualified"))))) -> Priority 3 | AJ42: =IF(AG42="Not scored","","P1 "&IF(E42="","?",E42)&"="&V42&" | P2 "&IF(F42="","?",F42)&"="&W42&" | P3 "&IF(C42="","?",C42)&"="&X42&" | P4 "&IF(G42="","?",G42)&"="&Y42&" | P5 "&IF(I42="","?",I42)&"="&Z42&" | P6="&AA42&" | P7 "&IF(M42="","?",M42)&"="&AB42&" | P8 "&IF(O42="","?",O42)&"="&AC42&" | P9 "&IF(L42="","?",L42)&"="&AD42&" | P10="&AE42) -> P1 Crypto=4 | P2 30=7 | P3 Czech Republic=12 | P4 Secondary Regime=3 | P5 Bootstrapped=3 | P6=14 | P7 No Card Program, No Plan=0 | P8 Cloud-native (AWS/Azure/GCP), API-first, AI signals=6 | P9 No Sponsor, Licensing Suggests Imminent=3 | P10=0 | AL42: Prospect | AM42: No | AO42: Unknown / TBD | AP42: =IF(AO42="","Not set",IF(OR(AO42="Q1 2027",AO42="Q2 2027",AO42="Q3 2027",AO42="Q4 2027",AO42="Live, Migration Window"),"OK",IF(AO42="Live, Urgent Need","Deferred","Watch"))) -> Watch | AQ42: Consumer
A43: ACC-CZ-011 | B43: Anycoin | C43: Czech Republic | D43: FinTech | E43: Crypto | F43: 20 | G43: Secondary Regime | H43: Private | I43: Bootstrapped | K43: None | L43: No Sponsor, Licensing Suggests Imminent | M43: No Card Program, No Plan | N43: No | O43: Cloud modern, Not API-first | P43: 0 | Q43: 0 | R43: No | S43: Czech Republic discovery | T43: 46216 | U43: First-wave MiCA CASP Feb 2026 via CNB; same thesis as Coinmate - crypto-linked cards a natural extension; card intent not confirmed | V43: =IF(E43="","",IFERROR(VLOOKUP(E43,Scoring_Lookups!$A$5:$B$18,2,FALSE()),0)) -> 4 | W43: =IF(F43="","",IF(AND(F43>=50,F43<=1000),10,IF(OR(AND(F43>=20,F43<=49),AND(F43>=1001,F43<=2000)),7,IF(OR(AND(F43>=10,F43<=19),AND(F43>=2001,F43<=5000)),4,0)))) -> 7 | X43: =IF(C43="","",IFERROR(VLOOKUP(C43,Scoring_Lookups!$D$5:$E$35,2,FALSE()),0)) -> 12 | Y43: =IF(G43="","",IFERROR(VLOOKUP(G43,Scoring_Lookups!$G$5:$H$16,2,FALSE()),0)) -> 3 | Z43: =IF(I43="","",IF(OR(I43="Administration/Insolvency",I43="Pending Wind-down",I43="Sanctions Exposure"),0,IF(OR(AND(OR(I43="Series B",I43="Series C",I43="Series D+"),J43<>"",J43>=TODAY()-730),I43="PE-controlled Growth Mandate",I43="Listed with Growth Profile"),8,IF(OR(I43="Series A",I43="Bootstrapped Profitable",I43="PE-controlled Stable",AND(OR(I43="Series B",I43="Series C",I43="Series D+"),J43<>"",J43<TODAY()-730)),6,IF(OR(I43="Seed",I43="Bootstrapped",I43="Listed Stable",I43="Established Private Flat"),3,0))))) -> 3 | AA43: =IF(N43="Yes",0,IF(A43="",0,IF(COUNTIFS('04_Triggers'!B:B,A43,'04_Triggers'!D:D,">="&(TODAY()-365))>=2,20,IF(COUNTIFS('04_Triggers'!B:B,A43,'04_Triggers'!D:D,">="&(TODAY()-365),'04_Triggers'!G:G,"High")>=1,14,IF(COUNTIFS('04_Triggers'!B:B,A43,'04_Triggers'!D:D,">="&(TODAY()-365))>=1,7,IF(COUNTIFS('04_Triggers'!B:B,A43,'04_Triggers'!D:D,">="&(TODAY()-1095),'04_Triggers'!D:D,"<"&(TODAY()-365))>=1,7,0)))))) -> 14 | AB43: =IF(M43="","",IFERROR(VLOOKUP(M43,Scoring_Lookups!$J$5:$K$16,2,FALSE()),0)) -> 0 | AC43: =IF(O43="","",IFERROR(VLOOKUP(O43,Scoring_Lookups!$M$5:$N$8,2,FALSE()),0)) -> 4 | AD43: =IF(L43="","",IFERROR(VLOOKUP(L43,Scoring_Lookups!$P$5:$Q$9,2,FALSE()),0)) -> 3 | AE43: =IF(AND(P43="",Q43="",R43=""),"",IF(OR(IFERROR(MAX(P43,Q43),0)>=500000,R43="Yes"),10,IF(IFERROR(MAX(P43,Q43),0)>=100000,7,IF(IFERROR(MAX(P43,Q43),0)>=10000,4,0)))) -> 0 | AF43: =IFERROR(N(V43)+N(W43)+N(X43)+N(Y43)+N(Z43)+N(AA43)+N(AB43)+N(AC43)+N(AD43)+N(AE43),0) -> 50 | AG43: =IF(OR(E43="",C43="",G43=""),"Not scored",IF(OR(V43=0,X43=0,Y43=0,N43="Yes"),"DQ Gating","OK")) -> OK | AH43: No | AI43: =IF(AG43="Not scored","",IF(OR(AG43="DQ Gating",AH43="Yes"),"Disqualified",IF(AF43>=80,"Priority 1",IF(AF43>=60,"Priority 2",IF(AF43>=40,"Priority 3","Disqualified"))))) -> Priority 3 | AJ43: =IF(AG43="Not scored","","P1 "&IF(E43="","?",E43)&"="&V43&" | P2 "&IF(F43="","?",F43)&"="&W43&" | P3 "&IF(C43="","?",C43)&"="&X43&" | P4 "&IF(G43="","?",G43)&"="&Y43&" | P5 "&IF(I43="","?",I43)&"="&Z43&" | P6="&AA43&" | P7 "&IF(M43="","?",M43)&"="&AB43&" | P8 "&IF(O43="","?",O43)&"="&AC43&" | P9 "&IF(L43="","?",L43)&"="&AD43&" | P10="&AE43) -> P1 Crypto=4 | P2 20=7 | P3 Czech Republic=12 | P4 Secondary Regime=3 | P5 Bootstrapped=3 | P6=14 | P7 No Card Program, No Plan=0 | P8 Cloud modern, Not API-first=4 | P9 No Sponsor, Licensing Suggests Imminent=3 | P10=0 | AL43: Prospect | AM43: No | AO43: Unknown / TBD | AP43: =IF(AO43="","Not set",IF(OR(AO43="Q1 2027",AO43="Q2 2027",AO43="Q3 2027",AO43="Q4 2027",AO43="Live, Migration Window"),"OK",IF(AO43="Live, Urgent Need","Deferred","Watch"))) -> Watch | AQ43: Consumer
A44: ACC-CZ-012 | B44: Simplecoin | C44: Czech Republic | D44: FinTech | E44: Crypto | F44: 15 | G44: Secondary Regime | H44: Private | I44: Bootstrapped | K44: None | L44: No Sponsor, Licensing Suggests Imminent | M44: No Card Program, No Plan | N44: No | O44: Cloud modern, Not API-first | P44: 0 | Q44: 0 | R44: No | S44: Czech Republic discovery | T44: 46216 | U44: CNB-supervised CASP; MiCA continuity preparation; fiat deposits via CZK/EUR/PLN; sub-scale (10-20 employees) - Priority 3 territory | V44: =IF(E44="","",IFERROR(VLOOKUP(E44,Scoring_Lookups!$A$5:$B$18,2,FALSE()),0)) -> 4 | W44: =IF(F44="","",IF(AND(F44>=50,F44<=1000),10,IF(OR(AND(F44>=20,F44<=49),AND(F44>=1001,F44<=2000)),7,IF(OR(AND(F44>=10,F44<=19),AND(F44>=2001,F44<=5000)),4,0)))) -> 4 | X44: =IF(C44="","",IFERROR(VLOOKUP(C44,Scoring_Lookups!$D$5:$E$35,2,FALSE()),0)) -> 12 | Y44: =IF(G44="","",IFERROR(VLOOKUP(G44,Scoring_Lookups!$G$5:$H$16,2,FALSE()),0)) -> 3 | Z44: =IF(I44="","",IF(OR(I44="Administration/Insolvency",I44="Pending Wind-down",I44="Sanctions Exposure"),0,IF(OR(AND(OR(I44="Series B",I44="Series C",I44="Series D+"),J44<>"",J44>=TODAY()-730),I44="PE-controlled Growth Mandate",I44="Listed with Growth Profile"),8,IF(OR(I44="Series A",I44="Bootstrapped Profitable",I44="PE-controlled Stable",AND(OR(I44="Series B",I44="Series C",I44="Series D+"),J44<>"",J44<TODAY()-730)),6,IF(OR(I44="Seed",I44="Bootstrapped",I44="Listed Stable",I44="Established Private Flat"),3,0))))) -> 3 | AA44: =IF(N44="Yes",0,IF(A44="",0,IF(COUNTIFS('04_Triggers'!B:B,A44,'04_Triggers'!D:D,">="&(TODAY()-365))>=2,20,IF(COUNTIFS('04_Triggers'!B:B,A44,'04_Triggers'!D:D,">="&(TODAY()-365),'04_Triggers'!G:G,"High")>=1,14,IF(COUNTIFS('04_Triggers'!B:B,A44,'04_Triggers'!D:D,">="&(TODAY()-365))>=1,7,IF(COUNTIFS('04_Triggers'!B:B,A44,'04_Triggers'!D:D,">="&(TODAY()-1095),'04_Triggers'!D:D,"<"&(TODAY()-365))>=1,7,0)))))) -> 0 | AB44: =IF(M44="","",IFERROR(VLOOKUP(M44,Scoring_Lookups!$J$5:$K$16,2,FALSE()),0)) -> 0 | AC44: =IF(O44="","",IFERROR(VLOOKUP(O44,Scoring_Lookups!$M$5:$N$8,2,FALSE()),0)) -> 4 | AD44: =IF(L44="","",IFERROR(VLOOKUP(L44,Scoring_Lookups!$P$5:$Q$9,2,FALSE()),0)) -> 3 | AE44: =IF(AND(P44="",Q44="",R44=""),"",IF(OR(IFERROR(MAX(P44,Q44),0)>=500000,R44="Yes"),10,IF(IFERROR(MAX(P44,Q44),0)>=100000,7,IF(IFERROR(MAX(P44,Q44),0)>=10000,4,0)))) -> 0 | AF44: =IFERROR(N(V44)+N(W44)+N(X44)+N(Y44)+N(Z44)+N(AA44)+N(AB44)+N(AC44)+N(AD44)+N(AE44),0) -> 33 | AG44: =IF(OR(E44="",C44="",G44=""),"Not scored",IF(OR(V44=0,X44=0,Y44=0,N44="Yes"),"DQ Gating","OK")) -> OK | AH44: No | AI44: =IF(AG44="Not scored","",IF(OR(AG44="DQ Gating",AH44="Yes"),"Disqualified",IF(AF44>=80,"Priority 1",IF(AF44>=60,"Priority 2",IF(AF44>=40,"Priority 3","Disqualified"))))) -> Disqualified | AJ44: =IF(AG44="Not scored","","P1 "&IF(E44="","?",E44)&"="&V44&" | P2 "&IF(F44="","?",F44)&"="&W44&" | P3 "&IF(C44="","?",C44)&"="&X44&" | P4 "&IF(G44="","?",G44)&"="&Y44&" | P5 "&IF(I44="","?",I44)&"="&Z44&" | P6="&AA44&" | P7 "&IF(M44="","?",M44)&"="&AB44&" | P8 "&IF(O44="","?",O44)&"="&AC44&" | P9 "&IF(L44="","?",L44)&"="&AD44&" | P10="&AE44) -> P1 Crypto=4 | P2 15=4 | P3 Czech Republic=12 | P4 Secondary Regime=3 | P5 Bootstrapped=3 | P6=0 | P7 No Card Program, No Plan=0 | P8 Cloud modern, Not API-first=4 | P9 No Sponsor, Licensing Suggests Imminent=3 | P10=0 | AL44: Prospect | AM44: No | AO44: Unknown / TBD | AP44: =IF(AO44="","Not set",IF(OR(AO44="Q1 2027",AO44="Q2 2027",AO44="Q3 2027",AO44="Q4 2027",AO44="Live, Migration Window"),"OK",IF(AO44="Live, Urgent Need","Deferred","Watch"))) -> Watch | AQ44: Consumer
A45: ACC-CZ-013 | B45: Comgate | C45: Czech Republic | D45: FinTech | E45: Payments | F45: 150 | G45: PI Licence | H45: Private | I45: Bootstrapped Profitable | K45: None (direct scheme) | L45: Scheme Principal | M45: No Card Program, No Plan | N45: No | O45: Cloud modern, Not API-first | P45: 0 | Q45: 0 | R45: No | S45: Czech Republic discovery | T45: 46216 | U45: 21,000+ merchants; CZK 53bn annual TPV; direct Visa and Mastercard acquirer since 2023; cross-border acquiring in CZ, SK, PL, HU, RO; no card issuing programme disclosed - potential future settlement/expense card | V45: =IF(E45="","",IFERROR(VLOOKUP(E45,Scoring_Lookups!$A$5:$B$18,2,FALSE()),0)) -> 4 | W45: =IF(F45="","",IF(AND(F45>=50,F45<=1000),10,IF(OR(AND(F45>=20,F45<=49),AND(F45>=1001,F45<=2000)),7,IF(OR(AND(F45>=10,F45<=19),AND(F45>=2001,F45<=5000)),4,0)))) -> 10 | X45: =IF(C45="","",IFERROR(VLOOKUP(C45,Scoring_Lookups!$D$5:$E$35,2,FALSE()),0)) -> 12 | Y45: =IF(G45="","",IFERROR(VLOOKUP(G45,Scoring_Lookups!$G$5:$H$16,2,FALSE()),0)) -> 6 | Z45: =IF(I45="","",IF(OR(I45="Administration/Insolvency",I45="Pending Wind-down",I45="Sanctions Exposure"),0,IF(OR(AND(OR(I45="Series B",I45="Series C",I45="Series D+"),J45<>"",J45>=TODAY()-730),I45="PE-controlled Growth Mandate",I45="Listed with Growth Profile"),8,IF(OR(I45="Series A",I45="Bootstrapped Profitable",I45="PE-controlled Stable",AND(OR(I45="Series B",I45="Series C",I45="Series D+"),J45<>"",J45<TODAY()-730)),6,IF(OR(I45="Seed",I45="Bootstrapped",I45="Listed Stable",I45="Established Private Flat"),3,0))))) -> 6 | AA45: =IF(N45="Yes",0,IF(A45="",0,IF(COUNTIFS('04_Triggers'!B:B,A45,'04_Triggers'!D:D,">="&(TODAY()-365))>=2,20,IF(COUNTIFS('04_Triggers'!B:B,A45,'04_Triggers'!D:D,">="&(TODAY()-365),'04_Triggers'!G:G,"High")>=1,14,IF(COUNTIFS('04_Triggers'!B:B,A45,'04_Triggers'!D:D,">="&(TODAY()-365))>=1,7,IF(COUNTIFS('04_Triggers'!B:B,A45,'04_Triggers'!D:D,">="&(TODAY()-1095),'04_Triggers'!D:D,"<"&(TODAY()-365))>=1,7,0)))))) -> 0 | AB45: =IF(M45="","",IFERROR(VLOOKUP(M45,Scoring_Lookups!$J$5:$K$16,2,FALSE()),0)) -> 0 | AC45: =IF(O45="","",IFERROR(VLOOKUP(O45,Scoring_Lookups!$M$5:$N$8,2,FALSE()),0)) -> 4 | AD45: =IF(L45="","",IFERROR(VLOOKUP(L45,Scoring_Lookups!$P$5:$Q$9,2,FALSE()),0)) -> 8 | AE45: =IF(AND(P45="",Q45="",R45=""),"",IF(OR(IFERROR(MAX(P45,Q45),0)>=500000,R45="Yes"),10,IF(IFERROR(MAX(P45,Q45),0)>=100000,7,IF(IFERROR(MAX(P45,Q45),0)>=10000,4,0)))) -> 0 | AF45: =IFERROR(N(V45)+N(W45)+N(X45)+N(Y45)+N(Z45)+N(AA45)+N(AB45)+N(AC45)+N(AD45)+N(AE45),0) -> 50 | AG45: =IF(OR(E45="",C45="",G45=""),"Not scored",IF(OR(V45=0,X45=0,Y45=0,N45="Yes"),"DQ Gating","OK")) -> OK | AH45: No | AI45: =IF(AG45="Not scored","",IF(OR(AG45="DQ Gating",AH45="Yes"),"Disqualified",IF(AF45>=80,"Priority 1",IF(AF45>=60,"Priority 2",IF(AF45>=40,"Priority 3","Disqualified"))))) -> Priority 3 | AJ45: =IF(AG45="Not scored","","P1 "&IF(E45="","?",E45)&"="&V45&" | P2 "&IF(F45="","?",F45)&"="&W45&" | P3 "&IF(C45="","?",C45)&"="&X45&" | P4 "&IF(G45="","?",G45)&"="&Y45&" | P5 "&IF(I45="","?",I45)&"="&Z45&" | P6="&AA45&" | P7 "&IF(M45="","?",M45)&"="&AB45&" | P8 "&IF(O45="","?",O45)&"="&AC45&" | P9 "&IF(L45="","?",L45)&"="&AD45&" | P10="&AE45) -> P1 Payments=4 | P2 150=10 | P3 Czech Republic=12 | P4 PI Licence=6 | P5 Bootstrapped Profitable=6 | P6=0 | P7 No Card Program, No Plan=0 | P8 Cloud modern, Not API-first=4 | P9 Scheme Principal=8 | P10=0 | AL45: Prospect | AM45: No | AO45: Unknown / TBD | AP45: =IF(AO45="","Not set",IF(OR(AO45="Q1 2027",AO45="Q2 2027",AO45="Q3 2027",AO45="Q4 2027",AO45="Live, Migration Window"),"OK",IF(AO45="Live, Urgent Need","Deferred","Watch"))) -> Watch | AQ45: Consumer
A46: ACC-CZ-014 | B46: Rohlik Group | C46: Czech Republic | D46: Retail | E46: Ecommerce | F46: 2000 | G46: Unlicensed, No Sponsor | H46: VC-backed | I46: Series D+ | J46: 45672 | K46: None | L46: No Scheme Participation Path | M46: No Card Program, No Plan | N46: No | O46: Cloud modern, Not API-first | P46: 0 | Q46: 100000 | R46: No | S46: Czech Republic discovery | T46: 46216 | U46: $92M venture debt Jan 2025; up to EUR 90M EIB loan; 2000 employees group total (European operations); e-grocery loyalty/subscription card pattern (Ocado, Getir) speculative but the funding is fresh | V46: =IF(E46="","",IFERROR(VLOOKUP(E46,Scoring_Lookups!$A$5:$B$18,2,FALSE()),0)) -> 4 | W46: =IF(F46="","",IF(AND(F46>=50,F46<=1000),10,IF(OR(AND(F46>=20,F46<=49),AND(F46>=1001,F46<=2000)),7,IF(OR(AND(F46>=10,F46<=19),AND(F46>=2001,F46<=5000)),4,0)))) -> 7 | X46: =IF(C46="","",IFERROR(VLOOKUP(C46,Scoring_Lookups!$D$5:$E$35,2,FALSE()),0)) -> 12 | Y46: =IF(G46="","",IFERROR(VLOOKUP(G46,Scoring_Lookups!$G$5:$H$16,2,FALSE()),0)) -> 0 | Z46: =IF(I46="","",IF(OR(I46="Administration/Insolvency",I46="Pending Wind-down",I46="Sanctions Exposure"),0,IF(OR(AND(OR(I46="Series B",I46="Series C",I46="Series D+"),J46<>"",J46>=TODAY()-730),I46="PE-controlled Growth Mandate",I46="Listed with Growth Profile"),8,IF(OR(I46="Series A",I46="Bootstrapped Profitable",I46="PE-controlled Stable",AND(OR(I46="Series B",I46="Series C",I46="Series D+"),J46<>"",J46<TODAY()-730)),6,IF(OR(I46="Seed",I46="Bootstrapped",I46="Listed Stable",I46="Established Private Flat"),3,0))))) -> 8 | AA46: =IF(N46="Yes",0,IF(A46="",0,IF(COUNTIFS('04_Triggers'!B:B,A46,'04_Triggers'!D:D,">="&(TODAY()-365))>=2,20,IF(COUNTIFS('04_Triggers'!B:B,A46,'04_Triggers'!D:D,">="&(TODAY()-365),'04_Triggers'!G:G,"High")>=1,14,IF(COUNTIFS('04_Triggers'!B:B,A46,'04_Triggers'!D:D,">="&(TODAY()-365))>=1,7,IF(COUNTIFS('04_Triggers'!B:B,A46,'04_Triggers'!D:D,">="&(TODAY()-1095),'04_Triggers'!D:D,"<"&(TODAY()-365))>=1,7,0)))))) -> 7 | AB46: =IF(M46="","",IFERROR(VLOOKUP(M46,Scoring_Lookups!$J$5:$K$16,2,FALSE()),0)) -> 0 | AC46: =IF(O46="","",IFERROR(VLOOKUP(O46,Scoring_Lookups!$M$5:$N$8,2,FALSE()),0)) -> 4 | AD46: =IF(L46="","",IFERROR(VLOOKUP(L46,Scoring_Lookups!$P$5:$Q$9,2,FALSE()),0)) -> 0 | AE46: =IF(AND(P46="",Q46="",R46=""),"",IF(OR(IFERROR(MAX(P46,Q46),0)>=500000,R46="Yes"),10,IF(IFERROR(MAX(P46,Q46),0)>=100000,7,IF(IFERROR(MAX(P46,Q46),0)>=10000,4,0)))) -> 7 | AF46: =IFERROR(N(V46)+N(W46)+N(X46)+N(Y46)+N(Z46)+N(AA46)+N(AB46)+N(AC46)+N(AD46)+N(AE46),0) -> 49 | AG46: =IF(OR(E46="",C46="",G46=""),"Not scored",IF(OR(V46=0,X46=0,Y46=0,N46="Yes"),"DQ Gating","OK")) -> DQ Gating | AH46: No | AI46: =IF(AG46="Not scored","",IF(OR(AG46="DQ Gating",AH46="Yes"),"Disqualified",IF(AF46>=80,"Priority 1",IF(AF46>=60,"Priority 2",IF(AF46>=40,"Priority 3","Disqualified"))))) -> Disqualified | AJ46: =IF(AG46="Not scored","","P1 "&IF(E46="","?",E46)&"="&V46&" | P2 "&IF(F46="","?",F46)&"="&W46&" | P3 "&IF(C46="","?",C46)&"="&X46&" | P4 "&IF(G46="","?",G46)&"="&Y46&" | P5 "&IF(I46="","?",I46)&"="&Z46&" | P6="&AA46&" | P7 "&IF(M46="","?",M46)&"="&AB46&" | P8 "&IF(O46="","?",O46)&"="&AC46&" | P9 "&IF(L46="","?",L46)&"="&AD46&" | P10="&AE46) -> P1 Ecommerce=4 | P2 2000=7 | P3 Czech Republic=12 | P4 Unlicensed, No Sponsor=0 | P5 Series D+=8 | P6=7 | P7 No Card Program, No Plan=0 | P8 Cloud modern, Not API-first=4 | P9 No Scheme Participation Path=0 | P10=7 | AL46: Prospect | AM46: No | AO46: Unknown / TBD | AP46: =IF(AO46="","Not set",IF(OR(AO46="Q1 2027",AO46="Q2 2027",AO46="Q3 2027",AO46="Q4 2027",AO46="Live, Migration Window"),"OK",IF(AO46="Live, Urgent Need","Deferred","Watch"))) -> Watch | AQ46: Consumer
A47: ACC-CZ-015 | B47: AvaFin Czech (ex-Creamfinance) | C47: Czech Republic | D47: FinTech | E47: Lending (Consumer) | F47: 250 | G47: BIN Sponsor Agreement In Place | H47: PE-controlled | I47: PE-controlled Stable | K47: TBD | L47: Existing BIN Sponsor Relationship | M47: Incumbent Unknown | N47: No | O47: Cloud modern, Not API-first | P47: 0 | Q47: 20000 | R47: Unknown | S47: Czech Republic discovery | T47: 46216 | U47: Rebrand from CreamCredit/Creamfinance to AvaFin; Multitude SE strategic investment; consumer instalment loans live; card issuing adjacent - group HQ Latvia | V47: =IF(E47="","",IFERROR(VLOOKUP(E47,Scoring_Lookups!$A$5:$B$18,2,FALSE()),0)) -> 7 | W47: =IF(F47="","",IF(AND(F47>=50,F47<=1000),10,IF(OR(AND(F47>=20,F47<=49),AND(F47>=1001,F47<=2000)),7,IF(OR(AND(F47>=10,F47<=19),AND(F47>=2001,F47<=5000)),4,0)))) -> 10 | X47: =IF(C47="","",IFERROR(VLOOKUP(C47,Scoring_Lookups!$D$5:$E$35,2,FALSE()),0)) -> 12 | Y47: =IF(G47="","",IFERROR(VLOOKUP(G47,Scoring_Lookups!$G$5:$H$16,2,FALSE()),0)) -> 6 | Z47: =IF(I47="","",IF(OR(I47="Administration/Insolvency",I47="Pending Wind-down",I47="Sanctions Exposure"),0,IF(OR(AND(OR(I47="Series B",I47="Series C",I47="Series D+"),J47<>"",J47>=TODAY()-730),I47="PE-controlled Growth Mandate",I47="Listed with Growth Profile"),8,IF(OR(I47="Series A",I47="Bootstrapped Profitable",I47="PE-controlled Stable",AND(OR(I47="Series B",I47="Series C",I47="Series D+"),J47<>"",J47<TODAY()-730)),6,IF(OR(I47="Seed",I47="Bootstrapped",I47="Listed Stable",I47="Established Private Flat"),3,0))))) -> 6 | AA47: =IF(N47="Yes",0,IF(A47="",0,IF(COUNTIFS('04_Triggers'!B:B,A47,'04_Triggers'!D:D,">="&(TODAY()-365))>=2,20,IF(COUNTIFS('04_Triggers'!B:B,A47,'04_Triggers'!D:D,">="&(TODAY()-365),'04_Triggers'!G:G,"High")>=1,14,IF(COUNTIFS('04_Triggers'!B:B,A47,'04_Triggers'!D:D,">="&(TODAY()-365))>=1,7,IF(COUNTIFS('04_Triggers'!B:B,A47,'04_Triggers'!D:D,">="&(TODAY()-1095),'04_Triggers'!D:D,"<"&(TODAY()-365))>=1,7,0)))))) -> 7 | AB47: =IF(M47="","",IFERROR(VLOOKUP(M47,Scoring_Lookups!$J$5:$K$16,2,FALSE()),0)) -> 3 | AC47: =IF(O47="","",IFERROR(VLOOKUP(O47,Scoring_Lookups!$M$5:$N$8,2,FALSE()),0)) -> 4 | AD47: =IF(L47="","",IFERROR(VLOOKUP(L47,Scoring_Lookups!$P$5:$Q$9,2,FALSE()),0)) -> 8 | AE47: =IF(AND(P47="",Q47="",R47=""),"",IF(OR(IFERROR(MAX(P47,Q47),0)>=500000,R47="Yes"),10,IF(IFERROR(MAX(P47,Q47),0)>=100000,7,IF(IFERROR(MAX(P47,Q47),0)>=10000,4,0)))) -> 4 | AF47: =IFERROR(N(V47)+N(W47)+N(X47)+N(Y47)+N(Z47)+N(AA47)+N(AB47)+N(AC47)+N(AD47)+N(AE47),0) -> 67 | AG47: =IF(OR(E47="",C47="",G47=""),"Not scored",IF(OR(V47=0,X47=0,Y47=0,N47="Yes"),"DQ Gating","OK")) -> OK | AH47: No | AI47: =IF(AG47="Not scored","",IF(OR(AG47="DQ Gating",AH47="Yes"),"Disqualified",IF(AF47>=80,"Priority 1",IF(AF47>=60,"Priority 2",IF(AF47>=40,"Priority 3","Disqualified"))))) -> Priority 2 | AJ47: =IF(AG47="Not scored","","P1 "&IF(E47="","?",E47)&"="&V47&" | P2 "&IF(F47="","?",F47)&"="&W47&" | P3 "&IF(C47="","?",C47)&"="&X47&" | P4 "&IF(G47="","?",G47)&"="&Y47&" | P5 "&IF(I47="","?",I47)&"="&Z47&" | P6="&AA47&" | P7 "&IF(M47="","?",M47)&"="&AB47&" | P8 "&IF(O47="","?",O47)&"="&AC47&" | P9 "&IF(L47="","?",L47)&"="&AD47&" | P10="&AE47) -> P1 Lending (Consumer)=7 | P2 250=10 | P3 Czech Republic=12 | P4 BIN Sponsor Agreement In Place=6 | P5 PE-controlled Stable=6 | P6=7 | P7 Incumbent Unknown=3 | P8 Cloud modern, Not API-first=4 | P9 Existing BIN Sponsor Relationship=8 | P10=4 | AL47: Prospect | AM47: No | AO47: Q4 2027 | AP47: =IF(AO47="","Not set",IF(OR(AO47="Q1 2027",AO47="Q2 2027",AO47="Q3 2027",AO47="Q4 2027",AO47="Live, Migration Window"),"OK",IF(AO47="Live, Urgent Need","Deferred","Watch"))) -> OK | AQ47: Consumer
A48: ACC-CZ-016 | B48: Fidoo | C48: Czech Republic | D48: FinTech | E48: Expense Management | F48: 50 | G48: PI Licence | H48: PE-controlled | I48: PE-controlled Stable | K48: TBD | L48: Existing BIN Sponsor Relationship | M48: Incumbent Unknown | N48: No | O48: Cloud modern, Not API-first | P48: 30000 | Q48: 60000 | R48: Yes | S48: Czech Republic discovery (added post-review) | T48: 46216 | U48: Corporate expense management platform; part of Direct Group (Czech Republic) - unrelated to Direct Transact (TXN co-founding owner in South Africa); active card program for corporate expense cards | V48: =IF(E48="","",IFERROR(VLOOKUP(E48,Scoring_Lookups!$A$5:$B$18,2,FALSE()),0)) -> 7 | W48: =IF(F48="","",IF(AND(F48>=50,F48<=1000),10,IF(OR(AND(F48>=20,F48<=49),AND(F48>=1001,F48<=2000)),7,IF(OR(AND(F48>=10,F48<=19),AND(F48>=2001,F48<=5000)),4,0)))) -> 10 | X48: =IF(C48="","",IFERROR(VLOOKUP(C48,Scoring_Lookups!$D$5:$E$35,2,FALSE()),0)) -> 12 | Y48: =IF(G48="","",IFERROR(VLOOKUP(G48,Scoring_Lookups!$G$5:$H$16,2,FALSE()),0)) -> 6 | Z48: =IF(I48="","",IF(OR(I48="Administration/Insolvency",I48="Pending Wind-down",I48="Sanctions Exposure"),0,IF(OR(AND(OR(I48="Series B",I48="Series C",I48="Series D+"),J48<>"",J48>=TODAY()-730),I48="PE-controlled Growth Mandate",I48="Listed with Growth Profile"),8,IF(OR(I48="Series A",I48="Bootstrapped Profitable",I48="PE-controlled Stable",AND(OR(I48="Series B",I48="Series C",I48="Series D+"),J48<>"",J48<TODAY()-730)),6,IF(OR(I48="Seed",I48="Bootstrapped",I48="Listed Stable",I48="Established Private Flat"),3,0))))) -> 6 | AA48: =IF(N48="Yes",0,IF(A48="",0,IF(COUNTIFS('04_Triggers'!B:B,A48,'04_Triggers'!D:D,">="&(TODAY()-365))>=2,20,IF(COUNTIFS('04_Triggers'!B:B,A48,'04_Triggers'!D:D,">="&(TODAY()-365),'04_Triggers'!G:G,"High")>=1,14,IF(COUNTIFS('04_Triggers'!B:B,A48,'04_Triggers'!D:D,">="&(TODAY()-365))>=1,7,IF(COUNTIFS('04_Triggers'!B:B,A48,'04_Triggers'!D:D,">="&(TODAY()-1095),'04_Triggers'!D:D,"<"&(TODAY()-365))>=1,7,0)))))) -> 0 | AB48: =IF(M48="","",IFERROR(VLOOKUP(M48,Scoring_Lookups!$J$5:$K$16,2,FALSE()),0)) -> 3 | AC48: =IF(O48="","",IFERROR(VLOOKUP(O48,Scoring_Lookups!$M$5:$N$8,2,FALSE()),0)) -> 4 | AD48: =IF(L48="","",IFERROR(VLOOKUP(L48,Scoring_Lookups!$P$5:$Q$9,2,FALSE()),0)) -> 8 | AE48: =IF(AND(P48="",Q48="",R48=""),"",IF(OR(IFERROR(MAX(P48,Q48),0)>=500000,R48="Yes"),10,IF(IFERROR(MAX(P48,Q48),0)>=100000,7,IF(IFERROR(MAX(P48,Q48),0)>=10000,4,0)))) -> 10 | AF48: =IFERROR(N(V48)+N(W48)+N(X48)+N(Y48)+N(Z48)+N(AA48)+N(AB48)+N(AC48)+N(AD48)+N(AE48),0) -> 66 | AG48: =IF(OR(E48="",C48="",G48=""),"Not scored",IF(OR(V48=0,X48=0,Y48=0,N48="Yes"),"DQ Gating","OK")) -> OK | AH48: No | AI48: =IF(AG48="Not scored","",IF(OR(AG48="DQ Gating",AH48="Yes"),"Disqualified",IF(AF48>=80,"Priority 1",IF(AF48>=60,"Priority 2",IF(AF48>=40,"Priority 3","Disqualified"))))) -> Priority 2 | AJ48: =IF(AG48="Not scored","","P1 "&IF(E48="","?",E48)&"="&V48&" | P2 "&IF(F48="","?",F48)&"="&W48&" | P3 "&IF(C48="","?",C48)&"="&X48&" | P4 "&IF(G48="","?",G48)&"="&Y48&" | P5 "&IF(I48="","?",I48)&"="&Z48&" | P6="&AA48&" | P7 "&IF(M48="","?",M48)&"="&AB48&" | P8 "&IF(O48="","?",O48)&"="&AC48&" | P9 "&IF(L48="","?",L48)&"="&AD48&" | P10="&AE48) -> P1 Expense Management=7 | P2 50=10 | P3 Czech Republic=12 | P4 PI Licence=6 | P5 PE-controlled Stable=6 | P6=0 | P7 Incumbent Unknown=3 | P8 Cloud modern, Not API-first=4 | P9 Existing BIN Sponsor Relationship=8 | P10=10 | AL48: Prospect | AM48: No | AO48: Live, Migration Window | AP48: =IF(AO48="","Not set",IF(OR(AO48="Q1 2027",AO48="Q2 2027",AO48="Q3 2027",AO48="Q4 2027",AO48="Live, Migration Window"),"OK",IF(AO48="Live, Urgent Need","Deferred","Watch"))) -> OK | AQ48: Commercial and B2B
A49: ACC-CZ-017 | B49: Fondee | C49: Czech Republic | D49: FinTech | E49: Investment Management | F49: 25 | G49: PI Licence | H49: VC-backed | I49: Series A | K49: None | L49: No Sponsor, Licensing Suggests Imminent | M49: No Card Program, No Plan | N49: No | O49: Cloud-native (AWS/Azure/GCP), API-first, AI signals | P49: 0 | Q49: 0 | R49: Unknown | S49: Czech Republic discovery (added post-review) | T49: 46216 | U49: Czech robo-advisor / ETF-based investment platform; founded ~2020 by Jan Hlavsa and Eva Hlavsová; backed by CyberCapital; wealthtech card pattern potential (Trade Republic, Scalable Capital) but not confirmed | V49: =IF(E49="","",IFERROR(VLOOKUP(E49,Scoring_Lookups!$A$5:$B$18,2,FALSE()),0)) -> 4 | W49: =IF(F49="","",IF(AND(F49>=50,F49<=1000),10,IF(OR(AND(F49>=20,F49<=49),AND(F49>=1001,F49<=2000)),7,IF(OR(AND(F49>=10,F49<=19),AND(F49>=2001,F49<=5000)),4,0)))) -> 7 | X49: =IF(C49="","",IFERROR(VLOOKUP(C49,Scoring_Lookups!$D$5:$E$35,2,FALSE()),0)) -> 12 | Y49: =IF(G49="","",IFERROR(VLOOKUP(G49,Scoring_Lookups!$G$5:$H$16,2,FALSE()),0)) -> 6 | Z49: =IF(I49="","",IF(OR(I49="Administration/Insolvency",I49="Pending Wind-down",I49="Sanctions Exposure"),0,IF(OR(AND(OR(I49="Series B",I49="Series C",I49="Series D+"),J49<>"",J49>=TODAY()-730),I49="PE-controlled Growth Mandate",I49="Listed with Growth Profile"),8,IF(OR(I49="Series A",I49="Bootstrapped Profitable",I49="PE-controlled Stable",AND(OR(I49="Series B",I49="Series C",I49="Series D+"),J49<>"",J49<TODAY()-730)),6,IF(OR(I49="Seed",I49="Bootstrapped",I49="Listed Stable",I49="Established Private Flat"),3,0))))) -> 6 | AA49: =IF(N49="Yes",0,IF(A49="",0,IF(COUNTIFS('04_Triggers'!B:B,A49,'04_Triggers'!D:D,">="&(TODAY()-365))>=2,20,IF(COUNTIFS('04_Triggers'!B:B,A49,'04_Triggers'!D:D,">="&(TODAY()-365),'04_Triggers'!G:G,"High")>=1,14,IF(COUNTIFS('04_Triggers'!B:B,A49,'04_Triggers'!D:D,">="&(TODAY()-365))>=1,7,IF(COUNTIFS('04_Triggers'!B:B,A49,'04_Triggers'!D:D,">="&(TODAY()-1095),'04_Triggers'!D:D,"<"&(TODAY()-365))>=1,7,0)))))) -> 0 | AB49: =IF(M49="","",IFERROR(VLOOKUP(M49,Scoring_Lookups!$J$5:$K$16,2,FALSE()),0)) -> 0 | AC49: =IF(O49="","",IFERROR(VLOOKUP(O49,Scoring_Lookups!$M$5:$N$8,2,FALSE()),0)) -> 6 | AD49: =IF(L49="","",IFERROR(VLOOKUP(L49,Scoring_Lookups!$P$5:$Q$9,2,FALSE()),0)) -> 3 | AE49: =IF(AND(P49="",Q49="",R49=""),"",IF(OR(IFERROR(MAX(P49,Q49),0)>=500000,R49="Yes"),10,IF(IFERROR(MAX(P49,Q49),0)>=100000,7,IF(IFERROR(MAX(P49,Q49),0)>=10000,4,0)))) -> 0 | AF49: =IFERROR(N(V49)+N(W49)+N(X49)+N(Y49)+N(Z49)+N(AA49)+N(AB49)+N(AC49)+N(AD49)+N(AE49),0) -> 44 | AG49: =IF(OR(E49="",C49="",G49=""),"Not scored",IF(OR(V49=0,X49=0,Y49=0,N49="Yes"),"DQ Gating","OK")) -> OK | AH49: No | AI49: =IF(AG49="Not scored","",IF(OR(AG49="DQ Gating",AH49="Yes"),"Disqualified",IF(AF49>=80,"Priority 1",IF(AF49>=60,"Priority 2",IF(AF49>=40,"Priority 3","Disqualified"))))) -> Priority 3 | AJ49: =IF(AG49="Not scored","","P1 "&IF(E49="","?",E49)&"="&V49&" | P2 "&IF(F49="","?",F49)&"="&W49&" | P3 "&IF(C49="","?",C49)&"="&X49&" | P4 "&IF(G49="","?",G49)&"="&Y49&" | P5 "&IF(I49="","?",I49)&"="&Z49&" | P6="&AA49&" | P7 "&IF(M49="","?",M49)&"="&AB49&" | P8 "&IF(O49="","?",O49)&"="&AC49&" | P9 "&IF(L49="","?",L49)&"="&AD49&" | P10="&AE49) -> P1 Investment Management=4 | P2 25=7 | P3 Czech Republic=12 | P4 PI Licence=6 | P5 Series A=6 | P6=0 | P7 No Card Program, No Plan=0 | P8 Cloud-native (AWS/Azure/GCP), API-first, AI signals=6 | P9 No Sponsor, Licensing Suggests Imminent=3 | P10=0 | AL49: Prospect | AM49: No | AO49: Unknown / TBD | AP49: =IF(AO49="","Not set",IF(OR(AO49="Q1 2027",AO49="Q2 2027",AO49="Q3 2027",AO49="Q4 2027",AO49="Live, Migration Window"),"OK",IF(AO49="Live, Urgent Need","Deferred","Watch"))) -> Watch | AQ49: Consumer
A50: ACC-RO-001 | B50: Salt Bank | C50: Romania | D50: Banking | E50: Digital Banking | F50: 300 | G50: Credit Institution Licence | H50: PE-controlled | I50: PE-controlled Stable | K50: None (direct scheme) | L50: Scheme Principal | M50: Smaller/Less-known Processor | N50: No | O50: Cloud-native (AWS/Azure/GCP), API-first, AI signals | P50: 200000 | Q50: 500000 | R50: Yes | S50: Romania discovery | T50: 46216 | U50: Banca Transilvania subsidiary; 200k+ customers first month; on track to 1M in 3 years; Best Digital Bank FinTech Breakthrough Awards; multicurrency Platinum Debit MC 17 currencies; Engine by Starling core + GFT + AWS; verify BT centralisation risk on processor decisions | V50: =IF(E50="","",IFERROR(VLOOKUP(E50,Scoring_Lookups!$A$5:$B$18,2,FALSE()),0)) -> 10 | W50: =IF(F50="","",IF(AND(F50>=50,F50<=1000),10,IF(OR(AND(F50>=20,F50<=49),AND(F50>=1001,F50<=2000)),7,IF(OR(AND(F50>=10,F50<=19),AND(F50>=2001,F50<=5000)),4,0)))) -> 10 | X50: =IF(C50="","",IFERROR(VLOOKUP(C50,Scoring_Lookups!$D$5:$E$35,2,FALSE()),0)) -> 12 | Y50: =IF(G50="","",IFERROR(VLOOKUP(G50,Scoring_Lookups!$G$5:$H$16,2,FALSE()),0)) -> 8 | Z50: =IF(I50="","",IF(OR(I50="Administration/Insolvency",I50="Pending Wind-down",I50="Sanctions Exposure"),0,IF(OR(AND(OR(I50="Series B",I50="Series C",I50="Series D+"),J50<>"",J50>=TODAY()-730),I50="PE-controlled Growth Mandate",I50="Listed with Growth Profile"),8,IF(OR(I50="Series A",I50="Bootstrapped Profitable",I50="PE-controlled Stable",AND(OR(I50="Series B",I50="Series C",I50="Series D+"),J50<>"",J50<TODAY()-730)),6,IF(OR(I50="Seed",I50="Bootstrapped",I50="Listed Stable",I50="Established Private Flat"),3,0))))) -> 6 | AA50: =IF(N50="Yes",0,IF(A50="",0,IF(COUNTIFS('04_Triggers'!B:B,A50,'04_Triggers'!D:D,">="&(TODAY()-365))>=2,20,IF(COUNTIFS('04_Triggers'!B:B,A50,'04_Triggers'!D:D,">="&(TODAY()-365),'04_Triggers'!G:G,"High")>=1,14,IF(COUNTIFS('04_Triggers'!B:B,A50,'04_Triggers'!D:D,">="&(TODAY()-365))>=1,7,IF(COUNTIFS('04_Triggers'!B:B,A50,'04_Triggers'!D:D,">="&(TODAY()-1095),'04_Triggers'!D:D,"<"&(TODAY()-365))>=1,7,0)))))) -> 7 | AB50: =IF(M50="","",IFERROR(VLOOKUP(M50,Scoring_Lookups!$J$5:$K$16,2,FALSE()),0)) -> 6 | AC50: =IF(O50="","",IFERROR(VLOOKUP(O50,Scoring_Lookups!$M$5:$N$8,2,FALSE()),0)) -> 6 | AD50: =IF(L50="","",IFERROR(VLOOKUP(L50,Scoring_Lookups!$P$5:$Q$9,2,FALSE()),0)) -> 8 | AE50: =IF(AND(P50="",Q50="",R50=""),"",IF(OR(IFERROR(MAX(P50,Q50),0)>=500000,R50="Yes"),10,IF(IFERROR(MAX(P50,Q50),0)>=100000,7,IF(IFERROR(MAX(P50,Q50),0)>=10000,4,0)))) -> 10 | AF50: =IFERROR(N(V50)+N(W50)+N(X50)+N(Y50)+N(Z50)+N(AA50)+N(AB50)+N(AC50)+N(AD50)+N(AE50),0) -> 83 | AG50: =IF(OR(E50="",C50="",G50=""),"Not scored",IF(OR(V50=0,X50=0,Y50=0,N50="Yes"),"DQ Gating","OK")) -> OK | AH50: No | AI50: =IF(AG50="Not scored","",IF(OR(AG50="DQ Gating",AH50="Yes"),"Disqualified",IF(AF50>=80,"Priority 1",IF(AF50>=60,"Priority 2",IF(AF50>=40,"Priority 3","Disqualified"))))) -> Priority 1 | AJ50: =IF(AG50="Not scored","","P1 "&IF(E50="","?",E50)&"="&V50&" | P2 "&IF(F50="","?",F50)&"="&W50&" | P3 "&IF(C50="","?",C50)&"="&X50&" | P4 "&IF(G50="","?",G50)&"="&Y50&" | P5 "&IF(I50="","?",I50)&"="&Z50&" | P6="&AA50&" | P7 "&IF(M50="","?",M50)&"="&AB50&" | P8 "&IF(O50="","?",O50)&"="&AC50&" | P9 "&IF(L50="","?",L50)&"="&AD50&" | P10="&AE50) -> P1 Digital Banking=10 | P2 300=10 | P3 Romania=12 | P4 Credit Institution Licence=8 | P5 PE-controlled Stable=6 | P6=7 | P7 Smaller/Less-known Processor=6 | P8 Cloud-native (AWS/Azure/GCP), API-first, AI signals=6 | P9 Scheme Principal=8 | P10=10 | AL50: Prospect | AM50: No | AO50: Live, Migration Window | AP50: =IF(AO50="","Not set",IF(OR(AO50="Q1 2027",AO50="Q2 2027",AO50="Q3 2027",AO50="Q4 2027",AO50="Live, Migration Window"),"OK",IF(AO50="Live, Urgent Need","Deferred","Watch"))) -> OK | AQ50: Consumer
A51: ACC-RO-002 | B51: HeyBlu Financial Services | C51: Romania | D51: FinTech | E51: Lending (Consumer) | F51: 100 | G51: EMI Licence | H51: PE-controlled | I51: PE-controlled Stable | K51: TBD | L51: Existing BIN Sponsor Relationship | M51: Incumbent Unknown | N51: No | O51: Cloud-native (AWS/Azure/GCP), API-first, AI signals | P51: 500000 | Q51: 1000000 | R51: Yes | S51: Romania discovery | T51: 46216 | U51: Jan 2025 acquisition of Orange Money IFN 100% shares from Orange Romania; eMAG My Wallet powers 2.5M eMAG customers; installment products; PayU/Naspers JV heritage | V51: =IF(E51="","",IFERROR(VLOOKUP(E51,Scoring_Lookups!$A$5:$B$18,2,FALSE()),0)) -> 7 | W51: =IF(F51="","",IF(AND(F51>=50,F51<=1000),10,IF(OR(AND(F51>=20,F51<=49),AND(F51>=1001,F51<=2000)),7,IF(OR(AND(F51>=10,F51<=19),AND(F51>=2001,F51<=5000)),4,0)))) -> 10 | X51: =IF(C51="","",IFERROR(VLOOKUP(C51,Scoring_Lookups!$D$5:$E$35,2,FALSE()),0)) -> 12 | Y51: =IF(G51="","",IFERROR(VLOOKUP(G51,Scoring_Lookups!$G$5:$H$16,2,FALSE()),0)) -> 8 | Z51: =IF(I51="","",IF(OR(I51="Administration/Insolvency",I51="Pending Wind-down",I51="Sanctions Exposure"),0,IF(OR(AND(OR(I51="Series B",I51="Series C",I51="Series D+"),J51<>"",J51>=TODAY()-730),I51="PE-controlled Growth Mandate",I51="Listed with Growth Profile"),8,IF(OR(I51="Series A",I51="Bootstrapped Profitable",I51="PE-controlled Stable",AND(OR(I51="Series B",I51="Series C",I51="Series D+"),J51<>"",J51<TODAY()-730)),6,IF(OR(I51="Seed",I51="Bootstrapped",I51="Listed Stable",I51="Established Private Flat"),3,0))))) -> 6 | AA51: =IF(N51="Yes",0,IF(A51="",0,IF(COUNTIFS('04_Triggers'!B:B,A51,'04_Triggers'!D:D,">="&(TODAY()-365))>=2,20,IF(COUNTIFS('04_Triggers'!B:B,A51,'04_Triggers'!D:D,">="&(TODAY()-365),'04_Triggers'!G:G,"High")>=1,14,IF(COUNTIFS('04_Triggers'!B:B,A51,'04_Triggers'!D:D,">="&(TODAY()-365))>=1,7,IF(COUNTIFS('04_Triggers'!B:B,A51,'04_Triggers'!D:D,">="&(TODAY()-1095),'04_Triggers'!D:D,"<"&(TODAY()-365))>=1,7,0)))))) -> 7 | AB51: =IF(M51="","",IFERROR(VLOOKUP(M51,Scoring_Lookups!$J$5:$K$16,2,FALSE()),0)) -> 3 | AC51: =IF(O51="","",IFERROR(VLOOKUP(O51,Scoring_Lookups!$M$5:$N$8,2,FALSE()),0)) -> 6 | AD51: =IF(L51="","",IFERROR(VLOOKUP(L51,Scoring_Lookups!$P$5:$Q$9,2,FALSE()),0)) -> 8 | AE51: =IF(AND(P51="",Q51="",R51=""),"",IF(OR(IFERROR(MAX(P51,Q51),0)>=500000,R51="Yes"),10,IF(IFERROR(MAX(P51,Q51),0)>=100000,7,IF(IFERROR(MAX(P51,Q51),0)>=10000,4,0)))) -> 10 | AF51: =IFERROR(N(V51)+N(W51)+N(X51)+N(Y51)+N(Z51)+N(AA51)+N(AB51)+N(AC51)+N(AD51)+N(AE51),0) -> 77 | AG51: =IF(OR(E51="",C51="",G51=""),"Not scored",IF(OR(V51=0,X51=0,Y51=0,N51="Yes"),"DQ Gating","OK")) -> OK | AH51: No | AI51: =IF(AG51="Not scored","",IF(OR(AG51="DQ Gating",AH51="Yes"),"Disqualified",IF(AF51>=80,"Priority 1",IF(AF51>=60,"Priority 2",IF(AF51>=40,"Priority 3","Disqualified"))))) -> Priority 2 | AJ51: =IF(AG51="Not scored","","P1 "&IF(E51="","?",E51)&"="&V51&" | P2 "&IF(F51="","?",F51)&"="&W51&" | P3 "&IF(C51="","?",C51)&"="&X51&" | P4 "&IF(G51="","?",G51)&"="&Y51&" | P5 "&IF(I51="","?",I51)&"="&Z51&" | P6="&AA51&" | P7 "&IF(M51="","?",M51)&"="&AB51&" | P8 "&IF(O51="","?",O51)&"="&AC51&" | P9 "&IF(L51="","?",L51)&"="&AD51&" | P10="&AE51) -> P1 Lending (Consumer)=7 | P2 100=10 | P3 Romania=12 | P4 EMI Licence=8 | P5 PE-controlled Stable=6 | P6=7 | P7 Incumbent Unknown=3 | P8 Cloud-native (AWS/Azure/GCP), API-first, AI signals=6 | P9 Existing BIN Sponsor Relationship=8 | P10=10 | AL51: Prospect | AM51: No | AO51: Live, Migration Window | AP51: =IF(AO51="","Not set",IF(OR(AO51="Q1 2027",AO51="Q2 2027",AO51="Q3 2027",AO51="Q4 2027",AO51="Live, Migration Window"),"OK",IF(AO51="Live, Urgent Need","Deferred","Watch"))) -> OK | AQ51: Consumer
A52: ACC-RO-003 | B52: xMoney (ex-Twispay) | C52: Romania | D52: FinTech | E52: Crypto | F52: 50 | G52: EMI Licence | H52: PE-controlled | I52: PE-controlled Stable | K52: None (own scheme membership) | L52: Scheme Principal | M52: In-house Legacy Processor | N52: No | O52: Cloud-native (AWS/Azure/GCP), API-first, AI signals | P52: 30000 | Q52: 100000 | R52: Yes | S52: Romania discovery | T52: 46216 | U52: Rebrand from Twispay to xMoney 2025; Jun 2026 stablecoin launch (EURXM, USDXM, RONXM); Visa+MC principal member; MultiversX parent restructuring risk - verify entity health separately before outreach | V52: =IF(E52="","",IFERROR(VLOOKUP(E52,Scoring_Lookups!$A$5:$B$18,2,FALSE()),0)) -> 4 | W52: =IF(F52="","",IF(AND(F52>=50,F52<=1000),10,IF(OR(AND(F52>=20,F52<=49),AND(F52>=1001,F52<=2000)),7,IF(OR(AND(F52>=10,F52<=19),AND(F52>=2001,F52<=5000)),4,0)))) -> 10 | X52: =IF(C52="","",IFERROR(VLOOKUP(C52,Scoring_Lookups!$D$5:$E$35,2,FALSE()),0)) -> 12 | Y52: =IF(G52="","",IFERROR(VLOOKUP(G52,Scoring_Lookups!$G$5:$H$16,2,FALSE()),0)) -> 8 | Z52: =IF(I52="","",IF(OR(I52="Administration/Insolvency",I52="Pending Wind-down",I52="Sanctions Exposure"),0,IF(OR(AND(OR(I52="Series B",I52="Series C",I52="Series D+"),J52<>"",J52>=TODAY()-730),I52="PE-controlled Growth Mandate",I52="Listed with Growth Profile"),8,IF(OR(I52="Series A",I52="Bootstrapped Profitable",I52="PE-controlled Stable",AND(OR(I52="Series B",I52="Series C",I52="Series D+"),J52<>"",J52<TODAY()-730)),6,IF(OR(I52="Seed",I52="Bootstrapped",I52="Listed Stable",I52="Established Private Flat"),3,0))))) -> 6 | AA52: =IF(N52="Yes",0,IF(A52="",0,IF(COUNTIFS('04_Triggers'!B:B,A52,'04_Triggers'!D:D,">="&(TODAY()-365))>=2,20,IF(COUNTIFS('04_Triggers'!B:B,A52,'04_Triggers'!D:D,">="&(TODAY()-365),'04_Triggers'!G:G,"High")>=1,14,IF(COUNTIFS('04_Triggers'!B:B,A52,'04_Triggers'!D:D,">="&(TODAY()-365))>=1,7,IF(COUNTIFS('04_Triggers'!B:B,A52,'04_Triggers'!D:D,">="&(TODAY()-1095),'04_Triggers'!D:D,"<"&(TODAY()-365))>=1,7,0)))))) -> 14 | AB52: =IF(M52="","",IFERROR(VLOOKUP(M52,Scoring_Lookups!$J$5:$K$16,2,FALSE()),0)) -> 8 | AC52: =IF(O52="","",IFERROR(VLOOKUP(O52,Scoring_Lookups!$M$5:$N$8,2,FALSE()),0)) -> 6 | AD52: =IF(L52="","",IFERROR(VLOOKUP(L52,Scoring_Lookups!$P$5:$Q$9,2,FALSE()),0)) -> 8 | AE52: =IF(AND(P52="",Q52="",R52=""),"",IF(OR(IFERROR(MAX(P52,Q52),0)>=500000,R52="Yes"),10,IF(IFERROR(MAX(P52,Q52),0)>=100000,7,IF(IFERROR(MAX(P52,Q52),0)>=10000,4,0)))) -> 10 | AF52: =IFERROR(N(V52)+N(W52)+N(X52)+N(Y52)+N(Z52)+N(AA52)+N(AB52)+N(AC52)+N(AD52)+N(AE52),0) -> 86 | AG52: =IF(OR(E52="",C52="",G52=""),"Not scored",IF(OR(V52=0,X52=0,Y52=0,N52="Yes"),"DQ Gating","OK")) -> OK | AH52: No | AI52: =IF(AG52="Not scored","",IF(OR(AG52="DQ Gating",AH52="Yes"),"Disqualified",IF(AF52>=80,"Priority 1",IF(AF52>=60,"Priority 2",IF(AF52>=40,"Priority 3","Disqualified"))))) -> Priority 1 | AJ52: =IF(AG52="Not scored","","P1 "&IF(E52="","?",E52)&"="&V52&" | P2 "&IF(F52="","?",F52)&"="&W52&" | P3 "&IF(C52="","?",C52)&"="&X52&" | P4 "&IF(G52="","?",G52)&"="&Y52&" | P5 "&IF(I52="","?",I52)&"="&Z52&" | P6="&AA52&" | P7 "&IF(M52="","?",M52)&"="&AB52&" | P8 "&IF(O52="","?",O52)&"="&AC52&" | P9 "&IF(L52="","?",L52)&"="&AD52&" | P10="&AE52) -> P1 Crypto=4 | P2 50=10 | P3 Romania=12 | P4 EMI Licence=8 | P5 PE-controlled Stable=6 | P6=14 | P7 In-house Legacy Processor=8 | P8 Cloud-native (AWS/Azure/GCP), API-first, AI signals=6 | P9 Scheme Principal=8 | P10=10 | AL52: Prospect | AM52: No | AO52: Live, Migration Window | AP52: =IF(AO52="","Not set",IF(OR(AO52="Q1 2027",AO52="Q2 2027",AO52="Q3 2027",AO52="Q4 2027",AO52="Live, Migration Window"),"OK",IF(AO52="Live, Urgent Need","Deferred","Watch"))) -> OK | AQ52: Consumer
A53: ACC-RO-004 | B53: NETOPIA Payments | C53: Romania | D53: FinTech | E53: Payments | F53: 35 | G53: EMI Licence In Application | H53: Private | I53: Bootstrapped Profitable | K53: TBD | L53: Scheme Participation Visible | M53: Planning to Launch (No Incumbent Yet) | N53: No | O53: Cloud modern, Not API-first | P53: 0 | Q53: 100000 | R53: Yes | S53: Romania discovery | T53: 46216 | U53: Largest RO PSP (~30% online card volume; EUR 2B annually; 25000+ merchants); Jun 2026 new CEO Raluca Micu ex-BNR; PI licence advancing | V53: =IF(E53="","",IFERROR(VLOOKUP(E53,Scoring_Lookups!$A$5:$B$18,2,FALSE()),0)) -> 4 | W53: =IF(F53="","",IF(AND(F53>=50,F53<=1000),10,IF(OR(AND(F53>=20,F53<=49),AND(F53>=1001,F53<=2000)),7,IF(OR(AND(F53>=10,F53<=19),AND(F53>=2001,F53<=5000)),4,0)))) -> 7 | X53: =IF(C53="","",IFERROR(VLOOKUP(C53,Scoring_Lookups!$D$5:$E$35,2,FALSE()),0)) -> 12 | Y53: =IF(G53="","",IFERROR(VLOOKUP(G53,Scoring_Lookups!$G$5:$H$16,2,FALSE()),0)) -> 6 | Z53: =IF(I53="","",IF(OR(I53="Administration/Insolvency",I53="Pending Wind-down",I53="Sanctions Exposure"),0,IF(OR(AND(OR(I53="Series B",I53="Series C",I53="Series D+"),J53<>"",J53>=TODAY()-730),I53="PE-controlled Growth Mandate",I53="Listed with Growth Profile"),8,IF(OR(I53="Series A",I53="Bootstrapped Profitable",I53="PE-controlled Stable",AND(OR(I53="Series B",I53="Series C",I53="Series D+"),J53<>"",J53<TODAY()-730)),6,IF(OR(I53="Seed",I53="Bootstrapped",I53="Listed Stable",I53="Established Private Flat"),3,0))))) -> 6 | AA53: =IF(N53="Yes",0,IF(A53="",0,IF(COUNTIFS('04_Triggers'!B:B,A53,'04_Triggers'!D:D,">="&(TODAY()-365))>=2,20,IF(COUNTIFS('04_Triggers'!B:B,A53,'04_Triggers'!D:D,">="&(TODAY()-365),'04_Triggers'!G:G,"High")>=1,14,IF(COUNTIFS('04_Triggers'!B:B,A53,'04_Triggers'!D:D,">="&(TODAY()-365))>=1,7,IF(COUNTIFS('04_Triggers'!B:B,A53,'04_Triggers'!D:D,">="&(TODAY()-1095),'04_Triggers'!D:D,"<"&(TODAY()-365))>=1,7,0)))))) -> 14 | AB53: =IF(M53="","",IFERROR(VLOOKUP(M53,Scoring_Lookups!$J$5:$K$16,2,FALSE()),0)) -> 4 | AC53: =IF(O53="","",IFERROR(VLOOKUP(O53,Scoring_Lookups!$M$5:$N$8,2,FALSE()),0)) -> 4 | AD53: =IF(L53="","",IFERROR(VLOOKUP(L53,Scoring_Lookups!$P$5:$Q$9,2,FALSE()),0)) -> 6 | AE53: =IF(AND(P53="",Q53="",R53=""),"",IF(OR(IFERROR(MAX(P53,Q53),0)>=500000,R53="Yes"),10,IF(IFERROR(MAX(P53,Q53),0)>=100000,7,IF(IFERROR(MAX(P53,Q53),0)>=10000,4,0)))) -> 10 | AF53: =IFERROR(N(V53)+N(W53)+N(X53)+N(Y53)+N(Z53)+N(AA53)+N(AB53)+N(AC53)+N(AD53)+N(AE53),0) -> 73 | AG53: =IF(OR(E53="",C53="",G53=""),"Not scored",IF(OR(V53=0,X53=0,Y53=0,N53="Yes"),"DQ Gating","OK")) -> OK | AH53: No | AI53: =IF(AG53="Not scored","",IF(OR(AG53="DQ Gating",AH53="Yes"),"Disqualified",IF(AF53>=80,"Priority 1",IF(AF53>=60,"Priority 2",IF(AF53>=40,"Priority 3","Disqualified"))))) -> Priority 2 | AJ53: =IF(AG53="Not scored","","P1 "&IF(E53="","?",E53)&"="&V53&" | P2 "&IF(F53="","?",F53)&"="&W53&" | P3 "&IF(C53="","?",C53)&"="&X53&" | P4 "&IF(G53="","?",G53)&"="&Y53&" | P5 "&IF(I53="","?",I53)&"="&Z53&" | P6="&AA53&" | P7 "&IF(M53="","?",M53)&"="&AB53&" | P8 "&IF(O53="","?",O53)&"="&AC53&" | P9 "&IF(L53="","?",L53)&"="&AD53&" | P10="&AE53) -> P1 Payments=4 | P2 35=7 | P3 Romania=12 | P4 EMI Licence In Application=6 | P5 Bootstrapped Profitable=6 | P6=14 | P7 Planning to Launch (No Incumbent Yet)=4 | P8 Cloud modern, Not API-first=4 | P9 Scheme Participation Visible=6 | P10=10 | AL53: Prospect | AM53: No | AO53: Q4 2027 | AP53: =IF(AO53="","Not set",IF(OR(AO53="Q1 2027",AO53="Q2 2027",AO53="Q3 2027",AO53="Q4 2027",AO53="Live, Migration Window"),"OK",IF(AO53="Live, Urgent Need","Deferred","Watch"))) -> OK | AQ53: Commercial and B2B
A54: ACC-RO-005 | B54: Pago | C54: Romania | D54: FinTech | E54: Payments | F54: 55 | G54: PI Licence | H54: VC-backed | I54: Series A | J54: 45580 | K54: TBD | L54: No Sponsor, Licensing Suggests Imminent | M54: Planning to Launch (No Incumbent Yet) | N54: No | O54: Cloud-native (AWS/Azure/GCP), API-first, AI signals | P54: 0 | Q54: 100000 | R54: Yes | S54: Romania discovery | T54: 46216 | U54: Oct 2024 EUR 2.3M SeedBlink round (largest on platform, Mozaik Investments co-invest); 550k MAUs across 3 markets; targeting 6M RO users; expansion to Italy/Poland/Czech Republic | V54: =IF(E54="","",IFERROR(VLOOKUP(E54,Scoring_Lookups!$A$5:$B$18,2,FALSE()),0)) -> 4 | W54: =IF(F54="","",IF(AND(F54>=50,F54<=1000),10,IF(OR(AND(F54>=20,F54<=49),AND(F54>=1001,F54<=2000)),7,IF(OR(AND(F54>=10,F54<=19),AND(F54>=2001,F54<=5000)),4,0)))) -> 10 | X54: =IF(C54="","",IFERROR(VLOOKUP(C54,Scoring_Lookups!$D$5:$E$35,2,FALSE()),0)) -> 12 | Y54: =IF(G54="","",IFERROR(VLOOKUP(G54,Scoring_Lookups!$G$5:$H$16,2,FALSE()),0)) -> 6 | Z54: =IF(I54="","",IF(OR(I54="Administration/Insolvency",I54="Pending Wind-down",I54="Sanctions Exposure"),0,IF(OR(AND(OR(I54="Series B",I54="Series C",I54="Series D+"),J54<>"",J54>=TODAY()-730),I54="PE-controlled Growth Mandate",I54="Listed with Growth Profile"),8,IF(OR(I54="Series A",I54="Bootstrapped Profitable",I54="PE-controlled Stable",AND(OR(I54="Series B",I54="Series C",I54="Series D+"),J54<>"",J54<TODAY()-730)),6,IF(OR(I54="Seed",I54="Bootstrapped",I54="Listed Stable",I54="Established Private Flat"),3,0))))) -> 6 | AA54: =IF(N54="Yes",0,IF(A54="",0,IF(COUNTIFS('04_Triggers'!B:B,A54,'04_Triggers'!D:D,">="&(TODAY()-365))>=2,20,IF(COUNTIFS('04_Triggers'!B:B,A54,'04_Triggers'!D:D,">="&(TODAY()-365),'04_Triggers'!G:G,"High")>=1,14,IF(COUNTIFS('04_Triggers'!B:B,A54,'04_Triggers'!D:D,">="&(TODAY()-365))>=1,7,IF(COUNTIFS('04_Triggers'!B:B,A54,'04_Triggers'!D:D,">="&(TODAY()-1095),'04_Triggers'!D:D,"<"&(TODAY()-365))>=1,7,0)))))) -> 7 | AB54: =IF(M54="","",IFERROR(VLOOKUP(M54,Scoring_Lookups!$J$5:$K$16,2,FALSE()),0)) -> 4 | AC54: =IF(O54="","",IFERROR(VLOOKUP(O54,Scoring_Lookups!$M$5:$N$8,2,FALSE()),0)) -> 6 | AD54: =IF(L54="","",IFERROR(VLOOKUP(L54,Scoring_Lookups!$P$5:$Q$9,2,FALSE()),0)) -> 3 | AE54: =IF(AND(P54="",Q54="",R54=""),"",IF(OR(IFERROR(MAX(P54,Q54),0)>=500000,R54="Yes"),10,IF(IFERROR(MAX(P54,Q54),0)>=100000,7,IF(IFERROR(MAX(P54,Q54),0)>=10000,4,0)))) -> 10 | AF54: =IFERROR(N(V54)+N(W54)+N(X54)+N(Y54)+N(Z54)+N(AA54)+N(AB54)+N(AC54)+N(AD54)+N(AE54),0) -> 68 | AG54: =IF(OR(E54="",C54="",G54=""),"Not scored",IF(OR(V54=0,X54=0,Y54=0,N54="Yes"),"DQ Gating","OK")) -> OK | AH54: No | AI54: =IF(AG54="Not scored","",IF(OR(AG54="DQ Gating",AH54="Yes"),"Disqualified",IF(AF54>=80,"Priority 1",IF(AF54>=60,"Priority 2",IF(AF54>=40,"Priority 3","Disqualified"))))) -> Priority 2 | AJ54: =IF(AG54="Not scored","","P1 "&IF(E54="","?",E54)&"="&V54&" | P2 "&IF(F54="","?",F54)&"="&W54&" | P3 "&IF(C54="","?",C54)&"="&X54&" | P4 "&IF(G54="","?",G54)&"="&Y54&" | P5 "&IF(I54="","?",I54)&"="&Z54&" | P6="&AA54&" | P7 "&IF(M54="","?",M54)&"="&AB54&" | P8 "&IF(O54="","?",O54)&"="&AC54&" | P9 "&IF(L54="","?",L54)&"="&AD54&" | P10="&AE54) -> P1 Payments=4 | P2 55=10 | P3 Romania=12 | P4 PI Licence=6 | P5 Series A=6 | P6=7 | P7 Planning to Launch (No Incumbent Yet)=4 | P8 Cloud-native (AWS/Azure/GCP), API-first, AI signals=6 | P9 No Sponsor, Licensing Suggests Imminent=3 | P10=10 | AL54: Prospect | AM54: No | AO54: Q3 2027 | AP54: =IF(AO54="","Not set",IF(OR(AO54="Q1 2027",AO54="Q2 2027",AO54="Q3 2027",AO54="Q4 2027",AO54="Live, Migration Window"),"OK",IF(AO54="Live, Urgent Need","Deferred","Watch"))) -> OK | AQ54: Consumer
A55: ACC-RO-006 | B55: Libra Internet Bank | C55: Romania | D55: Banking | E55: Digital Banking | F55: 1250 | G55: Credit Institution Licence | H55: Private | I55: Bootstrapped Profitable | K55: None (direct scheme) | L55: Scheme Principal | M55: In-house Legacy Processor | N55: No | O55: Cloud modern, Not API-first | P55: 500000 | Q55: 700000 | R55: Yes | S55: Romania discovery | T55: 46216 | U55: First RO bank in Mastercard Digital First Card programme; fintech partner bank offering technical accounts + IBANs to EU fintech partners; 2026 revenue $155.7M | V55: =IF(E55="","",IFERROR(VLOOKUP(E55,Scoring_Lookups!$A$5:$B$18,2,FALSE()),0)) -> 10 | W55: =IF(F55="","",IF(AND(F55>=50,F55<=1000),10,IF(OR(AND(F55>=20,F55<=49),AND(F55>=1001,F55<=2000)),7,IF(OR(AND(F55>=10,F55<=19),AND(F55>=2001,F55<=5000)),4,0)))) -> 7 | X55: =IF(C55="","",IFERROR(VLOOKUP(C55,Scoring_Lookups!$D$5:$E$35,2,FALSE()),0)) -> 12 | Y55: =IF(G55="","",IFERROR(VLOOKUP(G55,Scoring_Lookups!$G$5:$H$16,2,FALSE()),0)) -> 8 | Z55: =IF(I55="","",IF(OR(I55="Administration/Insolvency",I55="Pending Wind-down",I55="Sanctions Exposure"),0,IF(OR(AND(OR(I55="Series B",I55="Series C",I55="Series D+"),J55<>"",J55>=TODAY()-730),I55="PE-controlled Growth Mandate",I55="Listed with Growth Profile"),8,IF(OR(I55="Series A",I55="Bootstrapped Profitable",I55="PE-controlled Stable",AND(OR(I55="Series B",I55="Series C",I55="Series D+"),J55<>"",J55<TODAY()-730)),6,IF(OR(I55="Seed",I55="Bootstrapped",I55="Listed Stable",I55="Established Private Flat"),3,0))))) -> 6 | AA55: =IF(N55="Yes",0,IF(A55="",0,IF(COUNTIFS('04_Triggers'!B:B,A55,'04_Triggers'!D:D,">="&(TODAY()-365))>=2,20,IF(COUNTIFS('04_Triggers'!B:B,A55,'04_Triggers'!D:D,">="&(TODAY()-365),'04_Triggers'!G:G,"High")>=1,14,IF(COUNTIFS('04_Triggers'!B:B,A55,'04_Triggers'!D:D,">="&(TODAY()-365))>=1,7,IF(COUNTIFS('04_Triggers'!B:B,A55,'04_Triggers'!D:D,">="&(TODAY()-1095),'04_Triggers'!D:D,"<"&(TODAY()-365))>=1,7,0)))))) -> 7 | AB55: =IF(M55="","",IFERROR(VLOOKUP(M55,Scoring_Lookups!$J$5:$K$16,2,FALSE()),0)) -> 8 | AC55: =IF(O55="","",IFERROR(VLOOKUP(O55,Scoring_Lookups!$M$5:$N$8,2,FALSE()),0)) -> 4 | AD55: =IF(L55="","",IFERROR(VLOOKUP(L55,Scoring_Lookups!$P$5:$Q$9,2,FALSE()),0)) -> 8 | AE55: =IF(AND(P55="",Q55="",R55=""),"",IF(OR(IFERROR(MAX(P55,Q55),0)>=500000,R55="Yes"),10,IF(IFERROR(MAX(P55,Q55),0)>=100000,7,IF(IFERROR(MAX(P55,Q55),0)>=10000,4,0)))) -> 10 | AF55: =IFERROR(N(V55)+N(W55)+N(X55)+N(Y55)+N(Z55)+N(AA55)+N(AB55)+N(AC55)+N(AD55)+N(AE55),0) -> 80 | AG55: =IF(OR(E55="",C55="",G55=""),"Not scored",IF(OR(V55=0,X55=0,Y55=0,N55="Yes"),"DQ Gating","OK")) -> OK | AH55: No | AI55: =IF(AG55="Not scored","",IF(OR(AG55="DQ Gating",AH55="Yes"),"Disqualified",IF(AF55>=80,"Priority 1",IF(AF55>=60,"Priority 2",IF(AF55>=40,"Priority 3","Disqualified"))))) -> Priority 1 | AJ55: =IF(AG55="Not scored","","P1 "&IF(E55="","?",E55)&"="&V55&" | P2 "&IF(F55="","?",F55)&"="&W55&" | P3 "&IF(C55="","?",C55)&"="&X55&" | P4 "&IF(G55="","?",G55)&"="&Y55&" | P5 "&IF(I55="","?",I55)&"="&Z55&" | P6="&AA55&" | P7 "&IF(M55="","?",M55)&"="&AB55&" | P8 "&IF(O55="","?",O55)&"="&AC55&" | P9 "&IF(L55="","?",L55)&"="&AD55&" | P10="&AE55) -> P1 Digital Banking=10 | P2 1250=7 | P3 Romania=12 | P4 Credit Institution Licence=8 | P5 Bootstrapped Profitable=6 | P6=7 | P7 In-house Legacy Processor=8 | P8 Cloud modern, Not API-first=4 | P9 Scheme Principal=8 | P10=10 | AL55: Prospect | AM55: No | AO55: Live, Migration Window | AP55: =IF(AO55="","Not set",IF(OR(AO55="Q1 2027",AO55="Q2 2027",AO55="Q3 2027",AO55="Q4 2027",AO55="Live, Migration Window"),"OK",IF(AO55="Live, Urgent Need","Deferred","Watch"))) -> OK | AQ55: Consumer
